Workbook

Sheet YEARLY DASHBOARD
J2: ANNUAL INCOME | M2: ANNUAL BILLS | P2: ANNUAL EXPENSES | S2: ANNUAL DEBTS | V2: ANNUAL SAVINGS
J4: =SUM(C6:C17) -> 0 | M4: =SUM(D6:D17) -> 0 | P4: =SUM(E6:E17) -> 0 | S4: =SUM(F6:F17) -> 0 | V4: =SUM(G6:G17) -> 0
B5: Month | C5: Income | D5: Bills | E5: Expenses | F5: Debts | G5: Savings | H5: Total Expenditure
B6: January | C6: =SUM(JAN!$D$23:$D$38) -> 0 | D6: =SUM(JAN!$H$23:$H$38) -> 0 | E6: =SUM(JAN!$M$23:$M$38) -> 0 | F6: =SUM(JAN!$R$23:$R$38) -> 0 | G6: =SUM(JAN!$W$23:$W$38) -> 0 | H6: =SUM(D6:G6) -> 0
B7: Feburary | C7: =SUM(FEB!$D$23:$D$38) -> 0 | D7: =SUM(FEB!$H$23:$H$38) -> 0 | E7: =SUM(FEB!$M$23:$M$38) -> 0 | F7: =SUM(FEB!$R$23:$R$38) -> 0 | G7: =SUM(FEB!$W$23:$W$38) -> 0 | H7: =SUM(D7:G7) -> 0
B8: March | C8: =SUM(MAR!$D$23:$D$38) -> 0 | D8: =SUM(MAR!$H$23:$H$38) -> 0 | E8: =SUM(MAR!$M$23:$M$38) -> 0 | F8: =SUM(MAR!$R$23:$R$38) -> 0 | G8: =SUM(MAR!$W$23:$W$38) -> 0 | H8: =SUM(D8:G8) -> 0
B9: April | C9: =SUM(APR!$D$23:$D$38) -> 0 | D9: =SUM(APR!$H$23:$H$38) -> 0 | E9: =SUM(APR!$M$23:$M$38) -> 0 | F9: =SUM(APR!$R$23:$R$38) -> 0 | G9: =SUM(APR!$W$23:$W$38) -> 0 | H9: =SUM(D9:G9) -> 0
B10: May | C10: =SUM(MAY!$D$23:$D$38) -> 0 | D10: =SUM(MAY!$H$23:$H$38) -> 0 | E10: =SUM(MAY!$M$23:$M$38) -> 0 | F10: =SUM(MAY!$R$23:$R$38) -> 0 | G10: =SUM(MAY!$W$23:$W$38) -> 0 | H10: =SUM(D10:G10) -> 0
B11: June | C11: =SUM(JUN!$D$23:$D$38) -> 0 | D11: =SUM(JUN!$H$23:$H$38) -> 0 | E11: =SUM(JUN!$M$23:$M$38) -> 0 | F11: =SUM(JUN!$R$23:$R$38) -> 0 | G11: =SUM(JUN!$W$23:$W$38) -> 0 | H11: =SUM(D11:G11) -> 0
B12: July | C12: =SUM(JUL!$D$23:$D$38) -> 0 | D12: =SUM(JUL!$H$23:$H$38) -> 0 | E12: =SUM(JUL!$M$23:$M$38) -> 0 | F12: =SUM(JUL!$R$23:$R$38) -> 0 | G12: =SUM(JUL!$W$23:$W$38) -> 0 | H12: =SUM(D12:G12) -> 0
B13: August | C13: =SUM(AUG!$D$23:$D$38) -> 0 | D13: =SUM(AUG!$H$23:$H$38) -> 0 | E13: =SUM(AUG!$M$23:$M$38) -> 0 | F13: =SUM(AUG!$R$23:$R$38) -> 0 | G13: =SUM(AUG!$W$23:$W$38) -> 0 | H13: =SUM(D13:G13) -> 0
B14: September | C14: =SUM(SEPT!$D$23:$D$38) -> 0 | D14: =SUM(SEPT!$H$23:$H$38) -> 0 | E14: =SUM(SEPT!$M$23:$M$38) -> 0 | F14: =SUM(SEPT!$R$23:$R$38) -> 0 | G14: =SUM(SEPT!$W$23:$W$38) -> 0 | H14: =SUM(D14:G14) -> 0
B15: October | C15: =SUM(OCT!$D$23:$D$38) -> 0 | D15: =SUM(OCT!$H$23:$H$38) -> 0 | E15: =SUM(OCT!$M$23:$M$38) -> 0 | F15: =SUM(OCT!$R$23:$R$38) -> 0 | G15: =SUM(OCT!$W$23:$W$38) -> 0 | H15: =SUM(D15:G15) -> 0
B16: November | C16: =SUM(NOV!$D$23:$D$38) -> 0 | D16: =SUM(NOV!$H$23:$H$38) -> 0 | E16: =SUM(NOV!$M$23:$M$38) -> 0 | F16: =SUM(NOV!$R$23:$R$38) -> 0 | G16: =SUM(NOV!$W$23:$W$38) -> 0 | H16: =SUM(D16:G16) -> 0
B17: December | C17: =SUM(DEC!$D$23:$D$38) -> 0 | D17: =SUM(DEC!$H$23:$H$38) -> 0 | E17: =SUM(DEC!$M$23:$M$38) -> 0 | F17: =SUM(DEC!$R$23:$R$38) -> 0 | G17: =SUM(DEC!$W$23:$W$38) -> 0 | H17: =SUM(D17:G17) -> 0
B18: TOTAL | C18: =SUM(C6:C17) -> 0 | D18: =SUM(D6:D17) -> 0 | E18: =SUM(E6:E17) -> 0 | F18: =SUM(F6:F17) -> 0 | G18: =SUM(G6:G17) -> 0 | H18: =SUM(D18:G18) -> 0

Sheet lists
A1: Income | B1: Bills List | C1: Expenses List | D1: Debt List | E1: Savings List
A2: Salary | B2: Rent | C2: Food | D2: Mobile Money Loan | E2: Fixed Deposit
A3: Bonus | B3: Mortgage | C3: Groceries | D3: Airtel | E3: Home Setup Fund
A4: Overtime | B4: Electricity | C4: Transport | D4: Medical Loan | E4: Vehicle Purchase Fund
A5: Commission | B5: Water | C5: Fuel | D5: SACCO Loan | E5: Digital Wallet Savings
A6: Freelance Income | B6: Internet | C6: Transport Fare | D6: Bank Loan | E6: Airtel Money Savings
A7: Business Profits | B7: Airtime/Data | C7: Clothing | D7: Personal Loan | E7: MTN MoMo Savings
A8: Side Hustle Income | B8: Garbage Collection | C8: Household Items | D8: Business Loan | E8: Emergency Fund
A9: Agricultural Sales | B9: Pay TV | C9: Data Bundles | D9: Credit Card | E9: Land Purchase Fund
A10: Produce Sales | B10: School Fees | C10: Mobile Airtime | D10: Salary Advance | E10: Business Startup Fund
A11: Rental Income | B11: Tuition | C11: Entertainment | D11: Borrowed from Friends | E11: Child Education Fund
A12: Land Lease Income | B12: Mobile Money Fees | C12: Movies | D12: Borrowed from Family | E12: Holiday Fund
... A21: Refunds | B21: Land Lease | C21: Repairs | D21: Others | E21: Charity Fund
A22: Online Sales | B22: Service Subscriptions | C22: Home Repairs | E22: Health Savings
A23: Digital Products | B23: Parking Fees | C23: Electronics Repairs | E23: SACCO Savings
A24: YouTube Earnings | B24: Others | C24: Farming Inputs | E24: Insurance Reserve
A25: Tutoring Fees | C25: Pet Care | E25: Others
A26: Workshop Facilitation | C26: Subscriptions
A27: Event Hosting | C27: Books
A28: Transport Refunds | C28: Stationery
A29: Per Diem | C29: Data Bundles
A30: Allowance | C30: Mobile Airtime
A31: Pension | C31: Event Tickets
A32: Social Security | C32: Others
A33: Investment Returns
A34: Loan Disbursement
A35: Others

Sheet JAN
B2: JANUARY | F2: INCOME | J2: BILLS | N2: EXPENSES | R2: DEBT | V2: SAVINGS | AM2: Ranking | AN2: ITEM | AO2: CATEGORY | AP2: TOTAL SPENT
AM3: =IFERROR(_xlfn.RANK.EQ(AP3, $AP$3:$AP$150)+ COUNTIFS($AP$3:AP3, AP3) - 1,"") | AN3: =F23 -> SACCO Dues | AO3: BILLS | AP3: =IFERROR(VLOOKUP(AN3,JAN!$F$23:$H$38,3,FALSE),"")
F4: =SUM(JAN!$D$23:$D$38) -> 0 | J4: =SUM(JAN!$H$23:$H$38) -> 0 | N4: =SUM(JAN!$M$23:$M$38) -> 0 | R4: =SUM(JAN!$R$23:$R$38) -> 0 | V4: =SUM(JAN!$W$23:$W$38) -> 0 | AM4: =IFERROR(_xlfn.RANK.EQ(AP4, $AP$3:$AP$150)+ COUNTIFS($AP$3:AP4, AP4) - 1,"") | AN4: =F24 | AO4: BILLS | AP4: =IFERROR(VLOOKUP(AN4,JAN!$F$23:$H$38,3,FALSE),"")
B5: SUMMARY | AM5: =IFERROR(_xlfn.RANK.EQ(AP5, $AP$3:$AP$150)+ COUNTIFS($AP$3:AP5, AP5) - 1,"") | AN5: =F25 | AO5: BILLS | AP5: =IFERROR(VLOOKUP(AN5,JAN!$F$23:$H$38,3,FALSE),"")
AM6: =IFERROR(_xlfn.RANK.EQ(AP6, $AP$3:$AP$150)+ COUNTIFS($AP$3:AP6, AP6) - 1,"") | AN6: =F26 | AO6: BILLS | AP6: =IFERROR(VLOOKUP(AN6,JAN!$F$23:$H$38,3,FALSE),"")
B7: INCOME OVERVIEW | V7: RANK | W7: ITEM | X7: AMOUNT | AM7: =IFERROR(_xlfn.RANK.EQ(AP7, $AP$3:$AP$150)+ COUNTIFS($AP$3:AP7, AP7) - 1,"") | AN7: =F27 | AO7: BILLS | AP7: =IFERROR(VLOOKUP(AN7,JAN!$F$23:$H$38,3,FALSE),"")
V8: 1 | W8: =IFERROR(VLOOKUP(V8,$AM$3:$AP$65,2,FALSE),"") | X8: =IFERROR(VLOOKUP(V8,$AM$3:$AP$65,4,FALSE),"") | AM8: =IFERROR(_xlfn.RANK.EQ(AP8, $AP$3:$AP$150)+ COUNTIFS($AP$3:AP8, AP8) - 1,"") | AN8: =F28 | AO8: BILLS | AP8: =IFERROR(VLOOKUP(AN8,JAN!$F$23:$H$38,3,FALSE),"")
V9: 2 | W9: =IFERROR(VLOOKUP(V9,$AM$3:$AP$65,2,FALSE),"") | X9: =IFERROR(VLOOKUP(V9,$AM$3:$AP$65,4,FALSE),"") | AM9: =IFERROR(_xlfn.RANK.EQ(AP9, $AP$3:$AP$150)+ COUNTIFS($AP$3:AP9, AP9) - 1,"") | AN9: =F29 | AO9: BILLS | AP9: =IFERROR(VLOOKUP(AN9,JAN!$F$23:$H$38,3,FALSE),"")
C10: Planned | D10: Actual | V10: 3 | W10: =IFERROR(VLOOKUP(V10,$AM$3:$AP$65,2,FALSE),"") | X10: =IFERROR(VLOOKUP(V10,$AM$3:$AP$65,4,FALSE),"") | AM10: =IFERROR(_xlfn.RANK.EQ(AP10, $AP$3:$AP$150)+ COUNTIFS($AP$3:AP10, AP10) - 1,"") | AN10: =F30 | AO10: BILLS | AP10: =IFERROR(VLOOKUP(AN10,JAN!$F$23:$H$38,3,FALSE),"")
B11: INCOME | C11: =SUM(JAN!$C$23:$C$38) -> 0 | D11: =SUM(JAN!$D$23:$D$38) -> 0 | V11: 4 | W11: =IFERROR(VLOOKUP(V11,$AM$3:$AP$65,2,FALSE),"") | X11: =IFERROR(VLOOKUP(V11,$AM$3:$AP$65,4,FALSE),"") | AM11: =IFERROR(_xlfn.RANK.EQ(AP11, $AP$3:$AP$150)+ COUNTIFS($AP$3:AP11, AP11) - 1,"") | AN11: =F31 | AO11: BILLS | AP11: =IFERROR(VLOOKUP(AN11,JAN!$F$23:$H$38,3,FALSE),"")
B12: BILLS | C12: =SUM(JAN!$G$23:$G$38) -> 0 | D12: =SUM(JAN!$H$23:$H$38) -> 0 | V12: 5 | W12: =IFERROR(VLOOKUP(V12,$AM$3:$AP$65,2,FALSE),"") | X12: =IFERROR(VLOOKUP(V12,$AM$3:$AP$65,4,FALSE),"") | AM12: =IFERROR(_xlfn.RANK.EQ(AP12, $AP$3:$AP$150)+ COUNTIFS($AP$3:AP12, AP12) - 1,"") | AN12: =F32 | AO12: BILLS | AP12: =IFERROR(VLOOKUP(AN12,JAN!$F$23:$H$38,3,FALSE),"")
B13: EXPENSES | C13: =SUM(JAN!$L$23:$L$38) -> 0 | D13: =SUM(JAN!$M$23:$M$38) -> 0 | V13: 6 | W13: =IFERROR(VLOOKUP(V13,$AM$3:$AP$65,2,FALSE),"") | X13: =IFERROR(VLOOKUP(V13,$AM$3:$AP$65,4,FALSE),"") | AM13: =IFERROR(_xlfn.RANK.EQ(AP13, $AP$3:$AP$150)+ COUNTIFS($AP$3:AP13, AP13) - 1,"") | AN13: =F33 | AO13: BILLS | AP13: =IFERROR(VLOOKUP(AN13,JAN!$F$23:$H$38,3,FALSE),"")
B14: DEBT | C14: =SUM(JAN!$Q$23:$Q$38) -> 0 | D14: =SUM(JAN!$R$23:$R$38) -> 0 | V14: 7 | W14: =IFERROR(VLOOKUP(V14,$AM$3:$AP$65,2,FALSE),"") | X14: =IFERROR(VLOOKUP(V14,$AM$3:$AP$65,4,FALSE),"") | AM14: =IFERROR(_xlfn.RANK.EQ(AP14, $AP$3:$AP$150)+ COUNTIFS($AP$3:AP14, AP14) - 1,"") | AN14: =F34 | AO14: BILLS | AP14: =IFERROR(VLOOKUP(AN14,JAN!$F$23:$H$38,3,FALSE),"")
B15: SAVINGS | C15: =SUM(JAN!$V$23:$V$38) -> 0 | D15: =SUM(JAN!$W$23:$W$38) -> 0 | V15: 8 | W15: =IFERROR(VLOOKUP(V15,$AM$3:$AP$65,2,FALSE),"") | X15: =IFERROR(VLOOKUP(V15,$AM$3:$AP$65,4,FALSE),"") | AM15: =IFERROR(_xlfn.RANK.EQ(AP15, $AP$3:$AP$150)+ COUNTIFS($AP$3:AP15, AP15) - 1,"") | AN15: =F35 | AO15: BILLS | AP15: =IFERROR(VLOOKUP(AN15,JAN!$F$23:$H$38,3,FALSE),"")
B16: BALANCE | C16: =(C11-SUM(C12:C15)) -> 0 | D16: =(D11-SUM(D12:D15)) -> 0 | V16: 9 | W16: =IFERROR(VLOOKUP(V16,$AM$3:$AP$65,2,FALSE),"") | X16: =IFERROR(VLOOKUP(V16,$AM$3:$AP$65,4,FALSE),"") | AM16: =IFERROR(_xlfn.RANK.EQ(AP16, $AP$3:$AP$150)+ COUNTIFS($AP$3:AP16, AP16) - 1,"") | AN16: =F36 | AO16: BILLS | AP16: =IFERROR(VLOOKUP(AN16,JAN!$F$23:$H$38,3,FALSE),"")
V17: 10 | W17: =IFERROR(VLOOKUP(V17,$AM$3:$AP$65,2,FALSE),"") | X17: =IFERROR(VLOOKUP(V17,$AM$3:$AP$65,4,FALSE),"") | AM17: =IFERROR(_xlfn.RANK.EQ(AP17, $AP$3:$AP$150)+ COUNTIFS($AP$3:AP17, AP17) - 1,"") | AN17: =F37 | AO17: BILLS | AP17: =IFERROR(VLOOKUP(AN17,JAN!$F$23:$H$38,3,FALSE),"")
V18: 11 | W18: =IFERROR(VLOOKUP(V18,$AM$3:$AP$65,2,FALSE),"") | X18: =IFERROR(VLOOKUP(V18,$AM$3:$AP$65,4,FALSE),"") | AM18: =IFERROR(_xlfn.RANK.EQ(AP18, $AP$3:$AP$150)+ COUNTIFS($AP$3:AP18, AP18) - 1,"") | AN18: =F38 | AO18: BILLS | AP18: =IFERROR(VLOOKUP(AN18,JAN!$F$23:$H$38,3,FALSE),"")
AM19: =IFERROR(_xlfn.RANK.EQ(AP19, $AP$3:$AP$150)+ COUNTIFS($AP$3:AP19, AP19) - 1,"") | AN19: =K23 | AO19: EXPENSES | AP19: =IFERROR(VLOOKUP(AN19,JAN!$K$23:$M$38,3,FALSE),"")
B20: INCOME | F20: BILLS | K20: EXPENSES | P20: DEBT | U20: SAVINGS | AM20: =IFERROR(_xlfn.RANK.EQ(AP20, $AP$3:$AP$150)+ COUNTIFS($AP$3:AP20, AP20) - 1,"") | AN20: =K24 | AO20: EXPENSES | AP20: =IFERROR(VLOOKUP(AN20,JAN!$K$23:$M$38,3,FALSE),"")
AM21: =IFERROR(_xlfn.RANK.EQ(AP21, $AP$3:$AP$150)+ COUNTIFS($AP$3:AP21, AP21) - 1,"") | AN21: =K25 | AO21: EXPENSES | AP21: =IFERROR(VLOOKUP(AN21,JAN!$K$23:$M$38,3,FALSE),"")
B22: Details | C22: Planned | D22: Actual | F22: Details | G22: Planned | H22: Actual | I22: Variance | K22: Details | L22: Planned | M22: Actual | N22: Variance | P22: Details | Q22: Planned | R22: Actual | S22: Variance | U22: Details | V22: Planned | W22: Actual | X22: Variance | AM22: =IFERROR(_xlfn.RANK.EQ(AP22, $AP$3:$AP$150)+ COUNTIFS($AP$3:AP22, AP22) - 1,"") | AN22: =K26 | AO22: EXPENSES | AP22: =IFERROR(VLOOKUP(AN22,JAN!$K$23:$M$38,3,FALSE),"")
F23: SACCO Dues | I23: =JAN!$G23-JAN!$H23 -> 0 | N23: =JAN!$L23-JAN!$M23 -> 0 | S23: =JAN!$Q23-JAN!$R23 -> 0 | X23: =JAN!$V23-JAN!$W23 -> 0 | AM23: =IFERROR(_xlfn.RANK.EQ(AP23, $AP$3:$AP$150)+ COUNTIFS($AP$3:AP23, AP23) - 1,"") | AN23: =K27 | AO23: EXPENSES | AP23: =IFERROR(VLOOKUP(AN23,JAN!$K$23:$M$38,3,FALSE),"")
I24: =JAN!$G24-JAN!$H24 -> 0 | N24: =JAN!$L24-JAN!$M24 -> 0 | S24: =JAN!$Q24-JAN!$R24 -> 0 | X24: =JAN!$V24-JAN!$W24 -> 0 | AM24: =IFERROR(_xlfn.RANK.EQ(AP24, $AP$3:$AP$150)+ COUNTIFS($AP$3:AP24, AP24) - 1,"") | AN24: =K28 | AO24: EXPENSES | AP24: =IFERROR(VLOOKUP(AN24,JAN!$K$23:$M$38,3,FALSE),"")
I25: =JAN!$G25-JAN!$H25 -> 0 | N25: =JAN!$L25-JAN!$M25 -> 0 | S25: =JAN!$Q25-JAN!$R25 -> 0 | X25: =JAN!$V25-JAN!$W25 -> 0 | AM25: =IFERROR(_xlfn.RANK.EQ(AP25, $AP$3:$AP$150)+ COUNTIFS($AP$3:AP25, AP25) - 1,"") | AN25: =K29 | AO25: EXPENSES | AP25: =IFERROR(VLOOKUP(AN25,JAN!$K$23:$M$38,3,FALSE),"")
I26: =JAN!$G26-JAN!$H26 -> 0 | N26: =JAN!$L26-JAN!$M26 -> 0 | S26: =JAN!$Q26-JAN!$R26 -> 0 | X26: =JAN!$V26-JAN!$W26 -> 0 | AM26: =IFERROR(_xlfn.RANK.EQ(AP26, $AP$3:$AP$150)+ COUNTIFS($AP$3:AP26, AP26) - 1,"") | AN26: =K30 | AO26: EXPENSES | AP26: =IFERROR(VLOOKUP(AN26,JAN!$K$23:$M$38,3,FALSE),"")
I27: =JAN!$G27-JAN!$H27 -> 0 | N27: =JAN!$L27-JAN!$M27 -> 0 | S27: =JAN!$Q27-JAN!$R27 -> 0 | X27: =JAN!$V27-JAN!$W27 -> 0 | AM27: =IFERROR(_xlfn.RANK.EQ(AP27, $AP$3:$AP$150)+ COUNTIFS($AP$3:AP27, AP27) - 1,"") | AN27: =K31 | AO27: EXPENSES | AP27: =IFERROR(VLOOKUP(AN27,JAN!$K$23:$M$38,3,FALSE),"")
I28: =JAN!$G28-JAN!$H28 -> 0 | N28: =JAN!$L28-JAN!$M28 -> 0 | S28: =JAN!$Q28-JAN!$R28 -> 0 | X28: =JAN!$V28-JAN!$W28 -> 0 | AM28: =IFERROR(_xlfn.RANK.EQ(AP28, $AP$3:$AP$150)+ COUNTIFS($AP$3:AP28, AP28) - 1,"") | AN28: =K32 | AO28: EXPENSES | AP28: =IFERROR(VLOOKUP(AN28,JAN!$K$23:$M$38,3,FALSE),"")
I29: =JAN!$G29-JAN!$H29 -> 0 | N29: =JAN!$L29-JAN!$M29 -> 0 | S29: =JAN!$Q29-JAN!$R29 -> 0 | X29: =JAN!$V29-JAN!$W29 -> 0 | AM29: =IFERROR(_xlfn.RANK.EQ(AP29, $AP$3:$AP$150)+ COUNTIFS($AP$3:AP29, AP29) - 1,"") | AN29: =K33 | AO29: EXPENSES | AP29: =IFERROR(VLOOKUP(AN29,JAN!$K$23:$M$38,3,FALSE),"")
I30: =JAN!$G30-JAN!$H30 -> 0 | N30: =JAN!$L30-JAN!$M30 -> 0 | S30: =JAN!$Q30-JAN!$R30 -> 0 | X30: =JAN!$V30-JAN!$W30 -> 0 | AM30: =IFERROR(_xlfn.RANK.EQ(AP30, $AP$3:$AP$150)+ COUNTIFS($AP$3:AP30, AP30) - 1,"") | AN30: =K34 | AO30: EXPENSES | AP30: =IFERROR(VLOOKUP(AN30,JAN!$K$23:$M$38,3,FALSE),"")
I31: =JAN!$G31-JAN!$H31 -> 0 | N31: =JAN!$L31-JAN!$M31 -> 0 | S31: =JAN!$Q31-JAN!$R31 -> 0 | X31: =JAN!$V31-JAN!$W31 -> 0 | AM31: =IFERROR(_xlfn.RANK.EQ(AP31, $AP$3:$AP$150)+ COUNTIFS($AP$3:AP31, AP31) - 1,"") | AN31: =K35 | AO31: EXPENSES | AP31: =IFERROR(VLOOKUP(AN31,JAN!$K$23:$M$38,3,FALSE),"")
I32: =JAN!$G32-JAN!$H32 -> 0 | N32: =JAN!$L32-JAN!$M32 -> 0 | S32: =JAN!$Q32-JAN!$R32 -> 0 | X32: =JAN!$V32-JAN!$W32 -> 0 | AM32: =IFERROR(_xlfn.RANK.EQ(AP32, $AP$3:$AP$150)+ COUNTIFS($AP$3:AP32, AP32) - 1,"") | AN32: =K36 | AO32: EXPENSES | AP32: =IFERROR(VLOOKUP(AN32,JAN!$K$23:$M$38,3,FALSE),"")
I33: =JAN!$G33-JAN!$H33 -> 0 | N33: =JAN!$L33-JAN!$M33 -> 0 | S33: =JAN!$Q33-JAN!$R33 -> 0 | X33: =JAN!$V33-JAN!$W33 -> 0 | AM33: =IFERROR(_xlfn.RANK.EQ(AP33, $AP$3:$AP$150)+ COUNTIFS($AP$3:AP33, AP33) - 1,"") | AN33: =K37 | AO33: EXPENSES | AP33: =IFERROR(VLOOKUP(AN33,JAN!$K$23:$M$38,3,FALSE),"")
I34: =JAN!$G34-JAN!$H34 -> 0 | N34: =JAN!$L34-JAN!$M34 -> 0 | S34: =JAN!$Q34-JAN!$R34 -> 0 | X34: =JAN!$V34-JAN!$W34 -> 0 | AM34: =IFERROR(_xlfn.RANK.EQ(AP34, $AP$3:$AP$150)+ COUNTIFS($AP$3:AP34, AP34) - 1,"") | AN34: =K38 | AO34: DEBTS | AP34: =IFERROR(VLOOKUP(AN34,JAN!$K$23:$M$38,3,FALSE),"")
I35: =JAN!$G35-JAN!$H35 -> 0 | N35: =JAN!$L35-JAN!$M35 -> 0 | S35: =JAN!$Q35-JAN!$R35 -> 0 | X35: =JAN!$V35-JAN!$W35 -> 0 | AM35: =IFERROR(_xlfn.RANK.EQ(AP35, $AP$3:$AP$150)+ COUNTIFS($AP$3:AP35, AP35) - 1,"") | AN35: =P23 | AO35: DEBTS | AP35: =IFERROR(VLOOKUP(AN35,JAN!$P$23:$R$38,3,FALSE),"")
I36: =JAN!$G36-JAN!$H36 -> 0 | N36: =JAN!$L36-JAN!$M36 -> 0 | S36: =JAN!$Q36-JAN!$R36 -> 0 | X36: =JAN!$V36-JAN!$W36 -> 0 | AM36: =IFERROR(_xlfn.RANK.EQ(AP36, $AP$3:$AP$150)+ COUNTIFS($AP$3:AP36, AP36) - 1,"") | AN36: =P24 | AO36: DEBTS | AP36: =IFERROR(VLOOKUP(AN36,JAN!$P$23:$R$38,3,FALSE),"")
I37: =JAN!$G37-JAN!$H37 -> 0 | N37: =JAN!$L37-JAN!$M37 -> 0 | S37: =JAN!$Q37-JAN!$R37 -> 0 | X37: =JAN!$V37-JAN!$W37 -> 0 | AM37: =IFERROR(_xlfn.RANK.EQ(AP37, $AP$3:$AP$150)+ COUNTIFS($AP$3:AP37, AP37) - 1,"") | AN37: =P25 | AO37: DEBTS | AP37: =IFERROR(VLOOKUP(AN37,JAN!$P$23:$R$38,3,FALSE),"")
I38: =JAN!$G38-JAN!$H38 -> 0 | N38: =JAN!$L38-JAN!$M38 -> 0 | S38: =JAN!$Q38-JAN!$R38 -> 0 | X38: =JAN!$V38-JAN!$W38 -> 0 | AM38: =IFERROR(_xlfn.RANK.EQ(AP38, $AP$3:$AP$150)+ COUNTIFS($AP$3:AP38, AP38) - 1,"") | AN38: =P26 | AO38: DEBTS | AP38: =IFERROR(VLOOKUP(AN38,JAN!$P$23:$R$38,3,FALSE),"")
AM39: =IFERROR(_xlfn.RANK.EQ(AP39, $AP$3:$AP$150)+ COUNTIFS($AP$3:AP39, AP39) - 1,"") | AN39: =P27 | AO39: DEBTS | AP39: =IFERROR(VLOOKUP(AN39,JAN!$P$23:$R$38,3,FALSE),"")
AM40: =IFERROR(_xlfn.RANK.EQ(AP40, $AP$3:$AP$150)+ COUNTIFS($AP$3:AP40, AP40) - 1,"") | AN40: =P28 | AO40: DEBTS | AP40: =IFERROR(VLOOKUP(AN40,JAN!$P$23:$R$38,3,FALSE),"")
AM41: =IFERROR(_xlfn.RANK.EQ(AP41, $AP$3:$AP$150)+ COUNTIFS($AP$3:AP41, AP41) - 1,"") | AN41: =P29 | AO41: DEBTS | AP41: =IFERROR(VLOOKUP(AN41,JAN!$P$23:$R$38,3,FALSE),"")
AM42: =IFERROR(_xlfn.RANK.EQ(AP42, $AP$3:$AP$150)+ COUNTIFS($AP$3:AP42, AP42) - 1,"") | AN42: =P30 | AO42: DEBTS | AP42: =IFERROR(VLOOKUP(AN42,JAN!$P$23:$R$38,3,FALSE),"")
AM43: =IFERROR(_xlfn.RANK.EQ(AP43, $AP$3:$AP$150)+ COUNTIFS($AP$3:AP43, AP43) - 1,"") | AN43: =P31 | AO43: DEBTS | AP43: =IFERROR(VLOOKUP(AN43,JAN!$P$23:$R$38,3,FALSE),"")
AM44: =IFERROR(_xlfn.RANK.EQ(AP44, $AP$3:$AP$150)+ COUNTIFS($AP$3:AP44, AP44) - 1,"") | AN44: =P32 | AO44: DEBTS | AP44: =IFERROR(VLOOKUP(AN44,JAN!$P$23:$R$38,3,FALSE),"")
AM45: =IFERROR(_xlfn.RANK.EQ(AP45, $AP$3:$AP$150)+ COUNTIFS($AP$3:AP45, AP45) - 1,"") | AN45: =P33 | AO45: DEBTS | AP45: =IFERROR(VLOOKUP(AN45,JAN!$P$23:$R$38,3,FALSE),"")
AM46: =IFERROR(_xlfn.RANK.EQ(AP46, $AP$3:$AP$150)+ COUNTIFS($AP$3:AP46, AP46) - 1,"") | AN46: =P34 | AO46: DEBTS | AP46: =IFERROR(VLOOKUP(AN46,JAN!$P$23:$R$38,3,FALSE),"")
AM47: =IFERROR(_xlfn.RANK.EQ(AP47, $AP$3:$AP$150)+ COUNTIFS($AP$3:AP47, AP47) - 1,"") | AN47: =P35 | AO47: DEBTS | AP47: =IFERROR(VLOOKUP(AN47,JAN!$P$23:$R$38,3,FALSE),"")
AM48: =IFERROR(_xlfn.RANK.EQ(AP48, $AP$3:$AP$150)+ COUNTIFS($AP$3:AP48, AP48) - 1,"") | AN48: =P36 | AO48: DEBTS | AP48: =IFERROR(VLOOKUP(AN48,JAN!$P$23:$R$38,3,FALSE),"")
AM49: =IFERROR(_xlfn.RANK.EQ(AP49, $AP$3:$AP$150)+ COUNTIFS($AP$3:AP49, AP49) - 1,"") | AN49: =P37 | AO49: SAVINGS | AP49: =IFERROR(VLOOKUP(AN49,JAN!$P$23:$R$38,3,FALSE),"")
AM50: =IFERROR(_xlfn.RANK.EQ(AP50, $AP$3:$AP$150)+ COUNTIFS($AP$3:AP50, AP50) - 1,"") | AN50: =U23 | AO50: SAVINGS | AP50: =IFERROR(VLOOKUP(AN50,JAN!$U$23:$W$38,3,FALSE),"")
AM51: =IFERROR(_xlfn.RANK.EQ(AP51, $AP$3:$AP$150)+ COUNTIFS($AP$3:AP51, AP51) - 1,"") | AN51: =U24 | AO51: SAVINGS | AP51: =IFERROR(VLOOKUP(AN51,JAN!$U$23:$W$38,3,FALSE),"")
AM52: =IFERROR(_xlfn.RANK.EQ(AP52, $AP$3:$AP$150)+ COUNTIFS($AP$3:AP52, AP52) - 1,"") | AN52: =U25 | AO52: SAVINGS | AP52: =IFERROR(VLOOKUP(AN52,JAN!$U$23:$W$38,3,FALSE),"")
AM53: =IFERROR(_xlfn.RANK.EQ(AP53, $AP$3:$AP$150)+ COUNTIFS($AP$3:AP53, AP53) - 1,"") | AN53: =U26 | AO53: SAVINGS | AP53: =IFERROR(VLOOKUP(AN53,JAN!$U$23:$W$38,3,FALSE),"")
AM54: =IFERROR(_xlfn.RANK.EQ(AP54, $AP$3:$AP$150)+ COUNTIFS($AP$3:AP54, AP54) - 1,"") | AN54: =U27 | AO54: SAVINGS | AP54: =IFERROR(VLOOKUP(AN54,JAN!$U$23:$W$38,3,FALSE),"")
AM55: =IFERROR(_xlfn.RANK.EQ(AP55, $AP$3:$AP$150)+ COUNTIFS($AP$3:AP55, AP55) - 1,"") | AN55: =U28 | AO55: SAVINGS | AP55: =IFERROR(VLOOKUP(AN55,JAN!$U$23:$W$38,3,FALSE),"")
AM56: =IFERROR(_xlfn.RANK.EQ(AP56, $AP$3:$AP$150)+ COUNTIFS($AP$3:AP56, AP56) - 1,"") | AN56: =U29 | AO56: SAVINGS | AP56: =IFERROR(VLOOKUP(AN56,JAN!$U$23:$W$38,3,FALSE),"")
AM57: =IFERROR(_xlfn.RANK.EQ(AP57, $AP$3:$AP$150)+ COUNTIFS($AP$3:AP57, AP57) - 1,"") | AN57: =U30 | AO57: SAVINGS | AP57: =IFERROR(VLOOKUP(AN57,JAN!$U$23:$W$38,3,FALSE),"")
AM58: =IFERROR(_xlfn.RANK.EQ(AP58, $AP$3:$AP$150)+ COUNTIFS($AP$3:AP58, AP58) - 1,"") | AN58: =U31 | AO58: SAVINGS | AP58: =IFERROR(VLOOKUP(AN58,JAN!$U$23:$W$38,3,FALSE),"")
AM59: =IFERROR(_xlfn.RANK.EQ(AP59, $AP$3:$AP$150)+ COUNTIFS($AP$3:AP59, AP59) - 1,"") | AN59: =U32 | AO59: SAVINGS | AP59: =IFERROR(VLOOKUP(AN59,JAN!$U$23:$W$38,3,FALSE),"")
AM60: =IFERROR(_xlfn.RANK.EQ(AP60, $AP$3:$AP$150)+ COUNTIFS($AP$3:AP60, AP60) - 1,"") | AN60: =U33 | AO60: SAVINGS | AP60: =IFERROR(VLOOKUP(AN60,JAN!$U$23:$W$38,3,FALSE),"")
AM61: =IFERROR(_xlfn.RANK.EQ(AP61, $AP$3:$AP$150)+ COUNTIFS($AP$3:AP61, AP61) - 1,"") | AN61: =U34 | AO61: SAVINGS | AP61: =IFERROR(VLOOKUP(AN61,JAN!$U$23:$W$38,3,FALSE),"")
... AM65: =IFERROR(_xlfn.RANK.EQ(AP65, $AP$3:$AP$150)+ COUNTIFS($AP$3:AP65, AP65) - 1,"") | AN65: =U38 | AO65: SAVINGS | AP65: =IFERROR(VLOOKUP(AN65,JAN!$U$23:$W$38,3,FALSE),"")

Sheet FEB
B2: FEBURARY | F2: INCOME | J2: BILLS | N2: EXPENSES | R2: DEBT | V2: SAVINGS | AM2: Ranking | AN2: ITEM | AO2: CATEGORY | AP2: TOTAL SPENT
AM3: =IFERROR(_xlfn.RANK.EQ(AP3, $AP$3:$AP$150)+ COUNTIFS($AP$3:AP3, AP3) - 1,"") | AN3: =F23 | AO3: BILLS | AP3: =IFERROR(VLOOKUP(AN3,FEB!$F$23:$H$38,3,FALSE),"")
F4: =SUM(FEB!$D$23:$D$38) -> 0 | J4: =SUM(FEB!$H$23:$H$38) -> 0 | N4: =SUM(FEB!$M$23:$M$38) -> 0 | R4: =SUM(FEB!$R$23:$R$38) -> 0 | V4: =SUM(FEB!$W$23:$W$38) -> 0 | AM4: =IFERROR(_xlfn.RANK.EQ(AP4, $AP$3:$AP$150)+ COUNTIFS($AP$3:AP4, AP4) - 1,"") | AN4: =F24 | AO4: BILLS | AP4: =IFERROR(VLOOKUP(AN4,FEB!$F$23:$H$38,3,FALSE),"")
B5: SUMMARY | AM5: =IFERROR(_xlfn.RANK.EQ(AP5, $AP$3:$AP$150)+ COUNTIFS($AP$3:AP5, AP5) - 1,"") | AN5: =F25 | AO5: BILLS | AP5: =IFERROR(VLOOKUP(AN5,FEB!$F$23:$H$38,3,FALSE),"")
AM6: =IFERROR(_xlfn.RANK.EQ(AP6, $AP$3:$AP$150)+ COUNTIFS($AP$3:AP6, AP6) - 1,"") | AN6: =F26 | AO6: BILLS | AP6: =IFERROR(VLOOKUP(AN6,FEB!$F$23:$H$38,3,FALSE),"")
B7: INCOME OVERVIEW | V7: RANK | W7: ITEM | X7: AMOUNT | AM7: =IFERROR(_xlfn.RANK.EQ(AP7, $AP$3:$AP$150)+ COUNTIFS($AP$3:AP7, AP7) - 1,"") | AN7: =F27 | AO7: BILLS | AP7: =IFERROR(VLOOKUP(AN7,FEB!$F$23:$H$38,3,FALSE),"")
V8: 1 | W8: =IFERROR(VLOOKUP(V8,$AM$3:$AP$65,2,FALSE),"") | X8: =IFERROR(VLOOKUP(V8,$AM$3:$AP$65,4,FALSE),"") | AM8: =IFERROR(_xlfn.RANK.EQ(AP8, $AP$3:$AP$150)+ COUNTIFS($AP$3:AP8, AP8) - 1,"") | AN8: =F28 | AO8: BILLS | AP8: =IFERROR(VLOOKUP(AN8,FEB!$F$23:$H$38,3,FALSE),"")
V9: 2 | W9: =IFERROR(VLOOKUP(V9,$AM$3:$AP$65,2,FALSE),"") | X9: =IFERROR(VLOOKUP(V9,$AM$3:$AP$65,4,FALSE),"") | AM9: =IFERROR(_xlfn.RANK.EQ(AP9, $AP$3:$AP$150)+ COUNTIFS($AP$3:AP9, AP9) - 1,"") | AN9: =F29 | AO9: BILLS | AP9: =IFERROR(VLOOKUP(AN9,FEB!$F$23:$H$38,3,FALSE),"")
C10: Planned | D10: Actual | V10: 3 | W10: =IFERROR(VLOOKUP(V10,$AM$3:$AP$65,2,FALSE),"") | X10: =IFERROR(VLOOKUP(V10,$AM$3:$AP$65,4,FALSE),"") | AM10: =IFERROR(_xlfn.RANK.EQ(AP10, $AP$3:$AP$150)+ COUNTIFS($AP$3:AP10, AP10) - 1,"") | AN10: =F30 | AO10: BILLS | AP10: =IFERROR(VLOOKUP(AN10,FEB!$F$23:$H$38,3,FALSE),"")
B11: INCOME | C11: =SUM(FEB!$C$23:$C$38) -> 0 | D11: =SUM(FEB!$D$23:$D$38) -> 0 | V11: 4 | W11: =IFERROR(VLOOKUP(V11,$AM$3:$AP$65,2,FALSE),"") | X11: =IFERROR(VLOOKUP(V11,$AM$3:$AP$65,4,FALSE),"") | AM11: =IFERROR(_xlfn.RANK.EQ(AP11, $AP$3:$AP$150)+ COUNTIFS($AP$3:AP11, AP11) - 1,"") | AN11: =F31 | AO11: BILLS | AP11: =IFERROR(VLOOKUP(AN11,FEB!$F$23:$H$38,3,FALSE),"")
B12: BILLS | C12: =SUM(FEB!$G$23:$G$38) -> 0 | D12: =SUM(FEB!$H$23:$H$38) -> 0 | V12: 5 | W12: =IFERROR(VLOOKUP(V12,$AM$3:$AP$65,2,FALSE),"") | X12: =IFERROR(VLOOKUP(V12,$AM$3:$AP$65,4,FALSE),"") | AM12: =IFERROR(_xlfn.RANK.EQ(AP12, $AP$3:$AP$150)+ COUNTIFS($AP$3:AP12, AP12) - 1,"") | AN12: =F32 | AO12: BILLS | AP12: =IFERROR(VLOOKUP(AN12,FEB!$F$23:$H$38,3,FALSE),"")
B13: EXPENSES | C13: =SUM(FEB!$L$23:$L$38) -> 0 | D13: =SUM(FEB!$M$23:$M$38) -> 0 | V13: 6 | W13: =IFERROR(VLOOKUP(V13,$AM$3:$AP$65,2,FALSE),"") | X13: =IFERROR(VLOOKUP(V13,$AM$3:$AP$65,4,FALSE),"") | AM13: =IFERROR(_xlfn.RANK.EQ(AP13, $AP$3:$AP$150)+ COUNTIFS($AP$3:AP13, AP13) - 1,"") | AN13: =F33 | AO13: BILLS | AP13: =IFERROR(VLOOKUP(AN13,FEB!$F$23:$H$38,3,FALSE),"")
B14: DEBT | C14: =SUM(FEB!$Q$23:$Q$38) -> 0 | D14: =SUM(FEB!$R$23:$R$38) -> 0 | V14: 7 | W14: =IFERROR(VLOOKUP(V14,$AM$3:$AP$65,2,FALSE),"") | X14: =IFERROR(VLOOKUP(V14,$AM$3:$AP$65,4,FALSE),"") | AM14: =IFERROR(_xlfn.RANK.EQ(AP14, $AP$3:$AP$150)+ COUNTIFS($AP$3:AP14, AP14) - 1,"") | AN14: =F34 | AO14: BILLS | AP14: =IFERROR(VLOOKUP(AN14,FEB!$F$23:$H$38,3,FALSE),"")
B15: SAVINGS | C15: =SUM(FEB!$V$23:$V$38) -> 0 | D15: =SUM(FEB!$W$23:$W$38) -> 0 | V15: 8 | W15: =IFERROR(VLOOKUP(V15,$AM$3:$AP$65,2,FALSE),"") | X15: =IFERROR(VLOOKUP(V15,$AM$3:$AP$65,4,FALSE),"") | AM15: =IFERROR(_xlfn.RANK.EQ(AP15, $AP$3:$AP$150)+ COUNTIFS($AP$3:AP15, AP15) - 1,"") | AN15: =F35 | AO15: BILLS | AP15: =IFERROR(VLOOKUP(AN15,FEB!$F$23:$H$38,3,FALSE),"")
B16: BALANCE | C16: =(C11-SUM(C12:C15)) -> 0 | D16: =(D11-SUM(D12:D15)) -> 0 | V16: 9 | W16: =IFERROR(VLOOKUP(V16,$AM$3:$AP$65,2,FALSE),"") | X16: =IFERROR(VLOOKUP(V16,$AM$3:$AP$65,4,FALSE),"") | AM16: =IFERROR(_xlfn.RANK.EQ(AP16, $AP$3:$AP$150)+ COUNTIFS($AP$3:AP16, AP16) - 1,"") | AN16: =F36 | AO16: BILLS | AP16: =IFERROR(VLOOKUP(AN16,FEB!$F$23:$H$38,3,FALSE),"")
V17: 10 | W17: =IFERROR(VLOOKUP(V17,$AM$3:$AP$65,2,FALSE),"") | X17: =IFERROR(VLOOKUP(V17,$AM$3:$AP$65,4,FALSE),"") | AM17: =IFERROR(_xlfn.RANK.EQ(AP17, $AP$3:$AP$150)+ COUNTIFS($AP$3:AP17, AP17) - 1,"") | AN17: =F37 | AO17: BILLS | AP17: =IFERROR(VLOOKUP(AN17,FEB!$F$23:$H$38,3,FALSE),"")
V18: 11 | W18: =IFERROR(VLOOKUP(V18,$AM$3:$AP$65,2,FALSE),"") | X18: =IFERROR(VLOOKUP(V18,$AM$3:$AP$65,4,FALSE),"") | AM18: =IFERROR(_xlfn.RANK.EQ(AP18, $AP$3:$AP$150)+ COUNTIFS($AP$3:AP18, AP18) - 1,"") | AN18: =F38 | AO18: BILLS | AP18: =IFERROR(VLOOKUP(AN18,FEB!$F$23:$H$38,3,FALSE),"")
AM19: =IFERROR(_xlfn.RANK.EQ(AP19, $AP$3:$AP$150)+ COUNTIFS($AP$3:AP19, AP19) - 1,"") | AN19: =K23 | AO19: EXPENSES | AP19: =IFERROR(VLOOKUP(AN19,FEB!$K$23:$M$38,3,FALSE),"")
B20: INCOME | F20: BILLS | K20: EXPENSES | P20: DEBT | U20: SAVINGS | AM20: =IFERROR(_xlfn.RANK.EQ(AP20, $AP$3:$AP$150)+ COUNTIFS($AP$3:AP20, AP20) - 1,"") | AN20: =K24 | AO20: EXPENSES | AP20: =IFERROR(VLOOKUP(AN20,FEB!$K$23:$M$38,3,FALSE),"")
AM21: =IFERROR(_xlfn.RANK.EQ(AP21, $AP$3:$AP$150)+ COUNTIFS($AP$3:AP21, AP21) - 1,"") | AN21: =K25 | AO21: EXPENSES | AP21: =IFERROR(VLOOKUP(AN21,FEB!$K$23:$M$38,3,FALSE),"")
B22: Details | C22: Planned | D22: Actual | F22: Details | G22: Planned | H22: Actual | I22: Variance | K22: Details | L22: Planned | M22: Actual | N22: Variance | P22: Details | Q22: Planned | R22: Actual | S22: Variance | U22: Details | V22: Planned | W22: Actual | X22: Variance | AM22: =IFERROR(_xlfn.RANK.EQ(AP22, $AP$3:$AP$150)+ COUNTIFS($AP$3:AP22, AP22) - 1,"") | AN22: =K26 | AO22: EXPENSES | AP22: =IFERROR(VLOOKUP(AN22,FEB!$K$23:$M$38,3,FALSE),"")
I23: =FEB!$G23-FEB!$H23 -> 0 | N23: =FEB!$L23-FEB!$M23 -> 0 | S23: =FEB!$Q23-FEB!$R23 -> 0 | X23: =FEB!$V23-FEB!$W23 -> 0 | AM23: =IFERROR(_xlfn.RANK.EQ(AP23, $AP$3:$AP$150)+ COUNTIFS($AP$3:AP23, AP23) - 1,"") | AN23: =K27 | AO23: EXPENSES | AP23: =IFERROR(VLOOKUP(AN23,FEB!$K$23:$M$38,3,FALSE),"")
I24: =FEB!$G24-FEB!$H24 -> 0 | N24: =FEB!$L24-FEB!$M24 -> 0 | S24: =FEB!$Q24-FEB!$R24 -> 0 | X24: =FEB!$V24-FEB!$W24 -> 0 | AM24: =IFERROR(_xlfn.RANK.EQ(AP24, $AP$3:$AP$150)+ COUNTIFS($AP$3:AP24, AP24) - 1,"") | AN24: =K28 | AO24: EXPENSES | AP24: =IFERROR(VLOOKUP(AN24,FEB!$K$23:$M$38,3,FALSE),"")
I25: =FEB!$G25-FEB!$H25 -> 0 | N25: =FEB!$L25-FEB!$M25 -> 0 | S25: =FEB!$Q25-FEB!$R25 -> 0 | X25: =FEB!$V25-FEB!$W25 -> 0 | AM25: =IFERROR(_xlfn.RANK.EQ(AP25, $AP$3:$AP$150)+ COUNTIFS($AP$3:AP25, AP25) - 1,"") | AN25: =K29 | AO25: EXPENSES | AP25: =IFERROR(VLOOKUP(AN25,FEB!$K$23:$M$38,3,FALSE),"")
I26: =FEB!$G26-FEB!$H26 -> 0 | N26: =FEB!$L26-FEB!$M26 -> 0 | S26: =FEB!$Q26-FEB!$R26 -> 0 | X26: =FEB!$V26-FEB!$W26 -> 0 | AM26: =IFERROR(_xlfn.RANK.EQ(AP26, $AP$3:$AP$150)+ COUNTIFS($AP$3:AP26, AP26) - 1,"") | AN26: =K30 | AO26: EXPENSES | AP26: =IFERROR(VLOOKUP(AN26,FEB!$K$23:$M$38,3,FALSE),"")
I27: =FEB!$G27-FEB!$H27 -> 0 | N27: =FEB!$L27-FEB!$M27 -> 0 | S27: =FEB!$Q27-FEB!$R27 -> 0 | X27: =FEB!$V27-FEB!$W27 -> 0 | AM27: =IFERROR(_xlfn.RANK.EQ(AP27, $AP$3:$AP$150)+ COUNTIFS($AP$3:AP27, AP27) - 1,"") | AN27: =K31 | AO27: EXPENSES | AP27: =IFERROR(VLOOKUP(AN27,FEB!$K$23:$M$38,3,FALSE),"")
I28: =FEB!$G28-FEB!$H28 -> 0 | N28: =FEB!$L28-FEB!$M28 -> 0 | S28: =FEB!$Q28-FEB!$R28 -> 0 | X28: =FEB!$V28-FEB!$W28 -> 0 | AM28: =IFERROR(_xlfn.RANK.EQ(AP28, $AP$3:$AP$150)+ COUNTIFS($AP$3:AP28, AP28) - 1,"") | AN28: =K32 | AO28: EXPENSES | AP28: =IFERROR(VLOOKUP(AN28,FEB!$K$23:$M$38,3,FALSE),"")
I29: =FEB!$G29-FEB!$H29 -> 0 | N29: =FEB!$L29-FEB!$M29 -> 0 | S29: =FEB!$Q29-FEB!$R29 -> 0 | X29: =FEB!$V29-FEB!$W29 -> 0 | AM29: =IFERROR(_xlfn.RANK.EQ(AP29, $AP$3:$AP$150)+ COUNTIFS($AP$3:AP29, AP29) - 1,"") | AN29: =K33 | AO29: EXPENSES | AP29: =IFERROR(VLOOKUP(AN29,FEB!$K$23:$M$38,3,FALSE),"")
I30: =FEB!$G30-FEB!$H30 -> 0 | N30: =FEB!$L30-FEB!$M30 -> 0 | S30: =FEB!$Q30-FEB!$R30 -> 0 | X30: =FEB!$V30-FEB!$W30 -> 0 | AM30: =IFERROR(_xlfn.RANK.EQ(AP30, $AP$3:$AP$150)+ COUNTIFS($AP$3:AP30, AP30) - 1,"") | AN30: =K34 | AO30: EXPENSES | AP30: =IFERROR(VLOOKUP(AN30,FEB!$K$23:$M$38,3,FALSE),"")
I31: =FEB!$G31-FEB!$H31 -> 0 | N31: =FEB!$L31-FEB!$M31 -> 0 | S31: =FEB!$Q31-FEB!$R31 -> 0 | X31: =FEB!$V31-FEB!$W31 -> 0 | AM31: =IFERROR(_xlfn.RANK.EQ(AP31, $AP$3:$AP$150)+ COUNTIFS($AP$3:AP31, AP31) - 1,"") | AN31: =K35 | AO31: EXPENSES | AP31: =IFERROR(VLOOKUP(AN31,FEB!$K$23:$M$38,3,FALSE),"")
I32: =FEB!$G32-FEB!$H32 -> 0 | N32: =FEB!$L32-FEB!$M32 -> 0 | S32: =FEB!$Q32-FEB!$R32 -> 0 | X32: =FEB!$V32-FEB!$W32 -> 0 | AM32: =IFERROR(_xlfn.RANK.EQ(AP32, $AP$3:$AP$150)+ COUNTIFS($AP$3:AP32, AP32) - 1,"") | AN32: =K36 | AO32: EXPENSES | AP32: =IFERROR(VLOOKUP(AN32,FEB!$K$23:$M$38,3,FALSE),"")
I33: =FEB!$G33-FEB!$H33 -> 0 | N33: =FEB!$L33-FEB!$M33 -> 0 | S33: =FEB!$Q33-FEB!$R33 -> 0 | X33: =FEB!$V33-FEB!$W33 -> 0 | AM33: =IFERROR(_xlfn.RANK.EQ(AP33, $AP$3:$AP$150)+ COUNTIFS($AP$3:AP33, AP33) - 1,"") | AN33: =K37 | AO33: EXPENSES | AP33: =IFERROR(VLOOKUP(AN33,FEB!$K$23:$M$38,3,FALSE),"")
I34: =FEB!$G34-FEB!$H34 -> 0 | N34: =FEB!$L34-FEB!$M34 -> 0 | S34: =FEB!$Q34-FEB!$R34 -> 0 | X34: =FEB!$V34-FEB!$W34 -> 0 | AM34: =IFERROR(_xlfn.RANK.EQ(AP34, $AP$3:$AP$150)+ COUNTIFS($AP$3:AP34, AP34) - 1,"") | AN34: =K38 | AO34: DEBTS | AP34: =IFERROR(VLOOKUP(AN34,FEB!$K$23:$M$38,3,FALSE),"")
I35: =FEB!$G35-FEB!$H35 -> 0 | N35: =FEB!$L35-FEB!$M35 -> 0 | S35: =FEB!$Q35-FEB!$R35 -> 0 | X35: =FEB!$V35-FEB!$W35 -> 0 | AM35: =IFERROR(_xlfn.RANK.EQ(AP35, $AP$3:$AP$150)+ COUNTIFS($AP$3:AP35, AP35) - 1,"") | AN35: =P23 | AO35: DEBTS | AP35: =IFERROR(VLOOKUP(AN35,FEB!$P$23:$R$38,3,FALSE),"")
I36: =FEB!$G36-FEB!$H36 -> 0 | N36: =FEB!$L36-FEB!$M36 -> 0 | S36: =FEB!$Q36-FEB!$R36 -> 0 | X36: =FEB!$V36-FEB!$W36 -> 0 | AM36: =IFERROR(_xlfn.RANK.EQ(AP36, $AP$3:$AP$150)+ COUNTIFS($AP$3:AP36, AP36) - 1,"") | AN36: =P24 | AO36: DEBTS | AP36: =IFERROR(VLOOKUP(AN36,FEB!$P$23:$R$38,3,FALSE),"")
I37: =FEB!$G37-FEB!$H37 -> 0 | N37: =FEB!$L37-FEB!$M37 -> 0 | S37: =FEB!$Q37-FEB!$R37 -> 0 | X37: =FEB!$V37-FEB!$W37 -> 0 | AM37: =IFERROR(_xlfn.RANK.EQ(AP37, $AP$3:$AP$150)+ COUNTIFS($AP$3:AP37, AP37) - 1,"") | AN37: =P25 | AO37: DEBTS | AP37: =IFERROR(VLOOKUP(AN37,FEB!$P$23:$R$38,3,FALSE),"")
I38: =FEB!$G38-FEB!$H38 -> 0 | N38: =FEB!$L38-FEB!$M38 -> 0 | S38: =FEB!$Q38-FEB!$R38 -> 0 | X38: =FEB!$V38-FEB!$W38 -> 0 | AM38: =IFERROR(_xlfn.RANK.EQ(AP38, $AP$3:$AP$150)+ COUNTIFS($AP$3:AP38, AP38) - 1,"") | AN38: =P26 | AO38: DEBTS | AP38: =IFERROR(VLOOKUP(AN38,FEB!$P$23:$R$38,3,FALSE),"")
AM39: =IFERROR(_xlfn.RANK.EQ(AP39, $AP$3:$AP$150)+ COUNTIFS($AP$3:AP39, AP39) - 1,"") | AN39: =P27 | AO39: DEBTS | AP39: =IFERROR(VLOOKUP(AN39,FEB!$P$23:$R$38,3,FALSE),"")
AM40: =IFERROR(_xlfn.RANK.EQ(AP40, $AP$3:$AP$150)+ COUNTIFS($AP$3:AP40, AP40) - 1,"") | AN40: =P28 | AO40: DEBTS | AP40: =IFERROR(VLOOKUP(AN40,FEB!$P$23:$R$38,3,FALSE),"")
AM41: =IFERROR(_xlfn.RANK.EQ(AP41, $AP$3:$AP$150)+ COUNTIFS($AP$3:AP41, AP41) - 1,"") | AN41: =P29 | AO41: DEBTS | AP41: =IFERROR(VLOOKUP(AN41,FEB!$P$23:$R$38,3,FALSE),"")
AM42: =IFERROR(_xlfn.RANK.EQ(AP42, $AP$3:$AP$150)+ COUNTIFS($AP$3:AP42, AP42) - 1,"") | AN42: =P30 | AO42: DEBTS | AP42: =IFERROR(VLOOKUP(AN42,FEB!$P$23:$R$38,3,FALSE),"")
AM43: =IFERROR(_xlfn.RANK.EQ(AP43, $AP$3:$AP$150)+ COUNTIFS($AP$3:AP43, AP43) - 1,"") | AN43: =P31 | AO43: DEBTS | AP43: =IFERROR(VLOOKUP(AN43,FEB!$P$23:$R$38,3,FALSE),"")
AM44: =IFERROR(_xlfn.RANK.EQ(AP44, $AP$3:$AP$150)+ COUNTIFS($AP$3:AP44, AP44) - 1,"") | AN44: =P32 | AO44: DEBTS | AP44: =IFERROR(VLOOKUP(AN44,FEB!$P$23:$R$38,3,FALSE),"")
AM45: =IFERROR(_xlfn.RANK.EQ(AP45, $AP$3:$AP$150)+ COUNTIFS($AP$3:AP45, AP45) - 1,"") | AN45: =P33 | AO45: DEBTS | AP45: =IFERROR(VLOOKUP(AN45,FEB!$P$23:$R$38,3,FALSE),"")
AM46: =IFERROR(_xlfn.RANK.EQ(AP46, $AP$3:$AP$150)+ COUNTIFS($AP$3:AP46, AP46) - 1,"") | AN46: =P34 | AO46: DEBTS | AP46: =IFERROR(VLOOKUP(AN46,FEB!$P$23:$R$38,3,FALSE),"")
AM47: =IFERROR(_xlfn.RANK.EQ(AP47, $AP$3:$AP$150)+ COUNTIFS($AP$3:AP47, AP47) - 1,"") | AN47: =P35 | AO47: DEBTS | AP47: =IFERROR(VLOOKUP(AN47,FEB!$P$23:$R$38,3,FALSE),"")
AM48: =IFERROR(_xlfn.RANK.EQ(AP48, $AP$3:$AP$150)+ COUNTIFS($AP$3:AP48, AP48) - 1,"") | AN48: =P36 | AO48: DEBTS | AP48: =IFERROR(VLOOKUP(AN48,FEB!$P$23:$R$38,3,FALSE),"")
AM49: =IFERROR(_xlfn.RANK.EQ(AP49, $AP$3:$AP$150)+ COUNTIFS($AP$3:AP49, AP49) - 1,"") | AN49: =P37 | AO49: SAVINGS | AP49: =IFERROR(VLOOKUP(AN49,FEB!$P$23:$R$38,3,FALSE),"")
AM50: =IFERROR(_xlfn.RANK.EQ(AP50, $AP$3:$AP$150)+ COUNTIFS($AP$3:AP50, AP50) - 1,"") | AN50: =U23 | AO50: SAVINGS | AP50: =IFERROR(VLOOKUP(AN50,FEB!$U$23:$W$38,3,FALSE),"")
AM51: =IFERROR(_xlfn.RANK.EQ(AP51, $AP$3:$AP$150)+ COUNTIFS($AP$3:AP51, AP51) - 1,"") | AN51: =U24 | AO51: SAVINGS | AP51: =IFERROR(VLOOKUP(AN51,FEB!$U$23:$W$38,3,FALSE),"")
AM52: =IFERROR(_xlfn.RANK.EQ(AP52, $AP$3:$AP$150)+ COUNTIFS($AP$3:AP52, AP52) - 1,"") | AN52: =U25 | AO52: SAVINGS | AP52: =IFERROR(VLOOKUP(AN52,FEB!$U$23:$W$38,3,FALSE),"")
AM53: =IFERROR(_xlfn.RANK.EQ(AP53, $AP$3:$AP$150)+ COUNTIFS($AP$3:AP53, AP53) - 1,"") | AN53: =U26 | AO53: SAVINGS | AP53: =IFERROR(VLOOKUP(AN53,FEB!$U$23:$W$38,3,FALSE),"")
AM54: =IFERROR(_xlfn.RANK.EQ(AP54, $AP$3:$AP$150)+ COUNTIFS($AP$3:AP54, AP54) - 1,"") | AN54: =U27 | AO54: SAVINGS | AP54: =IFERROR(VLOOKUP(AN54,FEB!$U$23:$W$38,3,FALSE),"")
AM55: =IFERROR(_xlfn.RANK.EQ(AP55, $AP$3:$AP$150)+ COUNTIFS($AP$3:AP55, AP55) - 1,"") | AN55: =U28 | AO55: SAVINGS | AP55: =IFERROR(VLOOKUP(AN55,FEB!$U$23:$W$38,3,FALSE),"")
AM56: =IFERROR(_xlfn.RANK.EQ(AP56, $AP$3:$AP$150)+ COUNTIFS($AP$3:AP56, AP56) - 1,"") | AN56: =U29 | AO56: SAVINGS | AP56: =IFERROR(VLOOKUP(AN56,FEB!$U$23:$W$38,3,FALSE),"")
AM57: =IFERROR(_xlfn.RANK.EQ(AP57, $AP$3:$AP$150)+ COUNTIFS($AP$3:AP57, AP57) - 1,"") | AN57: =U30 | AO57: SAVINGS | AP57: =IFERROR(VLOOKUP(AN57,FEB!$U$23:$W$38,3,FALSE),"")
AM58: =IFERROR(_xlfn.RANK.EQ(AP58, $AP$3:$AP$150)+ COUNTIFS($AP$3:AP58, AP58) - 1,"") | AN58: =U31 | AO58: SAVINGS | AP58: =IFERROR(VLOOKUP(AN58,FEB!$U$23:$W$38,3,FALSE),"")
AM59: =IFERROR(_xlfn.RANK.EQ(AP59, $AP$3:$AP$150)+ COUNTIFS($AP$3:AP59, AP59) - 1,"") | AN59: =U32 | AO59: SAVINGS | AP59: =IFERROR(VLOOKUP(AN59,FEB!$U$23:$W$38,3,FALSE),"")
AM60: =IFERROR(_xlfn.RANK.EQ(AP60, $AP$3:$AP$150)+ COUNTIFS($AP$3:AP60, AP60) - 1,"") | AN60: =U33 | AO60: SAVINGS | AP60: =IFERROR(VLOOKUP(AN60,FEB!$U$23:$W$38,3,FALSE),"")
AM61: =IFERROR(_xlfn.RANK.EQ(AP61, $AP$3:$AP$150)+ COUNTIFS($AP$3:AP61, AP61) - 1,"") | AN61: =U34 | AO61: SAVINGS | AP61: =IFERROR(VLOOKUP(AN61,FEB!$U$23:$W$38,3,FALSE),"")
... AM65: =IFERROR(_xlfn.RANK.EQ(AP65, $AP$3:$AP$150)+ COUNTIFS($AP$3:AP65, AP65) - 1,"") | AN65: =U38 | AO65: SAVINGS | AP65: =IFERROR(VLOOKUP(AN65,FEB!$U$23:$W$38,3,FALSE),"")

Sheet APR
B2: APRIL | F2: INCOME | J2: BILLS | N2: EXPENSES | R2: DEBT | V2: SAVINGS | AM2: Ranking | AN2: ITEM | AO2: CATEGORY | AP2: TOTAL SPENT
AM3: =IFERROR(_xlfn.RANK.EQ(AP3, $AP$3:$AP$150)+ COUNTIFS($AP$3:AP3, AP3) - 1,"") | AN3: =F23 | AO3: BILLS | AP3: =IFERROR(VLOOKUP(AN3,APR!$F$23:$H$38,3,FALSE),"")
F4: =SUM(APR!$D$23:$D$38) -> 0 | J4: =SUM(APR!$H$23:$H$38) -> 0 | N4: =SUM(APR!$M$23:$M$38) -> 0 | R4: =SUM(APR!$R$23:$R$38) -> 0 | V4: =SUM(APR!$W$23:$W$38) -> 0 | AM4: =IFERROR(_xlfn.RANK.EQ(AP4, $AP$3:$AP$150)+ COUNTIFS($AP$3:AP4, AP4) - 1,"") | AN4: =F24 | AO4: BILLS | AP4: =IFERROR(VLOOKUP(AN4,APR!$F$23:$H$38,3,FALSE),"")
B5: SUMMARY | AM5: =IFERROR(_xlfn.RANK.EQ(AP5, $AP$3:$AP$150)+ COUNTIFS($AP$3:AP5, AP5) - 1,"") | AN5: =F25 | AO5: BILLS | AP5: =IFERROR(VLOOKUP(AN5,APR!$F$23:$H$38,3,FALSE),"")
AM6: =IFERROR(_xlfn.RANK.EQ(AP6, $AP$3:$AP$150)+ COUNTIFS($AP$3:AP6, AP6) - 1,"") | AN6: =F26 | AO6: BILLS | AP6: =IFERROR(VLOOKUP(AN6,APR!$F$23:$H$38,3,FALSE),"")
B7: INCOME OVERVIEW | V7: RANK | W7: ITEM | X7: AMOUNT | AM7: =IFERROR(_xlfn.RANK.EQ(AP7, $AP$3:$AP$150)+ COUNTIFS($AP$3:AP7, AP7) - 1,"") | AN7: =F27 | AO7: BILLS | AP7: =IFERROR(VLOOKUP(AN7,APR!$F$23:$H$38,3,FALSE),"")
V8: 1 | W8: =IFERROR(VLOOKUP(V8,$AM$3:$AP$65,2,FALSE),"") | X8: =IFERROR(VLOOKUP(V8,$AM$3:$AP$65,4,FALSE),"") | AM8: =IFERROR(_xlfn.RANK.EQ(AP8, $AP$3:$AP$150)+ COUNTIFS($AP$3:AP8, AP8) - 1,"") | AN8: =F28 | AO8: BILLS | AP8: =IFERROR(VLOOKUP(AN8,APR!$F$23:$H$38,3,FALSE),"")
V9: 2 | W9: =IFERROR(VLOOKUP(V9,$AM$3:$AP$65,2,FALSE),"") | X9: =IFERROR(VLOOKUP(V9,$AM$3:$AP$65,4,FALSE),"") | AM9: =IFERROR(_xlfn.RANK.EQ(AP9, $AP$3:$AP$150)+ COUNTIFS($AP$3:AP9, AP9) - 1,"") | AN9: =F29 | AO9: BILLS | AP9: =IFERROR(VLOOKUP(AN9,APR!$F$23:$H$38,3,FALSE),"")
C10: Planned | D10: Actual | V10: 3 | W10: =IFERROR(VLOOKUP(V10,$AM$3:$AP$65,2,FALSE),"") | X10: =IFERROR(VLOOKUP(V10,$AM$3:$AP$65,4,FALSE),"") | AM10: =IFERROR(_xlfn.RANK.EQ(AP10, $AP$3:$AP$150)+ COUNTIFS($AP$3:AP10, AP10) - 1,"") | AN10: =F30 | AO10: BILLS | AP10: =IFERROR(VLOOKUP(AN10,APR!$F$23:$H$38,3,FALSE),"")
B11: INCOME | C11: =SUM(APR!$C$23:$C$38) -> 0 | D11: =SUM(APR!$D$23:$D$38) -> 0 | V11: 4 | W11: =IFERROR(VLOOKUP(V11,$AM$3:$AP$65,2,FALSE),"") | X11: =IFERROR(VLOOKUP(V11,$AM$3:$AP$65,4,FALSE),"") | AM11: =IFERROR(_xlfn.RANK.EQ(AP11, $AP$3:$AP$150)+ COUNTIFS($AP$3:AP11, AP11) - 1,"") | AN11: =F31 | AO11: BILLS | AP11: =IFERROR(VLOOKUP(AN11,APR!$F$23:$H$38,3,FALSE),"")
B12: BILLS | C12: =SUM(APR!$G$23:$G$38) -> 0 | D12: =SUM(APR!$H$23:$H$38) -> 0 | V12: 5 | W12: =IFERROR(VLOOKUP(V12,$AM$3:$AP$65,2,FALSE),"") | X12: =IFERROR(VLOOKUP(V12,$AM$3:$AP$65,4,FALSE),"") | AM12: =IFERROR(_xlfn.RANK.EQ(AP12, $AP$3:$AP$150)+ COUNTIFS($AP$3:AP12, AP12) - 1,"") | AN12: =F32 | AO12: BILLS | AP12: =IFERROR(VLOOKUP(AN12,APR!$F$23:$H$38,3,FALSE),"")
B13: EXPENSES | C13: =SUM(APR!$L$23:$L$38) -> 0 | D13: =SUM(APR!$M$23:$M$38) -> 0 | V13: 6 | W13: =IFERROR(VLOOKUP(V13,$AM$3:$AP$65,2,FALSE),"") | X13: =IFERROR(VLOOKUP(V13,$AM$3:$AP$65,4,FALSE),"") | AM13: =IFERROR(_xlfn.RANK.EQ(AP13, $AP$3:$AP$150)+ COUNTIFS($AP$3:AP13, AP13) - 1,"") | AN13: =F33 | AO13: BILLS | AP13: =IFERROR(VLOOKUP(AN13,APR!$F$23:$H$38,3,FALSE),"")
B14: DEBT | C14: =SUM(APR!$Q$23:$Q$38) -> 0 | D14: =SUM(APR!$R$23:$R$38) -> 0 | V14: 7 | W14: =IFERROR(VLOOKUP(V14,$AM$3:$AP$65,2,FALSE),"") | X14: =IFERROR(VLOOKUP(V14,$AM$3:$AP$65,4,FALSE),"") | AM14: =IFERROR(_xlfn.RANK.EQ(AP14, $AP$3:$AP$150)+ COUNTIFS($AP$3:AP14, AP14) - 1,"") | AN14: =F34 | AO14: BILLS | AP14: =IFERROR(VLOOKUP(AN14,APR!$F$23:$H$38,3,FALSE),"")
B15: SAVINGS | C15: =SUM(APR!$V$23:$V$38) -> 0 | D15: =SUM(APR!$W$23:$W$38) -> 0 | V15: 8 | W15: =IFERROR(VLOOKUP(V15,$AM$3:$AP$65,2,FALSE),"") | X15: =IFERROR(VLOOKUP(V15,$AM$3:$AP$65,4,FALSE),"") | AM15: =IFERROR(_xlfn.RANK.EQ(AP15, $AP$3:$AP$150)+ COUNTIFS($AP$3:AP15, AP15) - 1,"") | AN15: =F35 | AO15: BILLS | AP15: =IFERROR(VLOOKUP(AN15,APR!$F$23:$H$38,3,FALSE),"")
B16: BALANCE | C16: =(C11-SUM(C12:C15)) -> 0 | D16: =(D11-SUM(D12:D15)) -> 0 | V16: 9 | W16: =IFERROR(VLOOKUP(V16,$AM$3:$AP$65,2,FALSE),"") | X16: =IFERROR(VLOOKUP(V16,$AM$3:$AP$65,4,FALSE),"") | AM16: =IFERROR(_xlfn.RANK.EQ(AP16, $AP$3:$AP$150)+ COUNTIFS($AP$3:AP16, AP16) - 1,"") | AN16: =F36 | AO16: BILLS | AP16: =IFERROR(VLOOKUP(AN16,APR!$F$23:$H$38,3,FALSE),"")
V17: 10 | W17: =IFERROR(VLOOKUP(V17,$AM$3:$AP$65,2,FALSE),"") | X17: =IFERROR(VLOOKUP(V17,$AM$3:$AP$65,4,FALSE),"") | AM17: =IFERROR(_xlfn.RANK.EQ(AP17, $AP$3:$AP$150)+ COUNTIFS($AP$3:AP17, AP17) - 1,"") | AN17: =F37 | AO17: BILLS | AP17: =IFERROR(VLOOKUP(AN17,APR!$F$23:$H$38,3,FALSE),"")
V18: 11 | W18: =IFERROR(VLOOKUP(V18,$AM$3:$AP$65,2,FALSE),"") | X18: =IFERROR(VLOOKUP(V18,$AM$3:$AP$65,4,FALSE),"") | AM18: =IFERROR(_xlfn.RANK.EQ(AP18, $AP$3:$AP$150)+ COUNTIFS($AP$3:AP18, AP18) - 1,"") | AN18: =F38 | AO18: BILLS | AP18: =IFERROR(VLOOKUP(AN18,APR!$F$23:$H$38,3,FALSE),"")
AM19: =IFERROR(_xlfn.RANK.EQ(AP19, $AP$3:$AP$150)+ COUNTIFS($AP$3:AP19, AP19) - 1,"") | AN19: =K23 | AO19: EXPENSES | AP19: =IFERROR(VLOOKUP(AN19,APR!$K$23:$M$38,3,FALSE),"")
B20: INCOME | F20: BILLS | K20: EXPENSES | P20: DEBT | U20: SAVINGS | AM20: =IFERROR(_xlfn.RANK.EQ(AP20, $AP$3:$AP$150)+ COUNTIFS($AP$3:AP20, AP20) - 1,"") | AN20: =K24 | AO20: EXPENSES | AP20: =IFERROR(VLOOKUP(AN20,APR!$K$23:$M$38,3,FALSE),"")
AM21: =IFERROR(_xlfn.RANK.EQ(AP21, $AP$3:$AP$150)+ COUNTIFS($AP$3:AP21, AP21) - 1,"") | AN21: =K25 | AO21: EXPENSES | AP21: =IFERROR(VLOOKUP(AN21,APR!$K$23:$M$38,3,FALSE),"")
B22: Details | C22: Planned | D22: Actual | F22: Details | G22: Planned | H22: Actual | I22: Variance | K22: Details | L22: Planned | M22: Actual | N22: Variance | P22: Details | Q22: Planned | R22: Actual | S22: Variance | U22: Details | V22: Planned | W22: Actual | X22: Variance | AM22: =IFERROR(_xlfn.RANK.EQ(AP22, $AP$3:$AP$150)+ COUNTIFS($AP$3:AP22, AP22) - 1,"") | AN22: =K26 | AO22: EXPENSES | AP22: =IFERROR(VLOOKUP(AN22,APR!$K$23:$M$38,3,FALSE),"")
I23: =APR!$G23-APR!$H23 -> 0 | N23: =APR!$L23-APR!$M23 -> 0 | S23: =APR!$Q23-APR!$R23 -> 0 | X23: =APR!$V23-APR!$W23 -> 0 | AM23: =IFERROR(_xlfn.RANK.EQ(AP23, $AP$3:$AP$150)+ COUNTIFS($AP$3:AP23, AP23) - 1,"") | AN23: =K27 | AO23: EXPENSES | AP23: =IFERROR(VLOOKUP(AN23,APR!$K$23:$M$38,3,FALSE),"")
I24: =APR!$G24-APR!$H24 -> 0 | N24: =APR!$L24-APR!$M24 -> 0 | S24: =APR!$Q24-APR!$R24 -> 0 | X24: =APR!$V24-APR!$W24 -> 0 | AM24: =IFERROR(_xlfn.RANK.EQ(AP24, $AP$3:$AP$150)+ COUNTIFS($AP$3:AP24, AP24) - 1,"") | AN24: =K28 | AO24: EXPENSES | AP24: =IFERROR(VLOOKUP(AN24,APR!$K$23:$M$38,3,FALSE),"")
I25: =APR!$G25-APR!$H25 -> 0 | N25: =APR!$L25-APR!$M25 -> 0 | S25: =APR!$Q25-APR!$R25 -> 0 | X25: =APR!$V25-APR!$W25 -> 0 | AM25: =IFERROR(_xlfn.RANK.EQ(AP25, $AP$3:$AP$150)+ COUNTIFS($AP$3:AP25, AP25) - 1,"") | AN25: =K29 | AO25: EXPENSES | AP25: =IFERROR(VLOOKUP(AN25,APR!$K$23:$M$38,3,FALSE),"")
I26: =APR!$G26-APR!$H26 -> 0 | N26: =APR!$L26-APR!$M26 -> 0 | S26: =APR!$Q26-APR!$R26 -> 0 | X26: =APR!$V26-APR!$W26 -> 0 | AM26: =IFERROR(_xlfn.RANK.EQ(AP26, $AP$3:$AP$150)+ COUNTIFS($AP$3:AP26, AP26) - 1,"") | AN26: =K30 | AO26: EXPENSES | AP26: =IFERROR(VLOOKUP(AN26,APR!$K$23:$M$38,3,FALSE),"")
I27: =APR!$G27-APR!$H27 -> 0 | N27: =APR!$L27-APR!$M27 -> 0 | S27: =APR!$Q27-APR!$R27 -> 0 | X27: =APR!$V27-APR!$W27 -> 0 | AM27: =IFERROR(_xlfn.RANK.EQ(AP27, $AP$3:$AP$150)+ COUNTIFS($AP$3:AP27, AP27) - 1,"") | AN27: =K31 | AO27: EXPENSES | AP27: =IFERROR(VLOOKUP(AN27,APR!$K$23:$M$38,3,FALSE),"")
I28: =APR!$G28-APR!$H28 -> 0 | N28: =APR!$L28-APR!$M28 -> 0 | S28: =APR!$Q28-APR!$R28 -> 0 | X28: =APR!$V28-APR!$W28 -> 0 | AM28: =IFERROR(_xlfn.RANK.EQ(AP28, $AP$3:$AP$150)+ COUNTIFS($AP$3:AP28, AP28) - 1,"") | AN28: =K32 | AO28: EXPENSES | AP28: =IFERROR(VLOOKUP(AN28,APR!$K$23:$M$38,3,FALSE),"")
I29: =APR!$G29-APR!$H29 -> 0 | N29: =APR!$L29-APR!$M29 -> 0 | S29: =APR!$Q29-APR!$R29 -> 0 | X29: =APR!$V29-APR!$W29 -> 0 | AM29: =IFERROR(_xlfn.RANK.EQ(AP29, $AP$3:$AP$150)+ COUNTIFS($AP$3:AP29, AP29) - 1,"") | AN29: =K33 | AO29: EXPENSES | AP29: =IFERROR(VLOOKUP(AN29,APR!$K$23:$M$38,3,FALSE),"")
I30: =APR!$G30-APR!$H30 -> 0 | N30: =APR!$L30-APR!$M30 -> 0 | S30: =APR!$Q30-APR!$R30 -> 0 | X30: =APR!$V30-APR!$W30 -> 0 | AM30: =IFERROR(_xlfn.RANK.EQ(AP30, $AP$3:$AP$150)+ COUNTIFS($AP$3:AP30, AP30) - 1,"") | AN30: =K34 | AO30: EXPENSES | AP30: =IFERROR(VLOOKUP(AN30,APR!$K$23:$M$38,3,FALSE),"")
I31: =APR!$G31-APR!$H31 -> 0 | N31: =APR!$L31-APR!$M31 -> 0 | S31: =APR!$Q31-APR!$R31 -> 0 | X31: =APR!$V31-APR!$W31 -> 0 | AM31: =IFERROR(_xlfn.RANK.EQ(AP31, $AP$3:$AP$150)+ COUNTIFS($AP$3:AP31, AP31) - 1,"") | AN31: =K35 | AO31: EXPENSES | AP31: =IFERROR(VLOOKUP(AN31,APR!$K$23:$M$38,3,FALSE),"")
I32: =APR!$G32-APR!$H32 -> 0 | N32: =APR!$L32-APR!$M32 -> 0 | S32: =APR!$Q32-APR!$R32 -> 0 | X32: =APR!$V32-APR!$W32 -> 0 | AM32: =IFERROR(_xlfn.RANK.EQ(AP32, $AP$3:$AP$150)+ COUNTIFS($AP$3:AP32, AP32) - 1,"") | AN32: =K36 | AO32: EXPENSES | AP32: =IFERROR(VLOOKUP(AN32,APR!$K$23:$M$38,3,FALSE),"")
I33: =APR!$G33-APR!$H33 -> 0 | N33: =APR!$L33-APR!$M33 -> 0 | S33: =APR!$Q33-APR!$R33 -> 0 | X33: =APR!$V33-APR!$W33 -> 0 | AM33: =IFERROR(_xlfn.RANK.EQ(AP33, $AP$3:$AP$150)+ COUNTIFS($AP$3:AP33, AP33) - 1,"") | AN33: =K37 | AO33: EXPENSES | AP33: =IFERROR(VLOOKUP(AN33,APR!$K$23:$M$38,3,FALSE),"")
I34: =APR!$G34-APR!$H34 -> 0 | N34: =APR!$L34-APR!$M34 -> 0 | S34: =APR!$Q34-APR!$R34 -> 0 | X34: =APR!$V34-APR!$W34 -> 0 | AM34: =IFERROR(_xlfn.RANK.EQ(AP34, $AP$3:$AP$150)+ COUNTIFS($AP$3:AP34, AP34) - 1,"") | AN34: =K38 | AO34: DEBTS | AP34: =IFERROR(VLOOKUP(AN34,APR!$K$23:$M$38,3,FALSE),"")
I35: =APR!$G35-APR!$H35 -> 0 | N35: =APR!$L35-APR!$M35 -> 0 | S35: =APR!$Q35-APR!$R35 -> 0 | X35: =APR!$V35-APR!$W35 -> 0 | AM35: =IFERROR(_xlfn.RANK.EQ(AP35, $AP$3:$AP$150)+ COUNTIFS($AP$3:AP35, AP35) - 1,"") | AN35: =P23 | AO35: DEBTS | AP35: =IFERROR(VLOOKUP(AN35,APR!$P$23:$R$38,3,FALSE),"")
I36: =APR!$G36-APR!$H36 -> 0 | N36: =APR!$L36-APR!$M36 -> 0 | S36: =APR!$Q36-APR!$R36 -> 0 | X36: =APR!$V36-APR!$W36 -> 0 | AM36: =IFERROR(_xlfn.RANK.EQ(AP36, $AP$3:$AP$150)+ COUNTIFS($AP$3:AP36, AP36) - 1,"") | AN36: =P24 | AO36: DEBTS | AP36: =IFERROR(VLOOKUP(AN36,APR!$P$23:$R$38,3,FALSE),"")
I37: =APR!$G37-APR!$H37 -> 0 | N37: =APR!$L37-APR!$M37 -> 0 | S37: =APR!$Q37-APR!$R37 -> 0 | X37: =APR!$V37-APR!$W37 -> 0 | AM37: =IFERROR(_xlfn.RANK.EQ(AP37, $AP$3:$AP$150)+ COUNTIFS($AP$3:AP37, AP37) - 1,"") | AN37: =P25 | AO37: DEBTS | AP37: =IFERROR(VLOOKUP(AN37,APR!$P$23:$R$38,3,FALSE),"")
I38: =APR!$G38-APR!$H38 -> 0 | N38: =APR!$L38-APR!$M38 -> 0 | S38: =APR!$Q38-APR!$R38 -> 0 | X38: =APR!$V38-APR!$W38 -> 0 | AM38: =IFERROR(_xlfn.RANK.EQ(AP38, $AP$3:$AP$150)+ COUNTIFS($AP$3:AP38, AP38) - 1,"") | AN38: =P26 | AO38: DEBTS | AP38: =IFERROR(VLOOKUP(AN38,APR!$P$23:$R$38,3,FALSE),"")
AM39: =IFERROR(_xlfn.RANK.EQ(AP39, $AP$3:$AP$150)+ COUNTIFS($AP$3:AP39, AP39) - 1,"") | AN39: =P27 | AO39: DEBTS | AP39: =IFERROR(VLOOKUP(AN39,APR!$P$23:$R$38,3,FALSE),"")
AM40: =IFERROR(_xlfn.RANK.EQ(AP40, $AP$3:$AP$150)+ COUNTIFS($AP$3:AP40, AP40) - 1,"") | AN40: =P28 | AO40: DEBTS | AP40: =IFERROR(VLOOKUP(AN40,APR!$P$23:$R$38,3,FALSE),"")
AM41: =IFERROR(_xlfn.RANK.EQ(AP41, $AP$3:$AP$150)+ COUNTIFS($AP$3:AP41, AP41) - 1,"") | AN41: =P29 | AO41: DEBTS | AP41: =IFERROR(VLOOKUP(AN41,APR!$P$23:$R$38,3,FALSE),"")
AM42: =IFERROR(_xlfn.RANK.EQ(AP42, $AP$3:$AP$150)+ COUNTIFS($AP$3:AP42, AP42) - 1,"") | AN42: =P30 | AO42: DEBTS | AP42: =IFERROR(VLOOKUP(AN42,APR!$P$23:$R$38,3,FALSE),"")
AM43: =IFERROR(_xlfn.RANK.EQ(AP43, $AP$3:$AP$150)+ COUNTIFS($AP$3:AP43, AP43) - 1,"") | AN43: =P31 | AO43: DEBTS | AP43: =IFERROR(VLOOKUP(AN43,APR!$P$23:$R$38,3,FALSE),"")
AM44: =IFERROR(_xlfn.RANK.EQ(AP44, $AP$3:$AP$150)+ COUNTIFS($AP$3:AP44, AP44) - 1,"") | AN44: =P32 | AO44: DEBTS | AP44: =IFERROR(VLOOKUP(AN44,APR!$P$23:$R$38,3,FALSE),"")
AM45: =IFERROR(_xlfn.RANK.EQ(AP45, $AP$3:$AP$150)+ COUNTIFS($AP$3:AP45, AP45) - 1,"") | AN45: =P33 | AO45: DEBTS | AP45: =IFERROR(VLOOKUP(AN45,APR!$P$23:$R$38,3,FALSE),"")
AM46: =IFERROR(_xlfn.RANK.EQ(AP46, $AP$3:$AP$150)+ COUNTIFS($AP$3:AP46, AP46) - 1,"") | AN46: =P34 | AO46: DEBTS | AP46: =IFERROR(VLOOKUP(AN46,APR!$P$23:$R$38,3,FALSE),"")
AM47: =IFERROR(_xlfn.RANK.EQ(AP47, $AP$3:$AP$150)+ COUNTIFS($AP$3:AP47, AP47) - 1,"") | AN47: =P35 | AO47: DEBTS | AP47: =IFERROR(VLOOKUP(AN47,APR!$P$23:$R$38,3,FALSE),"")
AM48: =IFERROR(_xlfn.RANK.EQ(AP48, $AP$3:$AP$150)+ COUNTIFS($AP$3:AP48, AP48) - 1,"") | AN48: =P36 | AO48: DEBTS | AP48: =IFERROR(VLOOKUP(AN48,APR!$P$23:$R$38,3,FALSE),"")
AM49: =IFERROR(_xlfn.RANK.EQ(AP49, $AP$3:$AP$150)+ COUNTIFS($AP$3:AP49, AP49) - 1,"") | AN49: =P37 | AO49: SAVINGS | AP49: =IFERROR(VLOOKUP(AN49,APR!$P$23:$R$38,3,FALSE),"")
AM50: =IFERROR(_xlfn.RANK.EQ(AP50, $AP$3:$AP$150)+ COUNTIFS($AP$3:AP50, AP50) - 1,"") | AN50: =U23 | AO50: SAVINGS | AP50: =IFERROR(VLOOKUP(AN50,APR!$U$23:$W$38,3,FALSE),"")
AM51: =IFERROR(_xlfn.RANK.EQ(AP51, $AP$3:$AP$150)+ COUNTIFS($AP$3:AP51, AP51) - 1,"") | AN51: =U24 | AO51: SAVINGS | AP51: =IFERROR(VLOOKUP(AN51,APR!$U$23:$W$38,3,FALSE),"")
AM52: =IFERROR(_xlfn.RANK.EQ(AP52, $AP$3:$AP$150)+ COUNTIFS($AP$3:AP52, AP52) - 1,"") | AN52: =U25 | AO52: SAVINGS | AP52: =IFERROR(VLOOKUP(AN52,APR!$U$23:$W$38,3,FALSE),"")
AM53: =IFERROR(_xlfn.RANK.EQ(AP53, $AP$3:$AP$150)+ COUNTIFS($AP$3:AP53, AP53) - 1,"") | AN53: =U26 | AO53: SAVINGS | AP53: =IFERROR(VLOOKUP(AN53,APR!$U$23:$W$38,3,FALSE),"")
AM54: =IFERROR(_xlfn.RANK.EQ(AP54, $AP$3:$AP$150)+ COUNTIFS($AP$3:AP54, AP54) - 1,"") | AN54: =U27 | AO54: SAVINGS | AP54: =IFERROR(VLOOKUP(AN54,APR!$U$23:$W$38,3,FALSE),"")
AM55: =IFERROR(_xlfn.RANK.EQ(AP55, $AP$3:$AP$150)+ COUNTIFS($AP$3:AP55, AP55) - 1,"") | AN55: =U28 | AO55: SAVINGS | AP55: =IFERROR(VLOOKUP(AN55,APR!$U$23:$W$38,3,FALSE),"")
AM56: =IFERROR(_xlfn.RANK.EQ(AP56, $AP$3:$AP$150)+ COUNTIFS($AP$3:AP56, AP56) - 1,"") | AN56: =U29 | AO56: SAVINGS | AP56: =IFERROR(VLOOKUP(AN56,APR!$U$23:$W$38,3,FALSE),"")
AM57: =IFERROR(_xlfn.RANK.EQ(AP57, $AP$3:$AP$150)+ COUNTIFS($AP$3:AP57, AP57) - 1,"") | AN57: =U30 | AO57: SAVINGS | AP57: =IFERROR(VLOOKUP(AN57,APR!$U$23:$W$38,3,FALSE),"")
AM58: =IFERROR(_xlfn.RANK.EQ(AP58, $AP$3:$AP$150)+ COUNTIFS($AP$3:AP58, AP58) - 1,"") | AN58: =U31 | AO58: SAVINGS | AP58: =IFERROR(VLOOKUP(AN58,APR!$U$23:$W$38,3,FALSE),"")
AM59: =IFERROR(_xlfn.RANK.EQ(AP59, $AP$3:$AP$150)+ COUNTIFS($AP$3:AP59, AP59) - 1,"") | AN59: =U32 | AO59: SAVINGS | AP59: =IFERROR(VLOOKUP(AN59,APR!$U$23:$W$38,3,FALSE),"")
AM60: =IFERROR(_xlfn.RANK.EQ(AP60, $AP$3:$AP$150)+ COUNTIFS($AP$3:AP60, AP60) - 1,"") | AN60: =U33 | AO60: SAVINGS | AP60: =IFERROR(VLOOKUP(AN60,APR!$U$23:$W$38,3,FALSE),"")
AM61: =IFERROR(_xlfn.RANK.EQ(AP61, $AP$3:$AP$150)+ COUNTIFS($AP$3:AP61, AP61) - 1,"") | AN61: =U34 | AO61: SAVINGS | AP61: =IFERROR(VLOOKUP(AN61,APR!$U$23:$W$38,3,FALSE),"")
... AM65: =IFERROR(_xlfn.RANK.EQ(AP65, $AP$3:$AP$150)+ COUNTIFS($AP$3:AP65, AP65) - 1,"") | AN65: =U38 | AO65: SAVINGS | AP65: =IFERROR(VLOOKUP(AN65,APR!$U$23:$W$38,3,FALSE),"")

Sheet MAY
B2: MAY | F2: INCOME | J2: BILLS | N2: EXPENSES | R2: DEBT | V2: SAVINGS | AM2: Ranking | AN2: ITEM | AO2: CATEGORY | AP2: TOTAL SPENT
AM3: =IFERROR(_xlfn.RANK.EQ(AP3, $AP$3:$AP$150)+ COUNTIFS($AP$3:AP3, AP3) - 1,"") | AN3: =F23 | AO3: BILLS | AP3: =IFERROR(VLOOKUP(AN3,MAY!$F$23:$H$38,3,FALSE),"")
F4: =SUM(MAY!$D$23:$D$38) -> 0 | J4: =SUM(MAY!$H$23:$H$38) -> 0 | N4: =SUM(MAY!$M$23:$M$38) -> 0 | R4: =SUM(MAY!$R$23:$R$38) -> 0 | V4: =SUM(MAY!$W$23:$W$38) -> 0 | AM4: =IFERROR(_xlfn.RANK.EQ(AP4, $AP$3:$AP$150)+ COUNTIFS($AP$3:AP4, AP4) - 1,"") | AN4: =F24 | AO4: BILLS | AP4: =IFERROR(VLOOKUP(AN4,MAY!$F$23:$H$38,3,FALSE),"")
B5: SUMMARY | AM5: =IFERROR(_xlfn.RANK.EQ(AP5, $AP$3:$AP$150)+ COUNTIFS($AP$3:AP5, AP5) - 1,"") | AN5: =F25 | AO5: BILLS | AP5: =IFERROR(VLOOKUP(AN5,MAY!$F$23:$H$38,3,FALSE),"")
AM6: =IFERROR(_xlfn.RANK.EQ(AP6, $AP$3:$AP$150)+ COUNTIFS($AP$3:AP6, AP6) - 1,"") | AN6: =F26 | AO6: BILLS | AP6: =IFERROR(VLOOKUP(AN6,MAY!$F$23:$H$38,3,FALSE),"")
B7: INCOME OVERVIEW | V7: RANK | W7: ITEM | X7: AMOUNT | AM7: =IFERROR(_xlfn.RANK.EQ(AP7, $AP$3:$AP$150)+ COUNTIFS($AP$3:AP7, AP7) - 1,"") | AN7: =F27 | AO7: BILLS | AP7: =IFERROR(VLOOKUP(AN7,MAY!$F$23:$H$38,3,FALSE),"")
V8: 1 | W8: =IFERROR(VLOOKUP(V8,$AM$3:$AP$65,2,FALSE),"") | X8: =IFERROR(VLOOKUP(V8,$AM$3:$AP$65,4,FALSE),"") | AM8: =IFERROR(_xlfn.RANK.EQ(AP8, $AP$3:$AP$150)+ COUNTIFS($AP$3:AP8, AP8) - 1,"") | AN8: =F28 | AO8: BILLS | AP8: =IFERROR(VLOOKUP(AN8,MAY!$F$23:$H$38,3,FALSE),"")
V9: 2 | W9: =IFERROR(VLOOKUP(V9,$AM$3:$AP$65,2,FALSE),"") | X9: =IFERROR(VLOOKUP(V9,$AM$3:$AP$65,4,FALSE),"") | AM9: =IFERROR(_xlfn.RANK.EQ(AP9, $AP$3:$AP$150)+ COUNTIFS($AP$3:AP9, AP9) - 1,"") | AN9: =F29 | AO9: BILLS | AP9: =IFERROR(VLOOKUP(AN9,MAY!$F$23:$H$38,3,FALSE),"")
C10: Planned | D10: Actual | V10: 3 | W10: =IFERROR(VLOOKUP(V10,$AM$3:$AP$65,2,FALSE),"") | X10: =IFERROR(VLOOKUP(V10,$AM$3:$AP$65,4,FALSE),"") | AM10: =IFERROR(_xlfn.RANK.EQ(AP10, $AP$3:$AP$150)+ COUNTIFS($AP$3:AP10, AP10) - 1,"") | AN10: =F30 | AO10: BILLS | AP10: =IFERROR(VLOOKUP(AN10,MAY!$F$23:$H$38,3,FALSE),"")
B11: INCOME | C11: =SUM(MAY!$C$23:$C$38) -> 0 | D11: =SUM(MAY!$D$23:$D$38) -> 0 | V11: 4 | W11: =IFERROR(VLOOKUP(V11,$AM$3:$AP$65,2,FALSE),"") | X11: =IFERROR(VLOOKUP(V11,$AM$3:$AP$65,4,FALSE),"") | AM11: =IFERROR(_xlfn.RANK.EQ(AP11, $AP$3:$AP$150)+ COUNTIFS($AP$3:AP11, AP11) - 1,"") | AN11: =F31 | AO11: BILLS | AP11: =IFERROR(VLOOKUP(AN11,MAY!$F$23:$H$38,3,FALSE),"")
B12: BILLS | C12: =SUM(MAY!$G$23:$G$38) -> 0 | D12: =SUM(MAY!$H$23:$H$38) -> 0 | V12: 5 | W12: =IFERROR(VLOOKUP(V12,$AM$3:$AP$65,2,FALSE),"") | X12: =IFERROR(VLOOKUP(V12,$AM$3:$AP$65,4,FALSE),"") | AM12: =IFERROR(_xlfn.RANK.EQ(AP12, $AP$3:$AP$150)+ COUNTIFS($AP$3:AP12, AP12) - 1,"") | AN12: =F32 | AO12: BILLS | AP12: =IFERROR(VLOOKUP(AN12,MAY!$F$23:$H$38,3,FALSE),"")
B13: EXPENSES | C13: =SUM(MAY!$L$23:$L$38) -> 0 | D13: =SUM(MAY!$M$23:$M$38) -> 0 | V13: 6 | W13: =IFERROR(VLOOKUP(V13,$AM$3:$AP$65,2,FALSE),"") | X13: =IFERROR(VLOOKUP(V13,$AM$3:$AP$65,4,FALSE),"") | AM13: =IFERROR(_xlfn.RANK.EQ(AP13, $AP$3:$AP$150)+ COUNTIFS($AP$3:AP13, AP13) - 1,"") | AN13: =F33 | AO13: BILLS | AP13: =IFERROR(VLOOKUP(AN13,MAY!$F$23:$H$38,3,FALSE),"")
B14: DEBT | C14: =SUM(MAY!$Q$23:$Q$38) -> 0 | D14: =SUM(MAY!$R$23:$R$38) -> 0 | V14: 7 | W14: =IFERROR(VLOOKUP(V14,$AM$3:$AP$65,2,FALSE),"") | X14: =IFERROR(VLOOKUP(V14,$AM$3:$AP$65,4,FALSE),"") | AM14: =IFERROR(_xlfn.RANK.EQ(AP14, $AP$3:$AP$150)+ COUNTIFS($AP$3:AP14, AP14) - 1,"") | AN14: =F34 | AO14: BILLS | AP14: =IFERROR(VLOOKUP(AN14,MAY!$F$23:$H$38,3,FALSE),"")
B15: SAVINGS | C15: =SUM(MAY!$V$23:$V$38) -> 0 | D15: =SUM(MAY!$W$23:$W$38) -> 0 | V15: 8 | W15: =IFERROR(VLOOKUP(V15,$AM$3:$AP$65,2,FALSE),"") | X15: =IFERROR(VLOOKUP(V15,$AM$3:$AP$65,4,FALSE),"") | AM15: =IFERROR(_xlfn.RANK.EQ(AP15, $AP$3:$AP$150)+ COUNTIFS($AP$3:AP15, AP15) - 1,"") | AN15: =F35 | AO15: BILLS | AP15: =IFERROR(VLOOKUP(AN15,MAY!$F$23:$H$38,3,FALSE),"")
B16: BALANCE | C16: =(C11-SUM(C12:C15)) -> 0 | D16: =(D11-SUM(D12:D15)) -> 0 | V16: 9 | W16: =IFERROR(VLOOKUP(V16,$AM$3:$AP$65,2,FALSE),"") | X16: =IFERROR(VLOOKUP(V16,$AM$3:$AP$65,4,FALSE),"") | AM16: =IFERROR(_xlfn.RANK.EQ(AP16, $AP$3:$AP$150)+ COUNTIFS($AP$3:AP16, AP16) - 1,"") | AN16: =F36 | AO16: BILLS | AP16: =IFERROR(VLOOKUP(AN16,MAY!$F$23:$H$38,3,FALSE),"")
V17: 10 | W17: =IFERROR(VLOOKUP(V17,$AM$3:$AP$65,2,FALSE),"") | X17: =IFERROR(VLOOKUP(V17,$AM$3:$AP$65,4,FALSE),"") | AM17: =IFERROR(_xlfn.RANK.EQ(AP17, $AP$3:$AP$150)+ COUNTIFS($AP$3:AP17, AP17) - 1,"") | AN17: =F37 | AO17: BILLS | AP17: =IFERROR(VLOOKUP(AN17,MAY!$F$23:$H$38,3,FALSE),"")
V18: 11 | W18: =IFERROR(VLOOKUP(V18,$AM$3:$AP$65,2,FALSE),"") | X18: =IFERROR(VLOOKUP(V18,$AM$3:$AP$65,4,FALSE),"") | AM18: =IFERROR(_xlfn.RANK.EQ(AP18, $AP$3:$AP$150)+ COUNTIFS($AP$3:AP18, AP18) - 1,"") | AN18: =F38 | AO18: BILLS | AP18: =IFERROR(VLOOKUP(AN18,MAY!$F$23:$H$38,3,FALSE),"")
AM19: =IFERROR(_xlfn.RANK.EQ(AP19, $AP$3:$AP$150)+ COUNTIFS($AP$3:AP19, AP19) - 1,"") | AN19: =K23 | AO19: EXPENSES | AP19: =IFERROR(VLOOKUP(AN19,MAY!$K$23:$M$38,3,FALSE),"")
B20: INCOME | F20: BILLS | K20: EXPENSES | P20: DEBT | U20: SAVINGS | AM20: =IFERROR(_xlfn.RANK.EQ(AP20, $AP$3:$AP$150)+ COUNTIFS($AP$3:AP20, AP20) - 1,"") | AN20: =K24 | AO20: EXPENSES | AP20: =IFERROR(VLOOKUP(AN20,MAY!$K$23:$M$38,3,FALSE),"")
AM21: =IFERROR(_xlfn.RANK.EQ(AP21, $AP$3:$AP$150)+ COUNTIFS($AP$3:AP21, AP21) - 1,"") | AN21: =K25 | AO21: EXPENSES | AP21: =IFERROR(VLOOKUP(AN21,MAY!$K$23:$M$38,3,FALSE),"")
B22: Details | C22: Planned | D22: Actual | F22: Details | G22: Planned | H22: Actual | I22: Variance | K22: Details | L22: Planned | M22: Actual | N22: Variance | P22: Details | Q22: Planned | R22: Actual | S22: Variance | U22: Details | V22: Planned | W22: Actual | X22: Variance | AM22: =IFERROR(_xlfn.RANK.EQ(AP22, $AP$3:$AP$150)+ COUNTIFS($AP$3:AP22, AP22) - 1,"") | AN22: =K26 | AO22: EXPENSES | AP22: =IFERROR(VLOOKUP(AN22,MAY!$K$23:$M$38,3,FALSE),"")
I23: =MAY!$G23-MAY!$H23 -> 0 | N23: =MAY!$L23-MAY!$M23 -> 0 | S23: =MAY!$Q23-MAY!$R23 -> 0 | X23: =MAY!$V23-MAY!$W23 -> 0 | AM23: =IFERROR(_xlfn.RANK.EQ(AP23, $AP$3:$AP$150)+ COUNTIFS($AP$3:AP23, AP23) - 1,"") | AN23: =K27 | AO23: EXPENSES | AP23: =IFERROR(VLOOKUP(AN23,MAY!$K$23:$M$38,3,FALSE),"")
I24: =MAY!$G24-MAY!$H24 -> 0 | N24: =MAY!$L24-MAY!$M24 -> 0 | S24: =MAY!$Q24-MAY!$R24 -> 0 | X24: =MAY!$V24-MAY!$W24 -> 0 | AM24: =IFERROR(_xlfn.RANK.EQ(AP24, $AP$3:$AP$150)+ COUNTIFS($AP$3:AP24, AP24) - 1,"") | AN24: =K28 | AO24: EXPENSES | AP24: =IFERROR(VLOOKUP(AN24,MAY!$K$23:$M$38,3,FALSE),"")
I25: =MAY!$G25-MAY!$H25 -> 0 | N25: =MAY!$L25-MAY!$M25 -> 0 | S25: =MAY!$Q25-MAY!$R25 -> 0 | X25: =MAY!$V25-MAY!$W25 -> 0 | AM25: =IFERROR(_xlfn.RANK.EQ(AP25, $AP$3:$AP$150)+ COUNTIFS($AP$3:AP25, AP25) - 1,"") | AN25: =K29 | AO25: EXPENSES | AP25: =IFERROR(VLOOKUP(AN25,MAY!$K$23:$M$38,3,FALSE),"")
I26: =MAY!$G26-MAY!$H26 -> 0 | N26: =MAY!$L26-MAY!$M26 -> 0 | S26: =MAY!$Q26-MAY!$R26 -> 0 | X26: =MAY!$V26-MAY!$W26 -> 0 | AM26: =IFERROR(_xlfn.RANK.EQ(AP26, $AP$3:$AP$150)+ COUNTIFS($AP$3:AP26, AP26) - 1,"") | AN26: =K30 | AO26: EXPENSES | AP26: =IFERROR(VLOOKUP(AN26,MAY!$K$23:$M$38,3,FALSE),"")
I27: =MAY!$G27-MAY!$H27 -> 0 | N27: =MAY!$L27-MAY!$M27 -> 0 | S27: =MAY!$Q27-MAY!$R27 -> 0 | X27: =MAY!$V27-MAY!$W27 -> 0 | AM27: =IFERROR(_xlfn.RANK.EQ(AP27, $AP$3:$AP$150)+ COUNTIFS($AP$3:AP27, AP27) - 1,"") | AN27: =K31 | AO27: EXPENSES | AP27: =IFERROR(VLOOKUP(AN27,MAY!$K$23:$M$38,3,FALSE),"")
I28: =MAY!$G28-MAY!$H28 -> 0 | N28: =MAY!$L28-MAY!$M28 -> 0 | S28: =MAY!$Q28-MAY!$R28 -> 0 | X28: =MAY!$V28-MAY!$W28 -> 0 | AM28: =IFERROR(_xlfn.RANK.EQ(AP28, $AP$3:$AP$150)+ COUNTIFS($AP$3:AP28, AP28) - 1,"") | AN28: =K32 | AO28: EXPENSES | AP28: =IFERROR(VLOOKUP(AN28,MAY!$K$23:$M$38,3,FALSE),"")
I29: =MAY!$G29-MAY!$H29 -> 0 | N29: =MAY!$L29-MAY!$M29 -> 0 | S29: =MAY!$Q29-MAY!$R29 -> 0 | X29: =MAY!$V29-MAY!$W29 -> 0 | AM29: =IFERROR(_xlfn.RANK.EQ(AP29, $AP$3:$AP$150)+ COUNTIFS($AP$3:AP29, AP29) - 1,"") | AN29: =K33 | AO29: EXPENSES | AP29: =IFERROR(VLOOKUP(AN29,MAY!$K$23:$M$38,3,FALSE),"")
I30: =MAY!$G30-MAY!$H30 -> 0 | N30: =MAY!$L30-MAY!$M30 -> 0 | S30: =MAY!$Q30-MAY!$R30 -> 0 | X30: =MAY!$V30-MAY!$W30 -> 0 | AM30: =IFERROR(_xlfn.RANK.EQ(AP30, $AP$3:$AP$150)+ COUNTIFS($AP$3:AP30, AP30) - 1,"") | AN30: =K34 | AO30: EXPENSES | AP30: =IFERROR(VLOOKUP(AN30,MAY!$K$23:$M$38,3,FALSE),"")
I31: =MAY!$G31-MAY!$H31 -> 0 | N31: =MAY!$L31-MAY!$M31 -> 0 | S31: =MAY!$Q31-MAY!$R31 -> 0 | X31: =MAY!$V31-MAY!$W31 -> 0 | AM31: =IFERROR(_xlfn.RANK.EQ(AP31, $AP$3:$AP$150)+ COUNTIFS($AP$3:AP31, AP31) - 1,"") | AN31: =K35 | AO31: EXPENSES | AP31: =IFERROR(VLOOKUP(AN31,MAY!$K$23:$M$38,3,FALSE),"")
I32: =MAY!$G32-MAY!$H32 -> 0 | N32: =MAY!$L32-MAY!$M32 -> 0 | S32: =MAY!$Q32-MAY!$R32 -> 0 | X32: =MAY!$V32-MAY!$W32 -> 0 | AM32: =IFERROR(_xlfn.RANK.EQ(AP32, $AP$3:$AP$150)+ COUNTIFS($AP$3:AP32, AP32) - 1,"") | AN32: =K36 | AO32: EXPENSES | AP32: =IFERROR(VLOOKUP(AN32,MAY!$K$23:$M$38,3,FALSE),"")
I33: =MAY!$G33-MAY!$H33 -> 0 | N33: =MAY!$L33-MAY!$M33 -> 0 | S33: =MAY!$Q33-MAY!$R33 -> 0 | X33: =MAY!$V33-MAY!$W33 -> 0 | AM33: =IFERROR(_xlfn.RANK.EQ(AP33, $AP$3:$AP$150)+ COUNTIFS($AP$3:AP33, AP33) - 1,"") | AN33: =K37 | AO33: EXPENSES | AP33: =IFERROR(VLOOKUP(AN33,MAY!$K$23:$M$38,3,FALSE),"")
I34: =MAY!$G34-MAY!$H34 -> 0 | N34: =MAY!$L34-MAY!$M34 -> 0 | S34: =MAY!$Q34-MAY!$R34 -> 0 | X34: =MAY!$V34-MAY!$W34 -> 0 | AM34: =IFERROR(_xlfn.RANK.EQ(AP34, $AP$3:$AP$150)+ COUNTIFS($AP$3:AP34, AP34) - 1,"") | AN34: =K38 | AO34: DEBTS | AP34: =IFERROR(VLOOKUP(AN34,MAY!$K$23:$M$38,3,FALSE),"")
I35: =MAY!$G35-MAY!$H35 -> 0 | N35: =MAY!$L35-MAY!$M35 -> 0 | S35: =MAY!$Q35-MAY!$R35 -> 0 | X35: =MAY!$V35-MAY!$W35 -> 0 | AM35: =IFERROR(_xlfn.RANK.EQ(AP35, $AP$3:$AP$150)+ COUNTIFS($AP$3:AP35, AP35) - 1,"") | AN35: =P23 | AO35: DEBTS | AP35: =IFERROR(VLOOKUP(AN35,MAY!$P$23:$R$38,3,FALSE),"")
I36: =MAY!$G36-MAY!$H36 -> 0 | N36: =MAY!$L36-MAY!$M36 -> 0 | S36: =MAY!$Q36-MAY!$R36 -> 0 | X36: =MAY!$V36-MAY!$W36 -> 0 | AM36: =IFERROR(_xlfn.RANK.EQ(AP36, $AP$3:$AP$150)+ COUNTIFS($AP$3:AP36, AP36) - 1,"") | AN36: =P24 | AO36: DEBTS | AP36: =IFERROR(VLOOKUP(AN36,MAY!$P$23:$R$38,3,FALSE),"")
I37: =MAY!$G37-MAY!$H37 -> 0 | N37: =MAY!$L37-MAY!$M37 -> 0 | S37: =MAY!$Q37-MAY!$R37 -> 0 | X37: =MAY!$V37-MAY!$W37 -> 0 | AM37: =IFERROR(_xlfn.RANK.EQ(AP37, $AP$3:$AP$150)+ COUNTIFS($AP$3:AP37, AP37) - 1,"") | AN37: =P25 | AO37: DEBTS | AP37: =IFERROR(VLOOKUP(AN37,MAY!$P$23:$R$38,3,FALSE),"")
I38: =MAY!$G38-MAY!$H38 -> 0 | N38: =MAY!$L38-MAY!$M38 -> 0 | S38: =MAY!$Q38-MAY!$R38 -> 0 | X38: =MAY!$V38-MAY!$W38 -> 0 | AM38: =IFERROR(_xlfn.RANK.EQ(AP38, $AP$3:$AP$150)+ COUNTIFS($AP$3:AP38, AP38) - 1,"") | AN38: =P26 | AO38: DEBTS | AP38: =IFERROR(VLOOKUP(AN38,MAY!$P$23:$R$38,3,FALSE),"")
AM39: =IFERROR(_xlfn.RANK.EQ(AP39, $AP$3:$AP$150)+ COUNTIFS($AP$3:AP39, AP39) - 1,"") | AN39: =P27 | AO39: DEBTS | AP39: =IFERROR(VLOOKUP(AN39,MAY!$P$23:$R$38,3,FALSE),"")
AM40: =IFERROR(_xlfn.RANK.EQ(AP40, $AP$3:$AP$150)+ COUNTIFS($AP$3:AP40, AP40) - 1,"") | AN40: =P28 | AO40: DEBTS | AP40: =IFERROR(VLOOKUP(AN40,MAY!$P$23:$R$38,3,FALSE),"")
AM41: =IFERROR(_xlfn.RANK.EQ(AP41, $AP$3:$AP$150)+ COUNTIFS($AP$3:AP41, AP41) - 1,"") | AN41: =P29 | AO41: DEBTS | AP41: =IFERROR(VLOOKUP(AN41,MAY!$P$23:$R$38,3,FALSE),"")
AM42: =IFERROR(_xlfn.RANK.EQ(AP42, $AP$3:$AP$150)+ COUNTIFS($AP$3:AP42, AP42) - 1,"") | AN42: =P30 | AO42: DEBTS | AP42: =IFERROR(VLOOKUP(AN42,MAY!$P$23:$R$38,3,FALSE),"")
AM43: =IFERROR(_xlfn.RANK.EQ(AP43, $AP$3:$AP$150)+ COUNTIFS($AP$3:AP43, AP43) - 1,"") | AN43: =P31 | AO43: DEBTS | AP43: =IFERROR(VLOOKUP(AN43,MAY!$P$23:$R$38,3,FALSE),"")
AM44: =IFERROR(_xlfn.RANK.EQ(AP44, $AP$3:$AP$150)+ COUNTIFS($AP$3:AP44, AP44) - 1,"") | AN44: =P32 | AO44: DEBTS | AP44: =IFERROR(VLOOKUP(AN44,MAY!$P$23:$R$38,3,FALSE),"")
AM45: =IFERROR(_xlfn.RANK.EQ(AP45, $AP$3:$AP$150)+ COUNTIFS($AP$3:AP45, AP45) - 1,"") | AN45: =P33 | AO45: DEBTS | AP45: =IFERROR(VLOOKUP(AN45,MAY!$P$23:$R$38,3,FALSE),"")
AM46: =IFERROR(_xlfn.RANK.EQ(AP46, $AP$3:$AP$150)+ COUNTIFS($AP$3:AP46, AP46) - 1,"") | AN46: =P34 | AO46: DEBTS | AP46: =IFERROR(VLOOKUP(AN46,MAY!$P$23:$R$38,3,FALSE),"")
AM47: =IFERROR(_xlfn.RANK.EQ(AP47, $AP$3:$AP$150)+ COUNTIFS($AP$3:AP47, AP47) - 1,"") | AN47: =P35 | AO47: DEBTS | AP47: =IFERROR(VLOOKUP(AN47,MAY!$P$23:$R$38,3,FALSE),"")
AM48: =IFERROR(_xlfn.RANK.EQ(AP48, $AP$3:$AP$150)+ COUNTIFS($AP$3:AP48, AP48) - 1,"") | AN48: =P36 | AO48: DEBTS | AP48: =IFERROR(VLOOKUP(AN48,MAY!$P$23:$R$38,3,FALSE),"")
AM49: =IFERROR(_xlfn.RANK.EQ(AP49, $AP$3:$AP$150)+ COUNTIFS($AP$3:AP49, AP49) - 1,"") | AN49: =P37 | AO49: SAVINGS | AP49: =IFERROR(VLOOKUP(AN49,MAY!$P$23:$R$38,3,FALSE),"")
AM50: =IFERROR(_xlfn.RANK.EQ(AP50, $AP$3:$AP$150)+ COUNTIFS($AP$3:AP50, AP50) - 1,"") | AN50: =U23 | AO50: SAVINGS | AP50: =IFERROR(VLOOKUP(AN50,MAY!$U$23:$W$38,3,FALSE),"")
AM51: =IFERROR(_xlfn.RANK.EQ(AP51, $AP$3:$AP$150)+ COUNTIFS($AP$3:AP51, AP51) - 1,"") | AN51: =U24 | AO51: SAVINGS | AP51: =IFERROR(VLOOKUP(AN51,MAY!$U$23:$W$38,3,FALSE),"")
AM52: =IFERROR(_xlfn.RANK.EQ(AP52, $AP$3:$AP$150)+ COUNTIFS($AP$3:AP52, AP52) - 1,"") | AN52: =U25 | AO52: SAVINGS | AP52: =IFERROR(VLOOKUP(AN52,MAY!$U$23:$W$38,3,FALSE),"")
AM53: =IFERROR(_xlfn.RANK.EQ(AP53, $AP$3:$AP$150)+ COUNTIFS($AP$3:AP53, AP53) - 1,"") | AN53: =U26 | AO53: SAVINGS | AP53: =IFERROR(VLOOKUP(AN53,MAY!$U$23:$W$38,3,FALSE),"")
AM54: =IFERROR(_xlfn.RANK.EQ(AP54, $AP$3:$AP$150)+ COUNTIFS($AP$3:AP54, AP54) - 1,"") | AN54: =U27 | AO54: SAVINGS | AP54: =IFERROR(VLOOKUP(AN54,MAY!$U$23:$W$38,3,FALSE),"")
AM55: =IFERROR(_xlfn.RANK.EQ(AP55, $AP$3:$AP$150)+ COUNTIFS($AP$3:AP55, AP55) - 1,"") | AN55: =U28 | AO55: SAVINGS | AP55: =IFERROR(VLOOKUP(AN55,MAY!$U$23:$W$38,3,FALSE),"")
AM56: =IFERROR(_xlfn.RANK.EQ(AP56, $AP$3:$AP$150)+ COUNTIFS($AP$3:AP56, AP56) - 1,"") | AN56: =U29 | AO56: SAVINGS | AP56: =IFERROR(VLOOKUP(AN56,MAY!$U$23:$W$38,3,FALSE),"")
AM57: =IFERROR(_xlfn.RANK.EQ(AP57, $AP$3:$AP$150)+ COUNTIFS($AP$3:AP57, AP57) - 1,"") | AN57: =U30 | AO57: SAVINGS | AP57: =IFERROR(VLOOKUP(AN57,MAY!$U$23:$W$38,3,FALSE),"")
AM58: =IFERROR(_xlfn.RANK.EQ(AP58, $AP$3:$AP$150)+ COUNTIFS($AP$3:AP58, AP58) - 1,"") | AN58: =U31 | AO58: SAVINGS | AP58: =IFERROR(VLOOKUP(AN58,MAY!$U$23:$W$38,3,FALSE),"")
AM59: =IFERROR(_xlfn.RANK.EQ(AP59, $AP$3:$AP$150)+ COUNTIFS($AP$3:AP59, AP59) - 1,"") | AN59: =U32 | AO59: SAVINGS | AP59: =IFERROR(VLOOKUP(AN59,MAY!$U$23:$W$38,3,FALSE),"")
AM60: =IFERROR(_xlfn.RANK.EQ(AP60, $AP$3:$AP$150)+ COUNTIFS($AP$3:AP60, AP60) - 1,"") | AN60: =U33 | AO60: SAVINGS | AP60: =IFERROR(VLOOKUP(AN60,MAY!$U$23:$W$38,3,FALSE),"")
AM61: =IFERROR(_xlfn.RANK.EQ(AP61, $AP$3:$AP$150)+ COUNTIFS($AP$3:AP61, AP61) - 1,"") | AN61: =U34 | AO61: SAVINGS | AP61: =IFERROR(VLOOKUP(AN61,MAY!$U$23:$W$38,3,FALSE),"")
... AM65: =IFERROR(_xlfn.RANK.EQ(AP65, $AP$3:$AP$150)+ COUNTIFS($AP$3:AP65, AP65) - 1,"") | AN65: =U38 | AO65: SAVINGS | AP65: =IFERROR(VLOOKUP(AN65,MAY!$U$23:$W$38,3,FALSE),"")

Sheet JUN
B2: JUNE | F2: INCOME | J2: BILLS | N2: EXPENSES | R2: DEBT | V2: SAVINGS | AM2: Ranking | AN2: ITEM | AO2: CATEGORY | AP2: TOTAL SPENT
AM3: =IFERROR(_xlfn.RANK.EQ(AP3, $AP$3:$AP$150)+ COUNTIFS($AP$3:AP3, AP3) - 1,"") | AN3: =F23 | AO3: BILLS | AP3: =IFERROR(VLOOKUP(AN3,JUN!$F$23:$H$38,3,FALSE),"")
F4: =SUM(JUN!$D$23:$D$38) -> 0 | J4: =SUM(JUN!$H$23:$H$38) -> 0 | N4: =SUM(JUN!$M$23:$M$38) -> 0 | R4: =SUM(JUN!$R$23:$R$38) -> 0 | V4: =SUM(JUN!$W$23:$W$38) -> 0 | AM4: =IFERROR(_xlfn.RANK.EQ(AP4, $AP$3:$AP$150)+ COUNTIFS($AP$3:AP4, AP4) - 1,"") | AN4: =F24 | AO4: BILLS | AP4: =IFERROR(VLOOKUP(AN4,JUN!$F$23:$H$38,3,FALSE),"")
B5: SUMMARY | AM5: =IFERROR(_xlfn.RANK.EQ(AP5, $AP$3:$AP$150)+ COUNTIFS($AP$3:AP5, AP5) - 1,"") | AN5: =F25 | AO5: BILLS | AP5: =IFERROR(VLOOKUP(AN5,JUN!$F$23:$H$38,3,FALSE),"")
AM6: =IFERROR(_xlfn.RANK.EQ(AP6, $AP$3:$AP$150)+ COUNTIFS($AP$3:AP6, AP6) - 1,"") | AN6: =F26 | AO6: BILLS | AP6: =IFERROR(VLOOKUP(AN6,JUN!$F$23:$H$38,3,FALSE),"")
B7: INCOME OVERVIEW | V7: RANK | W7: ITEM | X7: AMOUNT | AM7: =IFERROR(_xlfn.RANK.EQ(AP7, $AP$3:$AP$150)+ COUNTIFS($AP$3:AP7, AP7) - 1,"") | AN7: =F27 | AO7: BILLS | AP7: =IFERROR(VLOOKUP(AN7,JUN!$F$23:$H$38,3,FALSE),"")
V8: 1 | W8: =IFERROR(VLOOKUP(V8,$AM$3:$AP$65,2,FALSE),"") | X8: =IFERROR(VLOOKUP(V8,$AM$3:$AP$65,4,FALSE),"") | AM8: =IFERROR(_xlfn.RANK.EQ(AP8, $AP$3:$AP$150)+ COUNTIFS($AP$3:AP8, AP8) - 1,"") | AN8: =F28 | AO8: BILLS | AP8: =IFERROR(VLOOKUP(AN8,JUN!$F$23:$H$38,3,FALSE),"")
V9: 2 | W9: =IFERROR(VLOOKUP(V9,$AM$3:$AP$65,2,FALSE),"") | X9: =IFERROR(VLOOKUP(V9,$AM$3:$AP$65,4,FALSE),"") | AM9: =IFERROR(_xlfn.RANK.EQ(AP9, $AP$3:$AP$150)+ COUNTIFS($AP$3:AP9, AP9) - 1,"") | AN9: =F29 | AO9: BILLS | AP9: =IFERROR(VLOOKUP(AN9,JUN!$F$23:$H$38,3,FALSE),"")
C10: Planned | D10: Actual | V10: 3 | W10: =IFERROR(VLOOKUP(V10,$AM$3:$AP$65,2,FALSE),"") | X10: =IFERROR(VLOOKUP(V10,$AM$3:$AP$65,4,FALSE),"") | AM10: =IFERROR(_xlfn.RANK.EQ(AP10, $AP$3:$AP$150)+ COUNTIFS($AP$3:AP10, AP10) - 1,"") | AN10: =F30 | AO10: BILLS | AP10: =IFERROR(VLOOKUP(AN10,JUN!$F$23:$H$38,3,FALSE),"")
B11: INCOME | C11: =SUM(JUN!$C$23:$C$38) -> 0 | D11: =SUM(JUN!$D$23:$D$38) -> 0 | V11: 4 | W11: =IFERROR(VLOOKUP(V11,$AM$3:$AP$65,2,FALSE),"") | X11: =IFERROR(VLOOKUP(V11,$AM$3:$AP$65,4,FALSE),"") | AM11: =IFERROR(_xlfn.RANK.EQ(AP11, $AP$3:$AP$150)+ COUNTIFS($AP$3:AP11, AP11) - 1,"") | AN11: =F31 | AO11: BILLS | AP11: =IFERROR(VLOOKUP(AN11,JUN!$F$23:$H$38,3,FALSE),"")
B12: BILLS | C12: =SUM(JUN!$G$23:$G$38) -> 0 | D12: =SUM(JUN!$H$23:$H$38) -> 0 | V12: 5 | W12: =IFERROR(VLOOKUP(V12,$AM$3:$AP$65,2,FALSE),"") | X12: =IFERROR(VLOOKUP(V12,$AM$3:$AP$65,4,FALSE),"") | AM12: =IFERROR(_xlfn.RANK.EQ(AP12, $AP$3:$AP$150)+ COUNTIFS($AP$3:AP12, AP12) - 1,"") | AN12: =F32 | AO12: BILLS | AP12: =IFERROR(VLOOKUP(AN12,JUN!$F$23:$H$38,3,FALSE),"")
B13: EXPENSES | C13: =SUM(JUN!$L$23:$L$38) -> 0 | D13: =SUM(JUN!$M$23:$M$38) -> 0 | V13: 6 | W13: =IFERROR(VLOOKUP(V13,$AM$3:$AP$65,2,FALSE),"") | X13: =IFERROR(VLOOKUP(V13,$AM$3:$AP$65,4,FALSE),"") | AM13: =IFERROR(_xlfn.RANK.EQ(AP13, $AP$3:$AP$150)+ COUNTIFS($AP$3:AP13, AP13) - 1,"") | AN13: =F33 | AO13: BILLS | AP13: =IFERROR(VLOOKUP(AN13,JUN!$F$23:$H$38,3,FALSE),"")
B14: DEBT | C14: =SUM(JUN!$Q$23:$Q$38) -> 0 | D14: =SUM(JUN!$R$23:$R$38) -> 0 | V14: 7 | W14: =IFERROR(VLOOKUP(V14,$AM$3:$AP$65,2,FALSE),"") | X14: =IFERROR(VLOOKUP(V14,$AM$3:$AP$65,4,FALSE),"") | AM14: =IFERROR(_xlfn.RANK.EQ(AP14, $AP$3:$AP$150)+ COUNTIFS($AP$3:AP14, AP14) - 1,"") | AN14: =F34 | AO14: BILLS | AP14: =IFERROR(VLOOKUP(AN14,JUN!$F$23:$H$38,3,FALSE),"")
B15: SAVINGS | C15: =SUM(JUN!$V$23:$V$38) -> 0 | D15: =SUM(JUN!$W$23:$W$38) -> 0 | V15: 8 | W15: =IFERROR(VLOOKUP(V15,$AM$3:$AP$65,2,FALSE),"") | X15: =IFERROR(VLOOKUP(V15,$AM$3:$AP$65,4,FALSE),"") | AM15: =IFERROR(_xlfn.RANK.EQ(AP15, $AP$3:$AP$150)+ COUNTIFS($AP$3:AP15, AP15) - 1,"") | AN15: =F35 | AO15: BILLS | AP15: =IFERROR(VLOOKUP(AN15,JUN!$F$23:$H$38,3,FALSE),"")
B16: BALANCE | C16: =(C11-SUM(C12:C15)) -> 0 | D16: =(D11-SUM(D12:D15)) -> 0 | V16: 9 | W16: =IFERROR(VLOOKUP(V16,$AM$3:$AP$65,2,FALSE),"") | X16: =IFERROR(VLOOKUP(V16,$AM$3:$AP$65,4,FALSE),"") | AM16: =IFERROR(_xlfn.RANK.EQ(AP16, $AP$3:$AP$150)+ COUNTIFS($AP$3:AP16, AP16) - 1,"") | AN16: =F36 | AO16: BILLS | AP16: =IFERROR(VLOOKUP(AN16,JUN!$F$23:$H$38,3,FALSE),"")
V17: 10 | W17: =IFERROR(VLOOKUP(V17,$AM$3:$AP$65,2,FALSE),"") | X17: =IFERROR(VLOOKUP(V17,$AM$3:$AP$65,4,FALSE),"") | AM17: =IFERROR(_xlfn.RANK.EQ(AP17, $AP$3:$AP$150)+ COUNTIFS($AP$3:AP17, AP17) - 1,"") | AN17: =F37 | AO17: BILLS | AP17: =IFERROR(VLOOKUP(AN17,JUN!$F$23:$H$38,3,FALSE),"")
V18: 11 | W18: =IFERROR(VLOOKUP(V18,$AM$3:$AP$65,2,FALSE),"") | X18: =IFERROR(VLOOKUP(V18,$AM$3:$AP$65,4,FALSE),"") | AM18: =IFERROR(_xlfn.RANK.EQ(AP18, $AP$3:$AP$150)+ COUNTIFS($AP$3:AP18, AP18) - 1,"") | AN18: =F38 | AO18: BILLS | AP18: =IFERROR(VLOOKUP(AN18,JUN!$F$23:$H$38,3,FALSE),"")
AM19: =IFERROR(_xlfn.RANK.EQ(AP19, $AP$3:$AP$150)+ COUNTIFS($AP$3:AP19, AP19) - 1,"") | AN19: =K23 | AO19: EXPENSES | AP19: =IFERROR(VLOOKUP(AN19,JUN!$K$23:$M$38,3,FALSE),"")
B20: INCOME | F20: BILLS | K20: EXPENSES | P20: DEBT | U20: SAVINGS | AM20: =IFERROR(_xlfn.RANK.EQ(AP20, $AP$3:$AP$150)+ COUNTIFS($AP$3:AP20, AP20) - 1,"") | AN20: =K24 | AO20: EXPENSES | AP20: =IFERROR(VLOOKUP(AN20,JUN!$K$23:$M$38,3,FALSE),"")
AM21: =IFERROR(_xlfn.RANK.EQ(AP21, $AP$3:$AP$150)+ COUNTIFS($AP$3:AP21, AP21) - 1,"") | AN21: =K25 | AO21: EXPENSES | AP21: =IFERROR(VLOOKUP(AN21,JUN!$K$23:$M$38,3,FALSE),"")
B22: Details | C22: Planned | D22: Actual | F22: Details | G22: Planned | H22: Actual | I22: Variance | K22: Details | L22: Planned | M22: Actual | N22: Variance | P22: Details | Q22: Planned | R22: Actual | S22: Variance | U22: Details | V22: Planned | W22: Actual | X22: Variance | AM22: =IFERROR(_xlfn.RANK.EQ(AP22, $AP$3:$AP$150)+ COUNTIFS($AP$3:AP22, AP22) - 1,"") | AN22: =K26 | AO22: EXPENSES | AP22: =IFERROR(VLOOKUP(AN22,JUN!$K$23:$M$38,3,FALSE),"")
I23: =JUN!$G23-JUN!$H23 -> 0 | N23: =JUN!$L23-JUN!$M23 -> 0 | S23: =JUN!$Q23-JUN!$R23 -> 0 | X23: =JUN!$V23-JUN!$W23 -> 0 | AM23: =IFERROR(_xlfn.RANK.EQ(AP23, $AP$3:$AP$150)+ COUNTIFS($AP$3:AP23, AP23) - 1,"") | AN23: =K27 | AO23: EXPENSES | AP23: =IFERROR(VLOOKUP(AN23,JUN!$K$23:$M$38,3,FALSE),"")
I24: =JUN!$G24-JUN!$H24 -> 0 | N24: =JUN!$L24-JUN!$M24 -> 0 | S24: =JUN!$Q24-JUN!$R24 -> 0 | X24: =JUN!$V24-JUN!$W24 -> 0 | AM24: =IFERROR(_xlfn.RANK.EQ(AP24, $AP$3:$AP$150)+ COUNTIFS($AP$3:AP24, AP24) - 1,"") | AN24: =K28 | AO24: EXPENSES | AP24: =IFERROR(VLOOKUP(AN24,JUN!$K$23:$M$38,3,FALSE),"")
I25: =JUN!$G25-JUN!$H25 -> 0 | N25: =JUN!$L25-JUN!$M25 -> 0 | S25: =JUN!$Q25-JUN!$R25 -> 0 | X25: =JUN!$V25-JUN!$W25 -> 0 | AM25: =IFERROR(_xlfn.RANK.EQ(AP25, $AP$3:$AP$150)+ COUNTIFS($AP$3:AP25, AP25) - 1,"") | AN25: =K29 | AO25: EXPENSES | AP25: =IFERROR(VLOOKUP(AN25,JUN!$K$23:$M$38,3,FALSE),"")
I26: =JUN!$G26-JUN!$H26 -> 0 | N26: =JUN!$L26-JUN!$M26 -> 0 | S26: =JUN!$Q26-JUN!$R26 -> 0 | X26: =JUN!$V26-JUN!$W26 -> 0 | AM26: =IFERROR(_xlfn.RANK.EQ(AP26, $AP$3:$AP$150)+ COUNTIFS($AP$3:AP26, AP26) - 1,"") | AN26: =K30 | AO26: EXPENSES | AP26: =IFERROR(VLOOKUP(AN26,JUN!$K$23:$M$38,3,FALSE),"")
I27: =JUN!$G27-JUN!$H27 -> 0 | N27: =JUN!$L27-JUN!$M27 -> 0 | S27: =JUN!$Q27-JUN!$R27 -> 0 | X27: =JUN!$V27-JUN!$W27 -> 0 | AM27: =IFERROR(_xlfn.RANK.EQ(AP27, $AP$3:$AP$150)+ COUNTIFS($AP$3:AP27, AP27) - 1,"") | AN27: =K31 | AO27: EXPENSES | AP27: =IFERROR(VLOOKUP(AN27,JUN!$K$23:$M$38,3,FALSE),"")
I28: =JUN!$G28-JUN!$H28 -> 0 | N28: =JUN!$L28-JUN!$M28 -> 0 | S28: =JUN!$Q28-JUN!$R28 -> 0 | X28: =JUN!$V28-JUN!$W28 -> 0 | AM28: =IFERROR(_xlfn.RANK.EQ(AP28, $AP$3:$AP$150)+ COUNTIFS($AP$3:AP28, AP28) - 1,"") | AN28: =K32 | AO28: EXPENSES | AP28: =IFERROR(VLOOKUP(AN28,JUN!$K$23:$M$38,3,FALSE),"")
I29: =JUN!$G29-JUN!$H29 -> 0 | N29: =JUN!$L29-JUN!$M29 -> 0 | S29: =JUN!$Q29-JUN!$R29 -> 0 | X29: =JUN!$V29-JUN!$W29 -> 0 | AM29: =IFERROR(_xlfn.RANK.EQ(AP29, $AP$3:$AP$150)+ COUNTIFS($AP$3:AP29, AP29) - 1,"") | AN29: =K33 | AO29: EXPENSES | AP29: =IFERROR(VLOOKUP(AN29,JUN!$K$23:$M$38,3,FALSE),"")
I30: =JUN!$G30-JUN!$H30 -> 0 | N30: =JUN!$L30-JUN!$M30 -> 0 | S30: =JUN!$Q30-JUN!$R30 -> 0 | X30: =JUN!$V30-JUN!$W30 -> 0 | AM30: =IFERROR(_xlfn.RANK.EQ(AP30, $AP$3:$AP$150)+ COUNTIFS($AP$3:AP30, AP30) - 1,"") | AN30: =K34 | AO30: EXPENSES | AP30: =IFERROR(VLOOKUP(AN30,JUN!$K$23:$M$38,3,FALSE),"")
I31: =JUN!$G31-JUN!$H31 -> 0 | N31: =JUN!$L31-JUN!$M31 -> 0 | S31: =JUN!$Q31-JUN!$R31 -> 0 | X31: =JUN!$V31-JUN!$W31 -> 0 | AM31: =IFERROR(_xlfn.RANK.EQ(AP31, $AP$3:$AP$150)+ COUNTIFS($AP$3:AP31, AP31) - 1,"") | AN31: =K35 | AO31: EXPENSES | AP31: =IFERROR(VLOOKUP(AN31,JUN!$K$23:$M$38,3,FALSE),"")
I32: =JUN!$G32-JUN!$H32 -> 0 | N32: =JUN!$L32-JUN!$M32 -> 0 | S32: =JUN!$Q32-JUN!$R32 -> 0 | X32: =JUN!$V32-JUN!$W32 -> 0 | AM32: =IFERROR(_xlfn.RANK.EQ(AP32, $AP$3:$AP$150)+ COUNTIFS($AP$3:AP32, AP32) - 1,"") | AN32: =K36 | AO32: EXPENSES | AP32: =IFERROR(VLOOKUP(AN32,JUN!$K$23:$M$38,3,FALSE),"")
I33: =JUN!$G33-JUN!$H33 -> 0 | N33: =JUN!$L33-JUN!$M33 -> 0 | S33: =JUN!$Q33-JUN!$R33 -> 0 | X33: =JUN!$V33-JUN!$W33 -> 0 | AM33: =IFERROR(_xlfn.RANK.EQ(AP33, $AP$3:$AP$150)+ COUNTIFS($AP$3:AP33, AP33) - 1,"") | AN33: =K37 | AO33: EXPENSES | AP33: =IFERROR(VLOOKUP(AN33,JUN!$K$23:$M$38,3,FALSE),"")
I34: =JUN!$G34-JUN!$H34 -> 0 | N34: =JUN!$L34-JUN!$M34 -> 0 | S34: =JUN!$Q34-JUN!$R34 -> 0 | X34: =JUN!$V34-JUN!$W34 -> 0 | AM34: =IFERROR(_xlfn.RANK.EQ(AP34, $AP$3:$AP$150)+ COUNTIFS($AP$3:AP34, AP34) - 1,"") | AN34: =K38 | AO34: DEBTS | AP34: =IFERROR(VLOOKUP(AN34,JUN!$K$23:$M$38,3,FALSE),"")
I35: =JUN!$G35-JUN!$H35 -> 0 | N35: =JUN!$L35-JUN!$M35 -> 0 | S35: =JUN!$Q35-JUN!$R35 -> 0 | X35: =JUN!$V35-JUN!$W35 -> 0 | AM35: =IFERROR(_xlfn.RANK.EQ(AP35, $AP$3:$AP$150)+ COUNTIFS($AP$3:AP35, AP35) - 1,"") | AN35: =P23 | AO35: DEBTS | AP35: =IFERROR(VLOOKUP(AN35,JUN!$P$23:$R$38,3,FALSE),"")
I36: =JUN!$G36-JUN!$H36 -> 0 | N36: =JUN!$L36-JUN!$M36 -> 0 | S36: =JUN!$Q36-JUN!$R36 -> 0 | X36: =JUN!$V36-JUN!$W36 -> 0 | AM36: =IFERROR(_xlfn.RANK.EQ(AP36, $AP$3:$AP$150)+ COUNTIFS($AP$3:AP36, AP36) - 1,"") | AN36: =P24 | AO36: DEBTS | AP36: =IFERROR(VLOOKUP(AN36,JUN!$P$23:$R$38,3,FALSE),"")
I37: =JUN!$G37-JUN!$H37 -> 0 | N37: =JUN!$L37-JUN!$M37 -> 0 | S37: =JUN!$Q37-JUN!$R37 -> 0 | X37: =JUN!$V37-JUN!$W37 -> 0 | AM37: =IFERROR(_xlfn.RANK.EQ(AP37, $AP$3:$AP$150)+ COUNTIFS($AP$3:AP37, AP37) - 1,"") | AN37: =P25 | AO37: DEBTS | AP37: =IFERROR(VLOOKUP(AN37,JUN!$P$23:$R$38,3,FALSE),"")
I38: =JUN!$G38-JUN!$H38 -> 0 | N38: =JUN!$L38-JUN!$M38 -> 0 | S38: =JUN!$Q38-JUN!$R38 -> 0 | X38: =JUN!$V38-JUN!$W38 -> 0 | AM38: =IFERROR(_xlfn.RANK.EQ(AP38, $AP$3:$AP$150)+ COUNTIFS($AP$3:AP38, AP38) - 1,"") | AN38: =P26 | AO38: DEBTS | AP38: =IFERROR(VLOOKUP(AN38,JUN!$P$23:$R$38,3,FALSE),"")
AM39: =IFERROR(_xlfn.RANK.EQ(AP39, $AP$3:$AP$150)+ COUNTIFS($AP$3:AP39, AP39) - 1,"") | AN39: =P27 | AO39: DEBTS | AP39: =IFERROR(VLOOKUP(AN39,JUN!$P$23:$R$38,3,FALSE),"")
AM40: =IFERROR(_xlfn.RANK.EQ(AP40, $AP$3:$AP$150)+ COUNTIFS($AP$3:AP40, AP40) - 1,"") | AN40: =P28 | AO40: DEBTS | AP40: =IFERROR(VLOOKUP(AN40,JUN!$P$23:$R$38,3,FALSE),"")
AM41: =IFERROR(_xlfn.RANK.EQ(AP41, $AP$3:$AP$150)+ COUNTIFS($AP$3:AP41, AP41) - 1,"") | AN41: =P29 | AO41: DEBTS | AP41: =IFERROR(VLOOKUP(AN41,JUN!$P$23:$R$38,3,FALSE),"")
AM42: =IFERROR(_xlfn.RANK.EQ(AP42, $AP$3:$AP$150)+ COUNTIFS($AP$3:AP42, AP42) - 1,"") | AN42: =P30 | AO42: DEBTS | AP42: =IFERROR(VLOOKUP(AN42,JUN!$P$23:$R$38,3,FALSE),"")
AM43: =IFERROR(_xlfn.RANK.EQ(AP43, $AP$3:$AP$150)+ COUNTIFS($AP$3:AP43, AP43) - 1,"") | AN43: =P31 | AO43: DEBTS | AP43: =IFERROR(VLOOKUP(AN43,JUN!$P$23:$R$38,3,FALSE),"")
AM44: =IFERROR(_xlfn.RANK.EQ(AP44, $AP$3:$AP$150)+ COUNTIFS($AP$3:AP44, AP44) - 1,"") | AN44: =P32 | AO44: DEBTS | AP44: =IFERROR(VLOOKUP(AN44,JUN!$P$23:$R$38,3,FALSE),"")
AM45: =IFERROR(_xlfn.RANK.EQ(AP45, $AP$3:$AP$150)+ COUNTIFS($AP$3:AP45, AP45) - 1,"") | AN45: =P33 | AO45: DEBTS | AP45: =IFERROR(VLOOKUP(AN45,JUN!$P$23:$R$38,3,FALSE),"")
AM46: =IFERROR(_xlfn.RANK.EQ(AP46, $AP$3:$AP$150)+ COUNTIFS($AP$3:AP46, AP46) - 1,"") | AN46: =P34 | AO46: DEBTS | AP46: =IFERROR(VLOOKUP(AN46,JUN!$P$23:$R$38,3,FALSE),"")
AM47: =IFERROR(_xlfn.RANK.EQ(AP47, $AP$3:$AP$150)+ COUNTIFS($AP$3:AP47, AP47) - 1,"") | AN47: =P35 | AO47: DEBTS | AP47: =IFERROR(VLOOKUP(AN47,JUN!$P$23:$R$38,3,FALSE),"")
AM48: =IFERROR(_xlfn.RANK.EQ(AP48, $AP$3:$AP$150)+ COUNTIFS($AP$3:AP48, AP48) - 1,"") | AN48: =P36 | AO48: DEBTS | AP48: =IFERROR(VLOOKUP(AN48,JUN!$P$23:$R$38,3,FALSE),"")
AM49: =IFERROR(_xlfn.RANK.EQ(AP49, $AP$3:$AP$150)+ COUNTIFS($AP$3:AP49, AP49) - 1,"") | AN49: =P37 | AO49: SAVINGS | AP49: =IFERROR(VLOOKUP(AN49,JUN!$P$23:$R$38,3,FALSE),"")
AM50: =IFERROR(_xlfn.RANK.EQ(AP50, $AP$3:$AP$150)+ COUNTIFS($AP$3:AP50, AP50) - 1,"") | AN50: =U23 | AO50: SAVINGS | AP50: =IFERROR(VLOOKUP(AN50,JUN!$U$23:$W$38,3,FALSE),"")
AM51: =IFERROR(_xlfn.RANK.EQ(AP51, $AP$3:$AP$150)+ COUNTIFS($AP$3:AP51, AP51) - 1,"") | AN51: =U24 | AO51: SAVINGS | AP51: =IFERROR(VLOOKUP(AN51,JUN!$U$23:$W$38,3,FALSE),"")
AM52: =IFERROR(_xlfn.RANK.EQ(AP52, $AP$3:$AP$150)+ COUNTIFS($AP$3:AP52, AP52) - 1,"") | AN52: =U25 | AO52: SAVINGS | AP52: =IFERROR(VLOOKUP(AN52,JUN!$U$23:$W$38,3,FALSE),"")
AM53: =IFERROR(_xlfn.RANK.EQ(AP53, $AP$3:$AP$150)+ COUNTIFS($AP$3:AP53, AP53) - 1,"") | AN53: =U26 | AO53: SAVINGS | AP53: =IFERROR(VLOOKUP(AN53,JUN!$U$23:$W$38,3,FALSE),"")
AM54: =IFERROR(_xlfn.RANK.EQ(AP54, $AP$3:$AP$150)+ COUNTIFS($AP$3:AP54, AP54) - 1,"") | AN54: =U27 | AO54: SAVINGS | AP54: =IFERROR(VLOOKUP(AN54,JUN!$U$23:$W$38,3,FALSE),"")
AM55: =IFERROR(_xlfn.RANK.EQ(AP55, $AP$3:$AP$150)+ COUNTIFS($AP$3:AP55, AP55) - 1,"") | AN55: =U28 | AO55: SAVINGS | AP55: =IFERROR(VLOOKUP(AN55,JUN!$U$23:$W$38,3,FALSE),"")
AM56: =IFERROR(_xlfn.RANK.EQ(AP56, $AP$3:$AP$150)+ COUNTIFS($AP$3:AP56, AP56) - 1,"") | AN56: =U29 | AO56: SAVINGS | AP56: =IFERROR(VLOOKUP(AN56,JUN!$U$23:$W$38,3,FALSE),"")
AM57: =IFERROR(_xlfn.RANK.EQ(AP57, $AP$3:$AP$150)+ COUNTIFS($AP$3:AP57, AP57) - 1,"") | AN57: =U30 | AO57: SAVINGS | AP57: =IFERROR(VLOOKUP(AN57,JUN!$U$23:$W$38,3,FALSE),"")
AM58: =IFERROR(_xlfn.RANK.EQ(AP58, $AP$3:$AP$150)+ COUNTIFS($AP$3:AP58, AP58) - 1,"") | AN58: =U31 | AO58: SAVINGS | AP58: =IFERROR(VLOOKUP(AN58,JUN!$U$23:$W$38,3,FALSE),"")
AM59: =IFERROR(_xlfn.RANK.EQ(AP59, $AP$3:$AP$150)+ COUNTIFS($AP$3:AP59, AP59) - 1,"") | AN59: =U32 | AO59: SAVINGS | AP59: =IFERROR(VLOOKUP(AN59,JUN!$U$23:$W$38,3,FALSE),"")
AM60: =IFERROR(_xlfn.RANK.EQ(AP60, $AP$3:$AP$150)+ COUNTIFS($AP$3:AP60, AP60) - 1,"") | AN60: =U33 | AO60: SAVINGS | AP60: =IFERROR(VLOOKUP(AN60,JUN!$U$23:$W$38,3,FALSE),"")
AM61: =IFERROR(_xlfn.RANK.EQ(AP61, $AP$3:$AP$150)+ COUNTIFS($AP$3:AP61, AP61) - 1,"") | AN61: =U34 | AO61: SAVINGS | AP61: =IFERROR(VLOOKUP(AN61,JUN!$U$23:$W$38,3,FALSE),"")
... AM65: =IFERROR(_xlfn.RANK.EQ(AP65, $AP$3:$AP$150)+ COUNTIFS($AP$3:AP65, AP65) - 1,"") | AN65: =U38 | AO65: SAVINGS | AP65: =IFERROR(VLOOKUP(AN65,JUN!$U$23:$W$38,3,FALSE),"")

Sheet JUL
B2: JULY | F2: INCOME | J2: BILLS | N2: EXPENSES | R2: DEBT | V2: SAVINGS | AM2: Ranking | AN2: ITEM | AO2: CATEGORY | AP2: TOTAL SPENT
AM3: =IFERROR(_xlfn.RANK.EQ(AP3, $AP$3:$AP$150)+ COUNTIFS($AP$3:AP3, AP3) - 1,"") | AN3: =F23 | AO3: BILLS | AP3: =IFERROR(VLOOKUP(AN3,JUL!$F$23:$H$38,3,FALSE),"")
F4: =SUM(JUL!$D$23:$D$38) -> 0 | J4: =SUM(JUL!$H$23:$H$38) -> 0 | N4: =SUM(JUL!$M$23:$M$38) -> 0 | R4: =SUM(JUL!$R$23:$R$38) -> 0 | V4: =SUM(JUL!$W$23:$W$38) -> 0 | AM4: =IFERROR(_xlfn.RANK.EQ(AP4, $AP$3:$AP$150)+ COUNTIFS($AP$3:AP4, AP4) - 1,"") | AN4: =F24 | AO4: BILLS | AP4: =IFERROR(VLOOKUP(AN4,JUL!$F$23:$H$38,3,FALSE),"")
B5: SUMMARY | AM5: =IFERROR(_xlfn.RANK.EQ(AP5, $AP$3:$AP$150)+ COUNTIFS($AP$3:AP5, AP5) - 1,"") | AN5: =F25 | AO5: BILLS | AP5: =IFERROR(VLOOKUP(AN5,JUL!$F$23:$H$38,3,FALSE),"")
AM6: =IFERROR(_xlfn.RANK.EQ(AP6, $AP$3:$AP$150)+ COUNTIFS($AP$3:AP6, AP6) - 1,"") | AN6: =F26 | AO6: BILLS | AP6: =IFERROR(VLOOKUP(AN6,JUL!$F$23:$H$38,3,FALSE),"")
B7: INCOME OVERVIEW | V7: RANK | W7: ITEM | X7: AMOUNT | AM7: =IFERROR(_xlfn.RANK.EQ(AP7, $AP$3:$AP$150)+ COUNTIFS($AP$3:AP7, AP7) - 1,"") | AN7: =F27 | AO7: BILLS | AP7: =IFERROR(VLOOKUP(AN7,JUL!$F$23:$H$38,3,FALSE),"")
V8: 1 | W8: =IFERROR(VLOOKUP(V8,$AM$3:$AP$65,2,FALSE),"") | X8: =IFERROR(VLOOKUP(V8,$AM$3:$AP$65,4,FALSE),"") | AM8: =IFERROR(_xlfn.RANK.EQ(AP8, $AP$3:$AP$150)+ COUNTIFS($AP$3:AP8, AP8) - 1,"") | AN8: =F28 | AO8: BILLS | AP8: =IFERROR(VLOOKUP(AN8,JUL!$F$23:$H$38,3,FALSE),"")
V9: 2 | W9: =IFERROR(VLOOKUP(V9,$AM$3:$AP$65,2,FALSE),"") | X9: =IFERROR(VLOOKUP(V9,$AM$3:$AP$65,4,FALSE),"") | AM9: =IFERROR(_xlfn.RANK.EQ(AP9, $AP$3:$AP$150)+ COUNTIFS($AP$3:AP9, AP9) - 1,"") | AN9: =F29 | AO9: BILLS | AP9: =IFERROR(VLOOKUP(AN9,JUL!$F$23:$H$38,3,FALSE),"")
C10: Planned | D10: Actual | V10: 3 | W10: =IFERROR(VLOOKUP(V10,$AM$3:$AP$65,2,FALSE),"") | X10: =IFERROR(VLOOKUP(V10,$AM$3:$AP$65,4,FALSE),"") | AM10: =IFERROR(_xlfn.RANK.EQ(AP10, $AP$3:$AP$150)+ COUNTIFS($AP$3:AP10, AP10) - 1,"") | AN10: =F30 | AO10: BILLS | AP10: =IFERROR(VLOOKUP(AN10,JUL!$F$23:$H$38,3,FALSE),"")
B11: INCOME | C11: =SUM(JUL!$C$23:$C$38) -> 0 | D11: =SUM(JUL!$D$23:$D$38) -> 0 | V11: 4 | W11: =IFERROR(VLOOKUP(V11,$AM$3:$AP$65,2,FALSE),"") | X11: =IFERROR(VLOOKUP(V11,$AM$3:$AP$65,4,FALSE),"") | AM11: =IFERROR(_xlfn.RANK.EQ(AP11, $AP$3:$AP$150)+ COUNTIFS($AP$3:AP11, AP11) - 1,"") | AN11: =F31 | AO11: BILLS | AP11: =IFERROR(VLOOKUP(AN11,JUL!$F$23:$H$38,3,FALSE),"")
B12: BILLS | C12: =SUM(JUL!$G$23:$G$38) -> 0 | D12: =SUM(JUL!$H$23:$H$38) -> 0 | V12: 5 | W12: =IFERROR(VLOOKUP(V12,$AM$3:$AP$65,2,FALSE),"") | X12: =IFERROR(VLOOKUP(V12,$AM$3:$AP$65,4,FALSE),"") | AM12: =IFERROR(_xlfn.RANK.EQ(AP12, $AP$3:$AP$150)+ COUNTIFS($AP$3:AP12, AP12) - 1,"") | AN12: =F32 | AO12: BILLS | AP12: =IFERROR(VLOOKUP(AN12,JUL!$F$23:$H$38,3,FALSE),"")
B13: EXPENSES | C13: =SUM(JUL!$L$23:$L$38) -> 0 | D13: =SUM(JUL!$M$23:$M$38) -> 0 | V13: 6 | W13: =IFERROR(VLOOKUP(V13,$AM$3:$AP$65,2,FALSE),"") | X13: =IFERROR(VLOOKUP(V13,$AM$3:$AP$65,4,FALSE),"") | AM13: =IFERROR(_xlfn.RANK.EQ(AP13, $AP$3:$AP$150)+ COUNTIFS($AP$3:AP13, AP13) - 1,"") | AN13: =F33 | AO13: BILLS | AP13: =IFERROR(VLOOKUP(AN13,JUL!$F$23:$H$38,3,FALSE),"")
B14: DEBT | C14: =SUM(JUL!$Q$23:$Q$38) -> 0 | D14: =SUM(JUL!$R$23:$R$38) -> 0 | V14: 7 | W14: =IFERROR(VLOOKUP(V14,$AM$3:$AP$65,2,FALSE),"") | X14: =IFERROR(VLOOKUP(V14,$AM$3:$AP$65,4,FALSE),"") | AM14: =IFERROR(_xlfn.RANK.EQ(AP14, $AP$3:$AP$150)+ COUNTIFS($AP$3:AP14, AP14) - 1,"") | AN14: =F34 | AO14: BILLS | AP14: =IFERROR(VLOOKUP(AN14,JUL!$F$23:$H$38,3,FALSE),"")
B15: SAVINGS | C15: =SUM(JUL!$V$23:$V$38) -> 0 | D15: =SUM(JUL!$W$23:$W$38) -> 0 | V15: 8 | W15: =IFERROR(VLOOKUP(V15,$AM$3:$AP$65,2,FALSE),"") | X15: =IFERROR(VLOOKUP(V15,$AM$3:$AP$65,4,FALSE),"") | AM15: =IFERROR(_xlfn.RANK.EQ(AP15, $AP$3:$AP$150)+ COUNTIFS($AP$3:AP15, AP15) - 1,"") | AN15: =F35 | AO15: BILLS | AP15: =IFERROR(VLOOKUP(AN15,JUL!$F$23:$H$38,3,FALSE),"")
B16: BALANCE | C16: =(C11-SUM(C12:C15)) -> 0 | D16: =(D11-SUM(D12:D15)) -> 0 | V16: 9 | W16: =IFERROR(VLOOKUP(V16,$AM$3:$AP$65,2,FALSE),"") | X16: =IFERROR(VLOOKUP(V16,$AM$3:$AP$65,4,FALSE),"") | AM16: =IFERROR(_xlfn.RANK.EQ(AP16, $AP$3:$AP$150)+ COUNTIFS($AP$3:AP16, AP16) - 1,"") | AN16: =F36 | AO16: BILLS | AP16: =IFERROR(VLOOKUP(AN16,JUL!$F$23:$H$38,3,FALSE),"")
V17: 10 | W17: =IFERROR(VLOOKUP(V17,$AM$3:$AP$65,2,FALSE),"") | X17: =IFERROR(VLOOKUP(V17,$AM$3:$AP$65,4,FALSE),"") | AM17: =IFERROR(_xlfn.RANK.EQ(AP17, $AP$3:$AP$150)+ COUNTIFS($AP$3:AP17, AP17) - 1,"") | AN17: =F37 | AO17: BILLS | AP17: =IFERROR(VLOOKUP(AN17,JUL!$F$23:$H$38,3,FALSE),"")
V18: 11 | W18: =IFERROR(VLOOKUP(V18,$AM$3:$AP$65,2,FALSE),"") | X18: =IFERROR(VLOOKUP(V18,$AM$3:$AP$65,4,FALSE),"") | AM18: =IFERROR(_xlfn.RANK.EQ(AP18, $AP$3:$AP$150)+ COUNTIFS($AP$3:AP18, AP18) - 1,"") | AN18: =F38 | AO18: BILLS | AP18: =IFERROR(VLOOKUP(AN18,JUL!$F$23:$H$38,3,FALSE),"")
AM19: =IFERROR(_xlfn.RANK.EQ(AP19, $AP$3:$AP$150)+ COUNTIFS($AP$3:AP19, AP19) - 1,"") | AN19: =K23 | AO19: EXPENSES | AP19: =IFERROR(VLOOKUP(AN19,JUL!$K$23:$M$38,3,FALSE),"")
B20: INCOME | F20: BILLS | K20: EXPENSES | P20: DEBT | U20: SAVINGS | AM20: =IFERROR(_xlfn.RANK.EQ(AP20, $AP$3:$AP$150)+ COUNTIFS($AP$3:AP20, AP20) - 1,"") | AN20: =K24 | AO20: EXPENSES | AP20: =IFERROR(VLOOKUP(AN20,JUL!$K$23:$M$38,3,FALSE),"")
AM21: =IFERROR(_xlfn.RANK.EQ(AP21, $AP$3:$AP$150)+ COUNTIFS($AP$3:AP21, AP21) - 1,"") | AN21: =K25 | AO21: EXPENSES | AP21: =IFERROR(VLOOKUP(AN21,JUL!$K$23:$M$38,3,FALSE),"")
B22: Details | C22: Planned | D22: Actual | F22: Details | G22: Planned | H22: Actual | I22: Variance | K22: Details | L22: Planned | M22: Actual | N22: Variance | P22: Details | Q22: Planned | R22: Actual | S22: Variance | U22: Details | V22: Planned | W22: Actual | X22: Variance | AM22: =IFERROR(_xlfn.RANK.EQ(AP22, $AP$3:$AP$150)+ COUNTIFS($AP$3:AP22, AP22) - 1,"") | AN22: =K26 | AO22: EXPENSES | AP22: =IFERROR(VLOOKUP(AN22,JUL!$K$23:$M$38,3,FALSE),"")
I23: =JUL!$G23-JUL!$H23 -> 0 | N23: =JUL!$L23-JUL!$M23 -> 0 | S23: =JUL!$Q23-JUL!$R23 -> 0 | X23: =JUL!$V23-JUL!$W23 -> 0 | AM23: =IFERROR(_xlfn.RANK.EQ(AP23, $AP$3:$AP$150)+ COUNTIFS($AP$3:AP23, AP23) - 1,"") | AN23: =K27 | AO23: EXPENSES | AP23: =IFERROR(VLOOKUP(AN23,JUL!$K$23:$M$38,3,FALSE),"")
I24: =JUL!$G24-JUL!$H24 -> 0 | N24: =JUL!$L24-JUL!$M24 -> 0 | S24: =JUL!$Q24-JUL!$R24 -> 0 | X24: =JUL!$V24-JUL!$W24 -> 0 | AM24: =IFERROR(_xlfn.RANK.EQ(AP24, $AP$3:$AP$150)+ COUNTIFS($AP$3:AP24, AP24) - 1,"") | AN24: =K28 | AO24: EXPENSES | AP24: =IFERROR(VLOOKUP(AN24,JUL!$K$23:$M$38,3,FALSE),"")
I25: =JUL!$G25-JUL!$H25 -> 0 | N25: =JUL!$L25-JUL!$M25 -> 0 | S25: =JUL!$Q25-JUL!$R25 -> 0 | X25: =JUL!$V25-JUL!$W25 -> 0 | AM25: =IFERROR(_xlfn.RANK.EQ(AP25, $AP$3:$AP$150)+ COUNTIFS($AP$3:AP25, AP25) - 1,"") | AN25: =K29 | AO25: EXPENSES | AP25: =IFERROR(VLOOKUP(AN25,JUL!$K$23:$M$38,3,FALSE),"")
I26: =JUL!$G26-JUL!$H26 -> 0 | N26: =JUL!$L26-JUL!$M26 -> 0 | S26: =JUL!$Q26-JUL!$R26 -> 0 | X26: =JUL!$V26-JUL!$W26 -> 0 | AM26: =IFERROR(_xlfn.RANK.EQ(AP26, $AP$3:$AP$150)+ COUNTIFS($AP$3:AP26, AP26) - 1,"") | AN26: =K30 | AO26: EXPENSES | AP26: =IFERROR(VLOOKUP(AN26,JUL!$K$23:$M$38,3,FALSE),"")
I27: =JUL!$G27-JUL!$H27 -> 0 | N27: =JUL!$L27-JUL!$M27 -> 0 | S27: =JUL!$Q27-JUL!$R27 -> 0 | X27: =JUL!$V27-JUL!$W27 -> 0 | AM27: =IFERROR(_xlfn.RANK.EQ(AP27, $AP$3:$AP$150)+ COUNTIFS($AP$3:AP27, AP27) - 1,"") | AN27: =K31 | AO27: EXPENSES | AP27: =IFERROR(VLOOKUP(AN27,JUL!$K$23:$M$38,3,FALSE),"")
I28: =JUL!$G28-JUL!$H28 -> 0 | N28: =JUL!$L28-JUL!$M28 -> 0 | S28: =JUL!$Q28-JUL!$R28 -> 0 | X28: =JUL!$V28-JUL!$W28 -> 0 | AM28: =IFERROR(_xlfn.RANK.EQ(AP28, $AP$3:$AP$150)+ COUNTIFS($AP$3:AP28, AP28) - 1,"") | AN28: =K32 | AO28: EXPENSES | AP28: =IFERROR(VLOOKUP(AN28,JUL!$K$23:$M$38,3,FALSE),"")
I29: =JUL!$G29-JUL!$H29 -> 0 | N29: =JUL!$L29-JUL!$M29 -> 0 | S29: =JUL!$Q29-JUL!$R29 -> 0 | X29: =JUL!$V29-JUL!$W29 -> 0 | AM29: =IFERROR(_xlfn.RANK.EQ(AP29, $AP$3:$AP$150)+ COUNTIFS($AP$3:AP29, AP29) - 1,"") | AN29: =K33 | AO29: EXPENSES | AP29: =IFERROR(VLOOKUP(AN29,JUL!$K$23:$M$38,3,FALSE),"")
I30: =JUL!$G30-JUL!$H30 -> 0 | N30: =JUL!$L30-JUL!$M30 -> 0 | S30: =JUL!$Q30-JUL!$R30 -> 0 | X30: =JUL!$V30-JUL!$W30 -> 0 | AM30: =IFERROR(_xlfn.RANK.EQ(AP30, $AP$3:$AP$150)+ COUNTIFS($AP$3:AP30, AP30) - 1,"") | AN30: =K34 | AO30: EXPENSES | AP30: =IFERROR(VLOOKUP(AN30,JUL!$K$23:$M$38,3,FALSE),"")
I31: =JUL!$G31-JUL!$H31 -> 0 | N31: =JUL!$L31-JUL!$M31 -> 0 | S31: =JUL!$Q31-JUL!$R31 -> 0 | X31: =JUL!$V31-JUL!$W31 -> 0 | AM31: =IFERROR(_xlfn.RANK.EQ(AP31, $AP$3:$AP$150)+ COUNTIFS($AP$3:AP31, AP31) - 1,"") | AN31: =K35 | AO31: EXPENSES | AP31: =IFERROR(VLOOKUP(AN31,JUL!$K$23:$M$38,3,FALSE),"")
I32: =JUL!$G32-JUL!$H32 -> 0 | N32: =JUL!$L32-JUL!$M32 -> 0 | S32: =JUL!$Q32-JUL!$R32 -> 0 | X32: =JUL!$V32-JUL!$W32 -> 0 | AM32: =IFERROR(_xlfn.RANK.EQ(AP32, $AP$3:$AP$150)+ COUNTIFS($AP$3:AP32, AP32) - 1,"") | AN32: =K36 | AO32: EXPENSES | AP32: =IFERROR(VLOOKUP(AN32,JUL!$K$23:$M$38,3,FALSE),"")
I33: =JUL!$G33-JUL!$H33 -> 0 | N33: =JUL!$L33-JUL!$M33 -> 0 | S33: =JUL!$Q33-JUL!$R33 -> 0 | X33: =JUL!$V33-JUL!$W33 -> 0 | AM33: =IFERROR(_xlfn.RANK.EQ(AP33, $AP$3:$AP$150)+ COUNTIFS($AP$3:AP33, AP33) - 1,"") | AN33: =K37 | AO33: EXPENSES | AP33: =IFERROR(VLOOKUP(AN33,JUL!$K$23:$M$38,3,FALSE),"")
I34: =JUL!$G34-JUL!$H34 -> 0 | N34: =JUL!$L34-JUL!$M34 -> 0 | S34: =JUL!$Q34-JUL!$R34 -> 0 | X34: =JUL!$V34-JUL!$W34 -> 0 | AM34: =IFERROR(_xlfn.RANK.EQ(AP34, $AP$3:$AP$150)+ COUNTIFS($AP$3:AP34, AP34) - 1,"") | AN34: =K38 | AO34: DEBTS | AP34: =IFERROR(VLOOKUP(AN34,JUL!$K$23:$M$38,3,FALSE),"")
I35: =JUL!$G35-JUL!$H35 -> 0 | N35: =JUL!$L35-JUL!$M35 -> 0 | S35: =JUL!$Q35-JUL!$R35 -> 0 | X35: =JUL!$V35-JUL!$W35 -> 0 | AM35: =IFERROR(_xlfn.RANK.EQ(AP35, $AP$3:$AP$150)+ COUNTIFS($AP$3:AP35, AP35) - 1,"") | AN35: =P23 | AO35: DEBTS | AP35: =IFERROR(VLOOKUP(AN35,JUL!$P$23:$R$38,3,FALSE),"")
I36: =JUL!$G36-JUL!$H36 -> 0 | N36: =JUL!$L36-JUL!$M36 -> 0 | S36: =JUL!$Q36-JUL!$R36 -> 0 | X36: =JUL!$V36-JUL!$W36 -> 0 | AM36: =IFERROR(_xlfn.RANK.EQ(AP36, $AP$3:$AP$150)+ COUNTIFS($AP$3:AP36, AP36) - 1,"") | AN36: =P24 | AO36: DEBTS | AP36: =IFERROR(VLOOKUP(AN36,JUL!$P$23:$R$38,3,FALSE),"")
I37: =JUL!$G37-JUL!$H37 -> 0 | N37: =JUL!$L37-JUL!$M37 -> 0 | S37: =JUL!$Q37-JUL!$R37 -> 0 | X37: =JUL!$V37-JUL!$W37 -> 0 | AM37: =IFERROR(_xlfn.RANK.EQ(AP37, $AP$3:$AP$150)+ COUNTIFS($AP$3:AP37, AP37) - 1,"") | AN37: =P25 | AO37: DEBTS | AP37: =IFERROR(VLOOKUP(AN37,JUL!$P$23:$R$38,3,FALSE),"")
I38: =JUL!$G38-JUL!$H38 -> 0 | N38: =JUL!$L38-JUL!$M38 -> 0 | S38: =JUL!$Q38-JUL!$R38 -> 0 | X38: =JUL!$V38-JUL!$W38 -> 0 | AM38: =IFERROR(_xlfn.RANK.EQ(AP38, $AP$3:$AP$150)+ COUNTIFS($AP$3:AP38, AP38) - 1,"") | AN38: =P26 | AO38: DEBTS | AP38: =IFERROR(VLOOKUP(AN38,JUL!$P$23:$R$38,3,FALSE),"")
AM39: =IFERROR(_xlfn.RANK.EQ(AP39, $AP$3:$AP$150)+ COUNTIFS($AP$3:AP39, AP39) - 1,"") | AN39: =P27 | AO39: DEBTS | AP39: =IFERROR(VLOOKUP(AN39,JUL!$P$23:$R$38,3,FALSE),"")
AM40: =IFERROR(_xlfn.RANK.EQ(AP40, $AP$3:$AP$150)+ COUNTIFS($AP$3:AP40, AP40) - 1,"") | AN40: =P28 | AO40: DEBTS | AP40: =IFERROR(VLOOKUP(AN40,JUL!$P$23:$R$38,3,FALSE),"")
AM41: =IFERROR(_xlfn.RANK.EQ(AP41, $AP$3:$AP$150)+ COUNTIFS($AP$3:AP41, AP41) - 1,"") | AN41: =P29 | AO41: DEBTS | AP41: =IFERROR(VLOOKUP(AN41,JUL!$P$23:$R$38,3,FALSE),"")
AM42: =IFERROR(_xlfn.RANK.EQ(AP42, $AP$3:$AP$150)+ COUNTIFS($AP$3:AP42, AP42) - 1,"") | AN42: =P30 | AO42: DEBTS | AP42: =IFERROR(VLOOKUP(AN42,JUL!$P$23:$R$38,3,FALSE),"")
AM43: =IFERROR(_xlfn.RANK.EQ(AP43, $AP$3:$AP$150)+ COUNTIFS($AP$3:AP43, AP43) - 1,"") | AN43: =P31 | AO43: DEBTS | AP43: =IFERROR(VLOOKUP(AN43,JUL!$P$23:$R$38,3,FALSE),"")
AM44: =IFERROR(_xlfn.RANK.EQ(AP44, $AP$3:$AP$150)+ COUNTIFS($AP$3:AP44, AP44) - 1,"") | AN44: =P32 | AO44: DEBTS | AP44: =IFERROR(VLOOKUP(AN44,JUL!$P$23:$R$38,3,FALSE),"")
AM45: =IFERROR(_xlfn.RANK.EQ(AP45, $AP$3:$AP$150)+ COUNTIFS($AP$3:AP45, AP45) - 1,"") | AN45: =P33 | AO45: DEBTS | AP45: =IFERROR(VLOOKUP(AN45,JUL!$P$23:$R$38,3,FALSE),"")
AM46: =IFERROR(_xlfn.RANK.EQ(AP46, $AP$3:$AP$150)+ COUNTIFS($AP$3:AP46, AP46) - 1,"") | AN46: =P34 | AO46: DEBTS | AP46: =IFERROR(VLOOKUP(AN46,JUL!$P$23:$R$38,3,FALSE),"")
AM47: =IFERROR(_xlfn.RANK.EQ(AP47, $AP$3:$AP$150)+ COUNTIFS($AP$3:AP47, AP47) - 1,"") | AN47: =P35 | AO47: DEBTS | AP47: =IFERROR(VLOOKUP(AN47,JUL!$P$23:$R$38,3,FALSE),"")
AM48: =IFERROR(_xlfn.RANK.EQ(AP48, $AP$3:$AP$150)+ COUNTIFS($AP$3:AP48, AP48) - 1,"") | AN48: =P36 | AO48: DEBTS | AP48: =IFERROR(VLOOKUP(AN48,JUL!$P$23:$R$38,3,FALSE),"")
AM49: =IFERROR(_xlfn.RANK.EQ(AP49, $AP$3:$AP$150)+ COUNTIFS($AP$3:AP49, AP49) - 1,"") | AN49: =P37 | AO49: SAVINGS | AP49: =IFERROR(VLOOKUP(AN49,JUL!$P$23:$R$38,3,FALSE),"")
AM50: =IFERROR(_xlfn.RANK.EQ(AP50, $AP$3:$AP$150)+ COUNTIFS($AP$3:AP50, AP50) - 1,"") | AN50: =U23 | AO50: SAVINGS | AP50: =IFERROR(VLOOKUP(AN50,JUL!$U$23:$W$38,3,FALSE),"")
AM51: =IFERROR(_xlfn.RANK.EQ(AP51, $AP$3:$AP$150)+ COUNTIFS($AP$3:AP51, AP51) - 1,"") | AN51: =U24 | AO51: SAVINGS | AP51: =IFERROR(VLOOKUP(AN51,JUL!$U$23:$W$38,3,FALSE),"")
AM52: =IFERROR(_xlfn.RANK.EQ(AP52, $AP$3:$AP$150)+ COUNTIFS($AP$3:AP52, AP52) - 1,"") | AN52: =U25 | AO52: SAVINGS | AP52: =IFERROR(VLOOKUP(AN52,JUL!$U$23:$W$38,3,FALSE),"")
AM53: =IFERROR(_xlfn.RANK.EQ(AP53, $AP$3:$AP$150)+ COUNTIFS($AP$3:AP53, AP53) - 1,"") | AN53: =U26 | AO53: SAVINGS | AP53: =IFERROR(VLOOKUP(AN53,JUL!$U$23:$W$38,3,FALSE),"")
AM54: =IFERROR(_xlfn.RANK.EQ(AP54, $AP$3:$AP$150)+ COUNTIFS($AP$3:AP54, AP54) - 1,"") | AN54: =U27 | AO54: SAVINGS | AP54: =IFERROR(VLOOKUP(AN54,JUL!$U$23:$W$38,3,FALSE),"")
AM55: =IFERROR(_xlfn.RANK.EQ(AP55, $AP$3:$AP$150)+ COUNTIFS($AP$3:AP55, AP55) - 1,"") | AN55: =U28 | AO55: SAVINGS | AP55: =IFERROR(VLOOKUP(AN55,JUL!$U$23:$W$38,3,FALSE),"")
AM56: =IFERROR(_xlfn.RANK.EQ(AP56, $AP$3:$AP$150)+ COUNTIFS($AP$3:AP56, AP56) - 1,"") | AN56: =U29 | AO56: SAVINGS | AP56: =IFERROR(VLOOKUP(AN56,JUL!$U$23:$W$38,3,FALSE),"")
AM57: =IFERROR(_xlfn.RANK.EQ(AP57, $AP$3:$AP$150)+ COUNTIFS($AP$3:AP57, AP57) - 1,"") | AN57: =U30 | AO57: SAVINGS | AP57: =IFERROR(VLOOKUP(AN57,JUL!$U$23:$W$38,3,FALSE),"")
AM58: =IFERROR(_xlfn.RANK.EQ(AP58, $AP$3:$AP$150)+ COUNTIFS($AP$3:AP58, AP58) - 1,"") | AN58: =U31 | AO58: SAVINGS | AP58: =IFERROR(VLOOKUP(AN58,JUL!$U$23:$W$38,3,FALSE),"")
AM59: =IFERROR(_xlfn.RANK.EQ(AP59, $AP$3:$AP$150)+ COUNTIFS($AP$3:AP59, AP59) - 1,"") | AN59: =U32 | AO59: SAVINGS | AP59: =IFERROR(VLOOKUP(AN59,JUL!$U$23:$W$38,3,FALSE),"")
AM60: =IFERROR(_xlfn.RANK.EQ(AP60, $AP$3:$AP$150)+ COUNTIFS($AP$3:AP60, AP60) - 1,"") | AN60: =U33 | AO60: SAVINGS | AP60: =IFERROR(VLOOKUP(AN60,JUL!$U$23:$W$38,3,FALSE),"")
AM61: =IFERROR(_xlfn.RANK.EQ(AP61, $AP$3:$AP$150)+ COUNTIFS($AP$3:AP61, AP61) - 1,"") | AN61: =U34 | AO61: SAVINGS | AP61: =IFERROR(VLOOKUP(AN61,JUL!$U$23:$W$38,3,FALSE),"")
... AM65: =IFERROR(_xlfn.RANK.EQ(AP65, $AP$3:$AP$150)+ COUNTIFS($AP$3:AP65, AP65) - 1,"") | AN65: =U38 | AO65: SAVINGS | AP65: =IFERROR(VLOOKUP(AN65,JUL!$U$23:$W$38,3,FALSE),"")

Sheet MAR
B2: MARCH | F2: INCOME | J2: BILLS | N2: EXPENSES | R2: DEBT | V2: SAVINGS | AM2: Ranking | AN2: ITEM | AO2: CATEGORY | AP2: TOTAL SPENT
AM3: =IFERROR(_xlfn.RANK.EQ(AP3, $AP$3:$AP$150)+ COUNTIFS($AP$3:AP3, AP3) - 1,"") | AN3: =F23 | AO3: BILLS | AP3: =IFERROR(VLOOKUP(AN3,MAR!$F$23:$H$38,3,FALSE),"")
F4: =SUM(MAR!$D$23:$D$38) -> 0 | J4: =SUM(MAR!$H$23:$H$38) -> 0 | N4: =SUM(MAR!$M$23:$M$38) -> 0 | R4: =SUM(MAR!$R$23:$R$38) -> 0 | V4: =SUM(MAR!$W$23:$W$38) -> 0 | AM4: =IFERROR(_xlfn.RANK.EQ(AP4, $AP$3:$AP$150)+ COUNTIFS($AP$3:AP4, AP4) - 1,"") | AN4: =F24 | AO4: BILLS | AP4: =IFERROR(VLOOKUP(AN4,MAR!$F$23:$H$38,3,FALSE),"")
B5: SUMMARY | AM5: =IFERROR(_xlfn.RANK.EQ(AP5, $AP$3:$AP$150)+ COUNTIFS($AP$3:AP5, AP5) - 1,"") | AN5: =F25 | AO5: BILLS | AP5: =IFERROR(VLOOKUP(AN5,MAR!$F$23:$H$38,3,FALSE),"")
AM6: =IFERROR(_xlfn.RANK.EQ(AP6, $AP$3:$AP$150)+ COUNTIFS($AP$3:AP6, AP6) - 1,"") | AN6: =F26 | AO6: BILLS | AP6: =IFERROR(VLOOKUP(AN6,MAR!$F$23:$H$38,3,FALSE),"")
B7: INCOME OVERVIEW | V7: RANK | W7: ITEM | X7: AMOUNT | AM7: =IFERROR(_xlfn.RANK.EQ(AP7, $AP$3:$AP$150)+ COUNTIFS($AP$3:AP7, AP7) - 1,"") | AN7: =F27 | AO7: BILLS | AP7: =IFERROR(VLOOKUP(AN7,MAR!$F$23:$H$38,3,FALSE),"")
V8: 1 | W8: =IFERROR(VLOOKUP(V8,$AM$3:$AP$65,2,FALSE),"") | X8: =IFERROR(VLOOKUP(V8,$AM$3:$AP$65,4,FALSE),"") | AM8: =IFERROR(_xlfn.RANK.EQ(AP8, $AP$3:$AP$150)+ COUNTIFS($AP$3:AP8, AP8) - 1,"") | AN8: =F28 | AO8: BILLS | AP8: =IFERROR(VLOOKUP(AN8,MAR!$F$23:$H$38,3,FALSE),"")
V9: 2 | W9: =IFERROR(VLOOKUP(V9,$AM$3:$AP$65,2,FALSE),"") | X9: =IFERROR(VLOOKUP(V9,$AM$3:$AP$65,4,FALSE),"") | AM9: =IFERROR(_xlfn.RANK.EQ(AP9, $AP$3:$AP$150)+ COUNTIFS($AP$3:AP9, AP9) - 1,"") | AN9: =F29 | AO9: BILLS | AP9: =IFERROR(VLOOKUP(AN9,MAR!$F$23:$H$38,3,FALSE),"")
C10: Planned | D10: Actual | V10: 3 | W10: =IFERROR(VLOOKUP(V10,$AM$3:$AP$65,2,FALSE),"") | X10: =IFERROR(VLOOKUP(V10,$AM$3:$AP$65,4,FALSE),"") | AM10: =IFERROR(_xlfn.RANK.EQ(AP10, $AP$3:$AP$150)+ COUNTIFS($AP$3:AP10, AP10) - 1,"") | AN10: =F30 | AO10: BILLS | AP10: =IFERROR(VLOOKUP(AN10,MAR!$F$23:$H$38,3,FALSE),"")
B11: INCOME | C11: =SUM(MAR!$C$23:$C$38) -> 0 | D11: =SUM(MAR!$D$23:$D$38) -> 0 | V11: 4 | W11: =IFERROR(VLOOKUP(V11,$AM$3:$AP$65,2,FALSE),"") | X11: =IFERROR(VLOOKUP(V11,$AM$3:$AP$65,4,FALSE),"") | AM11: =IFERROR(_xlfn.RANK.EQ(AP11, $AP$3:$AP$150)+ COUNTIFS($AP$3:AP11, AP11) - 1,"") | AN11: =F31 | AO11: BILLS | AP11: =IFERROR(VLOOKUP(AN11,MAR!$F$23:$H$38,3,FALSE),"")
B12: BILLS | C12: =SUM(MAR!$G$23:$G$38) -> 0 | D12: =SUM(MAR!$H$23:$H$38) -> 0 | V12: 5 | W12: =IFERROR(VLOOKUP(V12,$AM$3:$AP$65,2,FALSE),"") | X12: =IFERROR(VLOOKUP(V12,$AM$3:$AP$65,4,FALSE),"") | AM12: =IFERROR(_xlfn.RANK.EQ(AP12, $AP$3:$AP$150)+ COUNTIFS($AP$3:AP12, AP12) - 1,"") | AN12: =F32 | AO12: BILLS | AP12: =IFERROR(VLOOKUP(AN12,MAR!$F$23:$H$38,3,FALSE),"")
B13: EXPENSES | C13: =SUM(MAR!$L$23:$L$38) -> 0 | D13: =SUM(MAR!$M$23:$M$38) -> 0 | V13: 6 | W13: =IFERROR(VLOOKUP(V13,$AM$3:$AP$65,2,FALSE),"") | X13: =IFERROR(VLOOKUP(V13,$AM$3:$AP$65,4,FALSE),"") | AM13: =IFERROR(_xlfn.RANK.EQ(AP13, $AP$3:$AP$150)+ COUNTIFS($AP$3:AP13, AP13) - 1,"") | AN13: =F33 | AO13: BILLS | AP13: =IFERROR(VLOOKUP(AN13,MAR!$F$23:$H$38,3,FALSE),"")
B14: DEBT | C14: =SUM(MAR!$Q$23:$Q$38) -> 0 | D14: =SUM(MAR!$R$23:$R$38) -> 0 | V14: 7 | W14: =IFERROR(VLOOKUP(V14,$AM$3:$AP$65,2,FALSE),"") | X14: =IFERROR(VLOOKUP(V14,$AM$3:$AP$65,4,FALSE),"") | AM14: =IFERROR(_xlfn.RANK.EQ(AP14, $AP$3:$AP$150)+ COUNTIFS($AP$3:AP14, AP14) - 1,"") | AN14: =F34 | AO14: BILLS | AP14: =IFERROR(VLOOKUP(AN14,MAR!$F$23:$H$38,3,FALSE),"")
B15: SAVINGS | C15: =SUM(MAR!$V$23:$V$38) -> 0 | D15: =SUM(MAR!$W$23:$W$38) -> 0 | V15: 8 | W15: =IFERROR(VLOOKUP(V15,$AM$3:$AP$65,2,FALSE),"") | X15: =IFERROR(VLOOKUP(V15,$AM$3:$AP$65,4,FALSE),"") | AM15: =IFERROR(_xlfn.RANK.EQ(AP15, $AP$3:$AP$150)+ COUNTIFS($AP$3:AP15, AP15) - 1,"") | AN15: =F35 | AO15: BILLS | AP15: =IFERROR(VLOOKUP(AN15,MAR!$F$23:$H$38,3,FALSE),"")
B16: BALANCE | C16: =(C11-SUM(C12:C15)) -> 0 | D16: =(D11-SUM(D12:D15)) -> 0 | V16: 9 | W16: =IFERROR(VLOOKUP(V16,$AM$3:$AP$65,2,FALSE),"") | X16: =IFERROR(VLOOKUP(V16,$AM$3:$AP$65,4,FALSE),"") | AM16: =IFERROR(_xlfn.RANK.EQ(AP16, $AP$3:$AP$150)+ COUNTIFS($AP$3:AP16, AP16) - 1,"") | AN16: =F36 | AO16: BILLS | AP16: =IFERROR(VLOOKUP(AN16,MAR!$F$23:$H$38,3,FALSE),"")
V17: 10 | W17: =IFERROR(VLOOKUP(V17,$AM$3:$AP$65,2,FALSE),"") | X17: =IFERROR(VLOOKUP(V17,$AM$3:$AP$65,4,FALSE),"") | AM17: =IFERROR(_xlfn.RANK.EQ(AP17, $AP$3:$AP$150)+ COUNTIFS($AP$3:AP17, AP17) - 1,"") | AN17: =F37 | AO17: BILLS | AP17: =IFERROR(VLOOKUP(AN17,MAR!$F$23:$H$38,3,FALSE),"")
V18: 11 | W18: =IFERROR(VLOOKUP(V18,$AM$3:$AP$65,2,FALSE),"") | X18: =IFERROR(VLOOKUP(V18,$AM$3:$AP$65,4,FALSE),"") | AM18: =IFERROR(_xlfn.RANK.EQ(AP18, $AP$3:$AP$150)+ COUNTIFS($AP$3:AP18, AP18) - 1,"") | AN18: =F38 | AO18: BILLS | AP18: =IFERROR(VLOOKUP(AN18,MAR!$F$23:$H$38,3,FALSE),"")
AM19: =IFERROR(_xlfn.RANK.EQ(AP19, $AP$3:$AP$150)+ COUNTIFS($AP$3:AP19, AP19) - 1,"") | AN19: =K23 | AO19: EXPENSES | AP19: =IFERROR(VLOOKUP(AN19,MAR!$K$23:$M$38,3,FALSE),"")
B20: INCOME | F20: BILLS | K20: EXPENSES | P20: DEBT | U20: SAVINGS | AM20: =IFERROR(_xlfn.RANK.EQ(AP20, $AP$3:$AP$150)+ COUNTIFS($AP$3:AP20, AP20) - 1,"") | AN20: =K24 | AO20: EXPENSES | AP20: =IFERROR(VLOOKUP(AN20,MAR!$K$23:$M$38,3,FALSE),"")
AM21: =IFERROR(_xlfn.RANK.EQ(AP21, $AP$3:$AP$150)+ COUNTIFS($AP$3:AP21, AP21) - 1,"") | AN21: =K25 | AO21: EXPENSES | AP21: =IFERROR(VLOOKUP(AN21,MAR!$K$23:$M$38,3,FALSE),"")
B22: Details | C22: Planned | D22: Actual | F22: Details | G22: Planned | H22: Actual | I22: Variance | K22: Details | L22: Planned | M22: Actual | N22: Variance | P22: Details | Q22: Planned | R22: Actual | S22: Variance | U22: Details | V22: Planned | W22: Actual | X22: Variance | AM22: =IFERROR(_xlfn.RANK.EQ(AP22, $AP$3:$AP$150)+ COUNTIFS($AP$3:AP22, AP22) - 1,"") | AN22: =K26 | AO22: EXPENSES | AP22: =IFERROR(VLOOKUP(AN22,MAR!$K$23:$M$38,3,FALSE),"")
I23: =MAR!$G23-MAR!$H23 -> 0 | N23: =MAR!$L23-MAR!$M23 -> 0 | S23: =MAR!$Q23-MAR!$R23 -> 0 | X23: =MAR!$V23-MAR!$W23 -> 0 | AM23: =IFERROR(_xlfn.RANK.EQ(AP23, $AP$3:$AP$150)+ COUNTIFS($AP$3:AP23, AP23) - 1,"") | AN23: =K27 | AO23: EXPENSES | AP23: =IFERROR(VLOOKUP(AN23,MAR!$K$23:$M$38,3,FALSE),"")
I24: =MAR!$G24-MAR!$H24 -> 0 | N24: =MAR!$L24-MAR!$M24 -> 0 | S24: =MAR!$Q24-MAR!$R24 -> 0 | X24: =MAR!$V24-MAR!$W24 -> 0 | AM24: =IFERROR(_xlfn.RANK.EQ(AP24, $AP$3:$AP$150)+ COUNTIFS($AP$3:AP24, AP24) - 1,"") | AN24: =K28 | AO24: EXPENSES | AP24: =IFERROR(VLOOKUP(AN24,MAR!$K$23:$M$38,3,FALSE),"")
I25: =MAR!$G25-MAR!$H25 -> 0 | N25: =MAR!$L25-MAR!$M25 -> 0 | S25: =MAR!$Q25-MAR!$R25 -> 0 | X25: =MAR!$V25-MAR!$W25 -> 0 | AM25: =IFERROR(_xlfn.RANK.EQ(AP25, $AP$3:$AP$150)+ COUNTIFS($AP$3:AP25, AP25) - 1,"") | AN25: =K29 | AO25: EXPENSES | AP25: =IFERROR(VLOOKUP(AN25,MAR!$K$23:$M$38,3,FALSE),"")
I26: =MAR!$G26-MAR!$H26 -> 0 | N26: =MAR!$L26-MAR!$M26 -> 0 | S26: =MAR!$Q26-MAR!$R26 -> 0 | X26: =MAR!$V26-MAR!$W26 -> 0 | AM26: =IFERROR(_xlfn.RANK.EQ(AP26, $AP$3:$AP$150)+ COUNTIFS($AP$3:AP26, AP26) - 1,"") | AN26: =K30 | AO26: EXPENSES | AP26: =IFERROR(VLOOKUP(AN26,MAR!$K$23:$M$38,3,FALSE),"")
I27: =MAR!$G27-MAR!$H27 -> 0 | N27: =MAR!$L27-MAR!$M27 -> 0 | S27: =MAR!$Q27-MAR!$R27 -> 0 | X27: =MAR!$V27-MAR!$W27 -> 0 | AM27: =IFERROR(_xlfn.RANK.EQ(AP27, $AP$3:$AP$150)+ COUNTIFS($AP$3:AP27, AP27) - 1,"") | AN27: =K31 | AO27: EXPENSES | AP27: =IFERROR(VLOOKUP(AN27,MAR!$K$23:$M$38,3,FALSE),"")
I28: =MAR!$G28-MAR!$H28 -> 0 | N28: =MAR!$L28-MAR!$M28 -> 0 | S28: =MAR!$Q28-MAR!$R28 -> 0 | X28: =MAR!$V28-MAR!$W28 -> 0 | AM28: =IFERROR(_xlfn.RANK.EQ(AP28, $AP$3:$AP$150)+ COUNTIFS($AP$3:AP28, AP28) - 1,"") | AN28: =K32 | AO28: EXPENSES | AP28: =IFERROR(VLOOKUP(AN28,MAR!$K$23:$M$38,3,FALSE),"")
I29: =MAR!$G29-MAR!$H29 -> 0 | N29: =MAR!$L29-MAR!$M29 -> 0 | S29: =MAR!$Q29-MAR!$R29 -> 0 | X29: =MAR!$V29-MAR!$W29 -> 0 | AM29: =IFERROR(_xlfn.RANK.EQ(AP29, $AP$3:$AP$150)+ COUNTIFS($AP$3:AP29, AP29) - 1,"") | AN29: =K33 | AO29: EXPENSES | AP29: =IFERROR(VLOOKUP(AN29,MAR!$K$23:$M$38,3,FALSE),"")
I30: =MAR!$G30-MAR!$H30 -> 0 | N30: =MAR!$L30-MAR!$M30 -> 0 | S30: =MAR!$Q30-MAR!$R30 -> 0 | X30: =MAR!$V30-MAR!$W30 -> 0 | AM30: =IFERROR(_xlfn.RANK.EQ(AP30, $AP$3:$AP$150)+ COUNTIFS($AP$3:AP30, AP30) - 1,"") | AN30: =K34 | AO30: EXPENSES | AP30: =IFERROR(VLOOKUP(AN30,MAR!$K$23:$M$38,3,FALSE),"")
I31: =MAR!$G31-MAR!$H31 -> 0 | N31: =MAR!$L31-MAR!$M31 -> 0 | S31: =MAR!$Q31-MAR!$R31 -> 0 | X31: =MAR!$V31-MAR!$W31 -> 0 | AM31: =IFERROR(_xlfn.RANK.EQ(AP31, $AP$3:$AP$150)+ COUNTIFS($AP$3:AP31, AP31) - 1,"") | AN31: =K35 | AO31: EXPENSES | AP31: =IFERROR(VLOOKUP(AN31,MAR!$K$23:$M$38,3,FALSE),"")
I32: =MAR!$G32-MAR!$H32 -> 0 | N32: =MAR!$L32-MAR!$M32 -> 0 | S32: =MAR!$Q32-MAR!$R32 -> 0 | X32: =MAR!$V32-MAR!$W32 -> 0 | AM32: =IFERROR(_xlfn.RANK.EQ(AP32, $AP$3:$AP$150)+ COUNTIFS($AP$3:AP32, AP32) - 1,"") | AN32: =K36 | AO32: EXPENSES | AP32: =IFERROR(VLOOKUP(AN32,MAR!$K$23:$M$38,3,FALSE),"")
I33: =MAR!$G33-MAR!$H33 -> 0 | N33: =MAR!$L33-MAR!$M33 -> 0 | S33: =MAR!$Q33-MAR!$R33 -> 0 | X33: =MAR!$V33-MAR!$W33 -> 0 | AM33: =IFERROR(_xlfn.RANK.EQ(AP33, $AP$3:$AP$150)+ COUNTIFS($AP$3:AP33, AP33) - 1,"") | AN33: =K37 | AO33: EXPENSES | AP33: =IFERROR(VLOOKUP(AN33,MAR!$K$23:$M$38,3,FALSE),"")
I34: =MAR!$G34-MAR!$H34 -> 0 | N34: =MAR!$L34-MAR!$M34 -> 0 | S34: =MAR!$Q34-MAR!$R34 -> 0 | X34: =MAR!$V34-MAR!$W34 -> 0 | AM34: =IFERROR(_xlfn.RANK.EQ(AP34, $AP$3:$AP$150)+ COUNTIFS($AP$3:AP34, AP34) - 1,"") | AN34: =K38 | AO34: DEBTS | AP34: =IFERROR(VLOOKUP(AN34,MAR!$K$23:$M$38,3,FALSE),"")
I35: =MAR!$G35-MAR!$H35 -> 0 | N35: =MAR!$L35-MAR!$M35 -> 0 | S35: =MAR!$Q35-MAR!$R35 -> 0 | X35: =MAR!$V35-MAR!$W35 -> 0 | AM35: =IFERROR(_xlfn.RANK.EQ(AP35, $AP$3:$AP$150)+ COUNTIFS($AP$3:AP35, AP35) - 1,"") | AN35: =P23 | AO35: DEBTS | AP35: =IFERROR(VLOOKUP(AN35,MAR!$P$23:$R$38,3,FALSE),"")
I36: =MAR!$G36-MAR!$H36 -> 0 | N36: =MAR!$L36-MAR!$M36 -> 0 | S36: =MAR!$Q36-MAR!$R36 -> 0 | X36: =MAR!$V36-MAR!$W36 -> 0 | AM36: =IFERROR(_xlfn.RANK.EQ(AP36, $AP$3:$AP$150)+ COUNTIFS($AP$3:AP36, AP36) - 1,"") | AN36: =P24 | AO36: DEBTS | AP36: =IFERROR(VLOOKUP(AN36,MAR!$P$23:$R$38,3,FALSE),"")
I37: =MAR!$G37-MAR!$H37 -> 0 | N37: =MAR!$L37-MAR!$M37 -> 0 | S37: =MAR!$Q37-MAR!$R37 -> 0 | X37: =MAR!$V37-MAR!$W37 -> 0 | AM37: =IFERROR(_xlfn.RANK.EQ(AP37, $AP$3:$AP$150)+ COUNTIFS($AP$3:AP37, AP37) - 1,"") | AN37: =P25 | AO37: DEBTS | AP37: =IFERROR(VLOOKUP(AN37,MAR!$P$23:$R$38,3,FALSE),"")
I38: =MAR!$G38-MAR!$H38 -> 0 | N38: =MAR!$L38-MAR!$M38 -> 0 | S38: =MAR!$Q38-MAR!$R38 -> 0 | X38: =MAR!$V38-MAR!$W38 -> 0 | AM38: =IFERROR(_xlfn.RANK.EQ(AP38, $AP$3:$AP$150)+ COUNTIFS($AP$3:AP38, AP38) - 1,"") | AN38: =P26 | AO38: DEBTS | AP38: =IFERROR(VLOOKUP(AN38,MAR!$P$23:$R$38,3,FALSE),"")
AM39: =IFERROR(_xlfn.RANK.EQ(AP39, $AP$3:$AP$150)+ COUNTIFS($AP$3:AP39, AP39) - 1,"") | AN39: =P27 | AO39: DEBTS | AP39: =IFERROR(VLOOKUP(AN39,MAR!$P$23:$R$38,3,FALSE),"")
AM40: =IFERROR(_xlfn.RANK.EQ(AP40, $AP$3:$AP$150)+ COUNTIFS($AP$3:AP40, AP40) - 1,"") | AN40: =P28 | AO40: DEBTS | AP40: =IFERROR(VLOOKUP(AN40,MAR!$P$23:$R$38,3,FALSE),"")
AM41: =IFERROR(_xlfn.RANK.EQ(AP41, $AP$3:$AP$150)+ COUNTIFS($AP$3:AP41, AP41) - 1,"") | AN41: =P29 | AO41: DEBTS | AP41: =IFERROR(VLOOKUP(AN41,MAR!$P$23:$R$38,3,FALSE),"")
AM42: =IFERROR(_xlfn.RANK.EQ(AP42, $AP$3:$AP$150)+ COUNTIFS($AP$3:AP42, AP42) - 1,"") | AN42: =P30 | AO42: DEBTS | AP42: =IFERROR(VLOOKUP(AN42,MAR!$P$23:$R$38,3,FALSE),"")
AM43: =IFERROR(_xlfn.RANK.EQ(AP43, $AP$3:$AP$150)+ COUNTIFS($AP$3:AP43, AP43) - 1,"") | AN43: =P31 | AO43: DEBTS | AP43: =IFERROR(VLOOKUP(AN43,MAR!$P$23:$R$38,3,FALSE),"")
AM44: =IFERROR(_xlfn.RANK.EQ(AP44, $AP$3:$AP$150)+ COUNTIFS($AP$3:AP44, AP44) - 1,"") | AN44: =P32 | AO44: DEBTS | AP44: =IFERROR(VLOOKUP(AN44,MAR!$P$23:$R$38,3,FALSE),"")
AM45: =IFERROR(_xlfn.RANK.EQ(AP45, $AP$3:$AP$150)+ COUNTIFS($AP$3:AP45, AP45) - 1,"") | AN45: =P33 | AO45: DEBTS | AP45: =IFERROR(VLOOKUP(AN45,MAR!$P$23:$R$38,3,FALSE),"")
AM46: =IFERROR(_xlfn.RANK.EQ(AP46, $AP$3:$AP$150)+ COUNTIFS($AP$3:AP46, AP46) - 1,"") | AN46: =P34 | AO46: DEBTS | AP46: =IFERROR(VLOOKUP(AN46,MAR!$P$23:$R$38,3,FALSE),"")
AM47: =IFERROR(_xlfn.RANK.EQ(AP47, $AP$3:$AP$150)+ COUNTIFS($AP$3:AP47, AP47) - 1,"") | AN47: =P35 | AO47: DEBTS | AP47: =IFERROR(VLOOKUP(AN47,MAR!$P$23:$R$38,3,FALSE),"")
AM48: =IFERROR(_xlfn.RANK.EQ(AP48, $AP$3:$AP$150)+ COUNTIFS($AP$3:AP48, AP48) - 1,"") | AN48: =P36 | AO48: DEBTS | AP48: =IFERROR(VLOOKUP(AN48,MAR!$P$23:$R$38,3,FALSE),"")
AM49: =IFERROR(_xlfn.RANK.EQ(AP49, $AP$3:$AP$150)+ COUNTIFS($AP$3:AP49, AP49) - 1,"") | AN49: =P37 | AO49: SAVINGS | AP49: =IFERROR(VLOOKUP(AN49,MAR!$P$23:$R$38,3,FALSE),"")
AM50: =IFERROR(_xlfn.RANK.EQ(AP50, $AP$3:$AP$150)+ COUNTIFS($AP$3:AP50, AP50) - 1,"") | AN50: =U23 | AO50: SAVINGS | AP50: =IFERROR(VLOOKUP(AN50,MAR!$U$23:$W$38,3,FALSE),"")
AM51: =IFERROR(_xlfn.RANK.EQ(AP51, $AP$3:$AP$150)+ COUNTIFS($AP$3:AP51, AP51) - 1,"") | AN51: =U24 | AO51: SAVINGS | AP51: =IFERROR(VLOOKUP(AN51,MAR!$U$23:$W$38,3,FALSE),"")
AM52: =IFERROR(_xlfn.RANK.EQ(AP52, $AP$3:$AP$150)+ COUNTIFS($AP$3:AP52, AP52) - 1,"") | AN52: =U25 | AO52: SAVINGS | AP52: =IFERROR(VLOOKUP(AN52,MAR!$U$23:$W$38,3,FALSE),"")
AM53: =IFERROR(_xlfn.RANK.EQ(AP53, $AP$3:$AP$150)+ COUNTIFS($AP$3:AP53, AP53) - 1,"") | AN53: =U26 | AO53: SAVINGS | AP53: =IFERROR(VLOOKUP(AN53,MAR!$U$23:$W$38,3,FALSE),"")
AM54: =IFERROR(_xlfn.RANK.EQ(AP54, $AP$3:$AP$150)+ COUNTIFS($AP$3:AP54, AP54) - 1,"") | AN54: =U27 | AO54: SAVINGS | AP54: =IFERROR(VLOOKUP(AN54,MAR!$U$23:$W$38,3,FALSE),"")
AM55: =IFERROR(_xlfn.RANK.EQ(AP55, $AP$3:$AP$150)+ COUNTIFS($AP$3:AP55, AP55) - 1,"") | AN55: =U28 | AO55: SAVINGS | AP55: =IFERROR(VLOOKUP(AN55,MAR!$U$23:$W$38,3,FALSE),"")
AM56: =IFERROR(_xlfn.RANK.EQ(AP56, $AP$3:$AP$150)+ COUNTIFS($AP$3:AP56, AP56) - 1,"") | AN56: =U29 | AO56: SAVINGS | AP56: =IFERROR(VLOOKUP(AN56,MAR!$U$23:$W$38,3,FALSE),"")
AM57: =IFERROR(_xlfn.RANK.EQ(AP57, $AP$3:$AP$150)+ COUNTIFS($AP$3:AP57, AP57) - 1,"") | AN57: =U30 | AO57: SAVINGS | AP57: =IFERROR(VLOOKUP(AN57,MAR!$U$23:$W$38,3,FALSE),"")
AM58: =IFERROR(_xlfn.RANK.EQ(AP58, $AP$3:$AP$150)+ COUNTIFS($AP$3:AP58, AP58) - 1,"") | AN58: =U31 | AO58: SAVINGS | AP58: =IFERROR(VLOOKUP(AN58,MAR!$U$23:$W$38,3,FALSE),"")
AM59: =IFERROR(_xlfn.RANK.EQ(AP59, $AP$3:$AP$150)+ COUNTIFS($AP$3:AP59, AP59) - 1,"") | AN59: =U32 | AO59: SAVINGS | AP59: =IFERROR(VLOOKUP(AN59,MAR!$U$23:$W$38,3,FALSE),"")
AM60: =IFERROR(_xlfn.RANK.EQ(AP60, $AP$3:$AP$150)+ COUNTIFS($AP$3:AP60, AP60) - 1,"") | AN60: =U33 | AO60: SAVINGS | AP60: =IFERROR(VLOOKUP(AN60,MAR!$U$23:$W$38,3,FALSE),"")
AM61: =IFERROR(_xlfn.RANK.EQ(AP61, $AP$3:$AP$150)+ COUNTIFS($AP$3:AP61, AP61) - 1,"") | AN61: =U34 | AO61: SAVINGS | AP61: =IFERROR(VLOOKUP(AN61,MAR!$U$23:$W$38,3,FALSE),"")
... AM65: =IFERROR(_xlfn.RANK.EQ(AP65, $AP$3:$AP$150)+ COUNTIFS($AP$3:AP65, AP65) - 1,"") | AN65: =U38 | AO65: SAVINGS | AP65: =IFERROR(VLOOKUP(AN65,MAR!$U$23:$W$38,3,FALSE),"")

Sheet AUG
B2: AUGUST | F2: INCOME | J2: BILLS | N2: EXPENSES | R2: DEBT | V2: SAVINGS | AM2: Ranking | AN2: ITEM | AO2: CATEGORY | AP2: TOTAL SPENT
AM3: =IFERROR(_xlfn.RANK.EQ(AP3, $AP$3:$AP$150)+ COUNTIFS($AP$3:AP3, AP3) - 1,"") | AN3: =F23 | AO3: BILLS | AP3: =IFERROR(VLOOKUP(AN3,AUG!$F$23:$H$38,3,FALSE),"")
F4: =SUM(AUG!$D$23:$D$38) -> 0 | J4: =SUM(AUG!$H$23:$H$38) -> 0 | N4: =SUM(AUG!$M$23:$M$38) -> 0 | R4: =SUM(AUG!$R$23:$R$38) -> 0 | V4: =SUM(AUG!$W$23:$W$38) -> 0 | AM4: =IFERROR(_xlfn.RANK.EQ(AP4, $AP$3:$AP$150)+ COUNTIFS($AP$3:AP4, AP4) - 1,"") | AN4: =F24 | AO4: BILLS | AP4: =IFERROR(VLOOKUP(AN4,AUG!$F$23:$H$38,3,FALSE),"")
B5: SUMMARY | AM5: =IFERROR(_xlfn.RANK.EQ(AP5, $AP$3:$AP$150)+ COUNTIFS($AP$3:AP5, AP5) - 1,"") | AN5: =F25 | AO5: BILLS | AP5: =IFERROR(VLOOKUP(AN5,AUG!$F$23:$H$38,3,FALSE),"")
AM6: =IFERROR(_xlfn.RANK.EQ(AP6, $AP$3:$AP$150)+ COUNTIFS($AP$3:AP6, AP6) - 1,"") | AN6: =F26 | AO6: BILLS | AP6: =IFERROR(VLOOKUP(AN6,AUG!$F$23:$H$38,3,FALSE),"")
B7: INCOME OVERVIEW | V7: RANK | W7: ITEM | X7: AMOUNT | AM7: =IFERROR(_xlfn.RANK.EQ(AP7, $AP$3:$AP$150)+ COUNTIFS($AP$3:AP7, AP7) - 1,"") | AN7: =F27 | AO7: BILLS | AP7: =IFERROR(VLOOKUP(AN7,AUG!$F$23:$H$38,3,FALSE),"")
V8: 1 | W8: =IFERROR(VLOOKUP(V8,$AM$3:$AP$65,2,FALSE),"") | X8: =IFERROR(VLOOKUP(V8,$AM$3:$AP$65,4,FALSE),"") | AM8: =IFERROR(_xlfn.RANK.EQ(AP8, $AP$3:$AP$150)+ COUNTIFS($AP$3:AP8, AP8) - 1,"") | AN8: =F28 | AO8: BILLS | AP8: =IFERROR(VLOOKUP(AN8,AUG!$F$23:$H$38,3,FALSE),"")
V9: 2 | W9: =IFERROR(VLOOKUP(V9,$AM$3:$AP$65,2,FALSE),"") | X9: =IFERROR(VLOOKUP(V9,$AM$3:$AP$65,4,FALSE),"") | AM9: =IFERROR(_xlfn.RANK.EQ(AP9, $AP$3:$AP$150)+ COUNTIFS($AP$3:AP9, AP9) - 1,"") | AN9: =F29 | AO9: BILLS | AP9: =IFERROR(VLOOKUP(AN9,AUG!$F$23:$H$38,3,FALSE),"")
C10: Planned | D10: Actual | V10: 3 | W10: =IFERROR(VLOOKUP(V10,$AM$3:$AP$65,2,FALSE),"") | X10: =IFERROR(VLOOKUP(V10,$AM$3:$AP$65,4,FALSE),"") | AM10: =IFERROR(_xlfn.RANK.EQ(AP10, $AP$3:$AP$150)+ COUNTIFS($AP$3:AP10, AP10) - 1,"") | AN10: =F30 | AO10: BILLS | AP10: =IFERROR(VLOOKUP(AN10,AUG!$F$23:$H$38,3,FALSE),"")
B11: INCOME | C11: =SUM(AUG!$C$23:$C$38) -> 0 | D11: =SUM(AUG!$D$23:$D$38) -> 0 | V11: 4 | W11: =IFERROR(VLOOKUP(V11,$AM$3:$AP$65,2,FALSE),"") | X11: =IFERROR(VLOOKUP(V11,$AM$3:$AP$65,4,FALSE),"") | AM11: =IFERROR(_xlfn.RANK.EQ(AP11, $AP$3:$AP$150)+ COUNTIFS($AP$3:AP11, AP11) - 1,"") | AN11: =F31 | AO11: BILLS | AP11: =IFERROR(VLOOKUP(AN11,AUG!$F$23:$H$38,3,FALSE),"")
B12: BILLS | C12: =SUM(AUG!$G$23:$G$38) -> 0 | D12: =SUM(AUG!$H$23:$H$38) -> 0 | V12: 5 | W12: =IFERROR(VLOOKUP(V12,$AM$3:$AP$65,2,FALSE),"") | X12: =IFERROR(VLOOKUP(V12,$AM$3:$AP$65,4,FALSE),"") | AM12: =IFERROR(_xlfn.RANK.EQ(AP12, $AP$3:$AP$150)+ COUNTIFS($AP$3:AP12, AP12) - 1,"") | AN12: =F32 | AO12: BILLS | AP12: =IFERROR(VLOOKUP(AN12,AUG!$F$23:$H$38,3,FALSE),"")
B13: EXPENSES | C13: =SUM(AUG!$L$23:$L$38) -> 0 | D13: =SUM(AUG!$M$23:$M$38) -> 0 | V13: 6 | W13: =IFERROR(VLOOKUP(V13,$AM$3:$AP$65,2,FALSE),"") | X13: =IFERROR(VLOOKUP(V13,$AM$3:$AP$65,4,FALSE),"") | AM13: =IFERROR(_xlfn.RANK.EQ(AP13, $AP$3:$AP$150)+ COUNTIFS($AP$3:AP13, AP13) - 1,"") | AN13: =F33 | AO13: BILLS | AP13: =IFERROR(VLOOKUP(AN13,AUG!$F$23:$H$38,3,FALSE),"")
B14: DEBT | C14: =SUM(AUG!$Q$23:$Q$38) -> 0 | D14: =SUM(AUG!$R$23:$R$38) -> 0 | V14: 7 | W14: =IFERROR(VLOOKUP(V14,$AM$3:$AP$65,2,FALSE),"") | X14: =IFERROR(VLOOKUP(V14,$AM$3:$AP$65,4,FALSE),"") | AM14: =IFERROR(_xlfn.RANK.EQ(AP14, $AP$3:$AP$150)+ COUNTIFS($AP$3:AP14, AP14) - 1,"") | AN14: =F34 | AO14: BILLS | AP14: =IFERROR(VLOOKUP(AN14,AUG!$F$23:$H$38,3,FALSE),"")
B15: SAVINGS | C15: =SUM(AUG!$V$23:$V$38) -> 0 | D15: =SUM(AUG!$W$23:$W$38) -> 0 | V15: 8 | W15: =IFERROR(VLOOKUP(V15,$AM$3:$AP$65,2,FALSE),"") | X15: =IFERROR(VLOOKUP(V15,$AM$3:$AP$65,4,FALSE),"") | AM15: =IFERROR(_xlfn.RANK.EQ(AP15, $AP$3:$AP$150)+ COUNTIFS($AP$3:AP15, AP15) - 1,"") | AN15: =F35 | AO15: BILLS | AP15: =IFERROR(VLOOKUP(AN15,AUG!$F$23:$H$38,3,FALSE),"")
B16: BALANCE | C16: =(C11-SUM(C12:C15)) -> 0 | D16: =(D11-SUM(D12:D15)) -> 0 | V16: 9 | W16: =IFERROR(VLOOKUP(V16,$AM$3:$AP$65,2,FALSE),"") | X16: =IFERROR(VLOOKUP(V16,$AM$3:$AP$65,4,FALSE),"") | AM16: =IFERROR(_xlfn.RANK.EQ(AP16, $AP$3:$AP$150)+ COUNTIFS($AP$3:AP16, AP16) - 1,"") | AN16: =F36 | AO16: BILLS | AP16: =IFERROR(VLOOKUP(AN16,AUG!$F$23:$H$38,3,FALSE),"")
V17: 10 | W17: =IFERROR(VLOOKUP(V17,$AM$3:$AP$65,2,FALSE),"") | X17: =IFERROR(VLOOKUP(V17,$AM$3:$AP$65,4,FALSE),"") | AM17: =IFERROR(_xlfn.RANK.EQ(AP17, $AP$3:$AP$150)+ COUNTIFS($AP$3:AP17, AP17) - 1,"") | AN17: =F37 | AO17: BILLS | AP17: =IFERROR(VLOOKUP(AN17,AUG!$F$23:$H$38,3,FALSE),"")
V18: 11 | W18: =IFERROR(VLOOKUP(V18,$AM$3:$AP$65,2,FALSE),"") | X18: =IFERROR(VLOOKUP(V18,$AM$3:$AP$65,4,FALSE),"") | AM18: =IFERROR(_xlfn.RANK.EQ(AP18, $AP$3:$AP$150)+ COUNTIFS($AP$3:AP18, AP18) - 1,"") | AN18: =F38 | AO18: BILLS | AP18: =IFERROR(VLOOKUP(AN18,AUG!$F$23:$H$38,3,FALSE),"")
AM19: =IFERROR(_xlfn.RANK.EQ(AP19, $AP$3:$AP$150)+ COUNTIFS($AP$3:AP19, AP19) - 1,"") | AN19: =K23 | AO19: EXPENSES | AP19: =IFERROR(VLOOKUP(AN19,AUG!$K$23:$M$38,3,FALSE),"")
B20: INCOME | F20: BILLS | K20: EXPENSES | P20: DEBT | U20: SAVINGS | AM20: =IFERROR(_xlfn.RANK.EQ(AP20, $AP$3:$AP$150)+ COUNTIFS($AP$3:AP20, AP20) - 1,"") | AN20: =K24 | AO20: EXPENSES | AP20: =IFERROR(VLOOKUP(AN20,AUG!$K$23:$M$38,3,FALSE),"")
AM21: =IFERROR(_xlfn.RANK.EQ(AP21, $AP$3:$AP$150)+ COUNTIFS($AP$3:AP21, AP21) - 1,"") | AN21: =K25 | AO21: EXPENSES | AP21: =IFERROR(VLOOKUP(AN21,AUG!$K$23:$M$38,3,FALSE),"")
B22: Details | C22: Planned | D22: Actual | F22: Details | G22: Planned | H22: Actual | I22: Variance | K22: Details | L22: Planned | M22: Actual | N22: Variance | P22: Details | Q22: Planned | R22: Actual | S22: Variance | U22: Details | V22: Planned | W22: Actual | X22: Variance | AM22: =IFERROR(_xlfn.RANK.EQ(AP22, $AP$3:$AP$150)+ COUNTIFS($AP$3:AP22, AP22) - 1,"") | AN22: =K26 | AO22: EXPENSES | AP22: =IFERROR(VLOOKUP(AN22,AUG!$K$23:$M$38,3,FALSE),"")
I23: =AUG!$G23-AUG!$H23 -> 0 | N23: =AUG!$L23-AUG!$M23 -> 0 | S23: =AUG!$Q23-AUG!$R23 -> 0 | X23: =AUG!$V23-AUG!$W23 -> 0 | AM23: =IFERROR(_xlfn.RANK.EQ(AP23, $AP$3:$AP$150)+ COUNTIFS($AP$3:AP23, AP23) - 1,"") | AN23: =K27 | AO23: EXPENSES | AP23: =IFERROR(VLOOKUP(AN23,AUG!$K$23:$M$38,3,FALSE),"")
I24: =AUG!$G24-AUG!$H24 -> 0 | N24: =AUG!$L24-AUG!$M24 -> 0 | S24: =AUG!$Q24-AUG!$R24 -> 0 | X24: =AUG!$V24-AUG!$W24 -> 0 | AM24: =IFERROR(_xlfn.RANK.EQ(AP24, $AP$3:$AP$150)+ COUNTIFS($AP$3:AP24, AP24) - 1,"") | AN24: =K28 | AO24: EXPENSES | AP24: =IFERROR(VLOOKUP(AN24,AUG!$K$23:$M$38,3,FALSE),"")
I25: =AUG!$G25-AUG!$H25 -> 0 | N25: =AUG!$L25-AUG!$M25 -> 0 | S25: =AUG!$Q25-AUG!$R25 -> 0 | X25: =AUG!$V25-AUG!$W25 -> 0 | AM25: =IFERROR(_xlfn.RANK.EQ(AP25, $AP$3:$AP$150)+ COUNTIFS($AP$3:AP25, AP25) - 1,"") | AN25: =K29 | AO25: EXPENSES | AP25: =IFERROR(VLOOKUP(AN25,AUG!$K$23:$M$38,3,FALSE),"")
I26: =AUG!$G26-AUG!$H26 -> 0 | N26: =AUG!$L26-AUG!$M26 -> 0 | S26: =AUG!$Q26-AUG!$R26 -> 0 | X26: =AUG!$V26-AUG!$W26 -> 0 | AM26: =IFERROR(_xlfn.RANK.EQ(AP26, $AP$3:$AP$150)+ COUNTIFS($AP$3:AP26, AP26) - 1,"") | AN26: =K30 | AO26: EXPENSES | AP26: =IFERROR(VLOOKUP(AN26,AUG!$K$23:$M$38,3,FALSE),"")
I27: =AUG!$G27-AUG!$H27 -> 0 | N27: =AUG!$L27-AUG!$M27 -> 0 | S27: =AUG!$Q27-AUG!$R27 -> 0 | X27: =AUG!$V27-AUG!$W27 -> 0 | AM27: =IFERROR(_xlfn.RANK.EQ(AP27, $AP$3:$AP$150)+ COUNTIFS($AP$3:AP27, AP27) - 1,"") | AN27: =K31 | AO27: EXPENSES | AP27: =IFERROR(VLOOKUP(AN27,AUG!$K$23:$M$38,3,FALSE),"")
I28: =AUG!$G28-AUG!$H28 -> 0 | N28: =AUG!$L28-AUG!$M28 -> 0 | S28: =AUG!$Q28-AUG!$R28 -> 0 | X28: =AUG!$V28-AUG!$W28 -> 0 | AM28: =IFERROR(_xlfn.RANK.EQ(AP28, $AP$3:$AP$150)+ COUNTIFS($AP$3:AP28, AP28) - 1,"") | AN28: =K32 | AO28: EXPENSES | AP28: =IFERROR(VLOOKUP(AN28,AUG!$K$23:$M$38,3,FALSE),"")
I29: =AUG!$G29-AUG!$H29 -> 0 | N29: =AUG!$L29-AUG!$M29 -> 0 | S29: =AUG!$Q29-AUG!$R29 -> 0 | X29: =AUG!$V29-AUG!$W29 -> 0 | AM29: =IFERROR(_xlfn.RANK.EQ(AP29, $AP$3:$AP$150)+ COUNTIFS($AP$3:AP29, AP29) - 1,"") | AN29: =K33 | AO29: EXPENSES | AP29: =IFERROR(VLOOKUP(AN29,AUG!$K$23:$M$38,3,FALSE),"")
I30: =AUG!$G30-AUG!$H30 -> 0 | N30: =AUG!$L30-AUG!$M30 -> 0 | S30: =AUG!$Q30-AUG!$R30 -> 0 | X30: =AUG!$V30-AUG!$W30 -> 0 | AM30: =IFERROR(_xlfn.RANK.EQ(AP30, $AP$3:$AP$150)+ COUNTIFS($AP$3:AP30, AP30) - 1,"") | AN30: =K34 | AO30: EXPENSES | AP30: =IFERROR(VLOOKUP(AN30,AUG!$K$23:$M$38,3,FALSE),"")
I31: =AUG!$G31-AUG!$H31 -> 0 | N31: =AUG!$L31-AUG!$M31 -> 0 | S31: =AUG!$Q31-AUG!$R31 -> 0 | X31: =AUG!$V31-AUG!$W31 -> 0 | AM31: =IFERROR(_xlfn.RANK.EQ(AP31, $AP$3:$AP$150)+ COUNTIFS($AP$3:AP31, AP31) - 1,"") | AN31: =K35 | AO31: EXPENSES | AP31: =IFERROR(VLOOKUP(AN31,AUG!$K$23:$M$38,3,FALSE),"")
I32: =AUG!$G32-AUG!$H32 -> 0 | N32: =AUG!$L32-AUG!$M32 -> 0 | S32: =AUG!$Q32-AUG!$R32 -> 0 | X32: =AUG!$V32-AUG!$W32 -> 0 | AM32: =IFERROR(_xlfn.RANK.EQ(AP32, $AP$3:$AP$150)+ COUNTIFS($AP$3:AP32, AP32) - 1,"") | AN32: =K36 | AO32: EXPENSES | AP32: =IFERROR(VLOOKUP(AN32,AUG!$K$23:$M$38,3,FALSE),"")
I33: =AUG!$G33-AUG!$H33 -> 0 | N33: =AUG!$L33-AUG!$M33 -> 0 | S33: =AUG!$Q33-AUG!$R33 -> 0 | X33: =AUG!$V33-AUG!$W33 -> 0 | AM33: =IFERROR(_xlfn.RANK.EQ(AP33, $AP$3:$AP$150)+ COUNTIFS($AP$3:AP33, AP33) - 1,"") | AN33: =K37 | AO33: EXPENSES | AP33: =IFERROR(VLOOKUP(AN33,AUG!$K$23:$M$38,3,FALSE),"")
I34: =AUG!$G34-AUG!$H34 -> 0 | N34: =AUG!$L34-AUG!$M34 -> 0 | S34: =AUG!$Q34-AUG!$R34 -> 0 | X34: =AUG!$V34-AUG!$W34 -> 0 | AM34: =IFERROR(_xlfn.RANK.EQ(AP34, $AP$3:$AP$150)+ COUNTIFS($AP$3:AP34, AP34) - 1,"") | AN34: =K38 | AO34: DEBTS | AP34: =IFERROR(VLOOKUP(AN34,AUG!$K$23:$M$38,3,FALSE),"")
I35: =AUG!$G35-AUG!$H35 -> 0 | N35: =AUG!$L35-AUG!$M35 -> 0 | S35: =AUG!$Q35-AUG!$R35 -> 0 | X35: =AUG!$V35-AUG!$W35 -> 0 | AM35: =IFERROR(_xlfn.RANK.EQ(AP35, $AP$3:$AP$150)+ COUNTIFS($AP$3:AP35, AP35) - 1,"") | AN35: =P23 | AO35: DEBTS | AP35: =IFERROR(VLOOKUP(AN35,AUG!$P$23:$R$38,3,FALSE),"")
I36: =AUG!$G36-AUG!$H36 -> 0 | N36: =AUG!$L36-AUG!$M36 -> 0 | S36: =AUG!$Q36-AUG!$R36 -> 0 | X36: =AUG!$V36-AUG!$W36 -> 0 | AM36: =IFERROR(_xlfn.RANK.EQ(AP36, $AP$3:$AP$150)+ COUNTIFS($AP$3:AP36, AP36) - 1,"") | AN36: =P24 | AO36: DEBTS | AP36: =IFERROR(VLOOKUP(AN36,AUG!$P$23:$R$38,3,FALSE),"")
I37: =AUG!$G37-AUG!$H37 -> 0 | N37: =AUG!$L37-AUG!$M37 -> 0 | S37: =AUG!$Q37-AUG!$R37 -> 0 | X37: =AUG!$V37-AUG!$W37 -> 0 | AM37: =IFERROR(_xlfn.RANK.EQ(AP37, $AP$3:$AP$150)+ COUNTIFS($AP$3:AP37, AP37) - 1,"") | AN37: =P25 | AO37: DEBTS | AP37: =IFERROR(VLOOKUP(AN37,AUG!$P$23:$R$38,3,FALSE),"")
I38: =AUG!$G38-AUG!$H38 -> 0 | N38: =AUG!$L38-AUG!$M38 -> 0 | S38: =AUG!$Q38-AUG!$R38 -> 0 | X38: =AUG!$V38-AUG!$W38 -> 0 | AM38: =IFERROR(_xlfn.RANK.EQ(AP38, $AP$3:$AP$150)+ COUNTIFS($AP$3:AP38, AP38) - 1,"") | AN38: =P26 | AO38: DEBTS | AP38: =IFERROR(VLOOKUP(AN38,AUG!$P$23:$R$38,3,FALSE),"")
AM39: =IFERROR(_xlfn.RANK.EQ(AP39, $AP$3:$AP$150)+ COUNTIFS($AP$3:AP39, AP39) - 1,"") | AN39: =P27 | AO39: DEBTS | AP39: =IFERROR(VLOOKUP(AN39,AUG!$P$23:$R$38,3,FALSE),"")
AM40: =IFERROR(_xlfn.RANK.EQ(AP40, $AP$3:$AP$150)+ COUNTIFS($AP$3:AP40, AP40) - 1,"") | AN40: =P28 | AO40: DEBTS | AP40: =IFERROR(VLOOKUP(AN40,AUG!$P$23:$R$38,3,FALSE),"")
AM41: =IFERROR(_xlfn.RANK.EQ(AP41, $AP$3:$AP$150)+ COUNTIFS($AP$3:AP41, AP41) - 1,"") | AN41: =P29 | AO41: DEBTS | AP41: =IFERROR(VLOOKUP(AN41,AUG!$P$23:$R$38,3,FALSE),"")
AM42: =IFERROR(_xlfn.RANK.EQ(AP42, $AP$3:$AP$150)+ COUNTIFS($AP$3:AP42, AP42) - 1,"") | AN42: =P30 | AO42: DEBTS | AP42: =IFERROR(VLOOKUP(AN42,AUG!$P$23:$R$38,3,FALSE),"")
AM43: =IFERROR(_xlfn.RANK.EQ(AP43, $AP$3:$AP$150)+ COUNTIFS($AP$3:AP43, AP43) - 1,"") | AN43: =P31 | AO43: DEBTS | AP43: =IFERROR(VLOOKUP(AN43,AUG!$P$23:$R$38,3,FALSE),"")
AM44: =IFERROR(_xlfn.RANK.EQ(AP44, $AP$3:$AP$150)+ COUNTIFS($AP$3:AP44, AP44) - 1,"") | AN44: =P32 | AO44: DEBTS | AP44: =IFERROR(VLOOKUP(AN44,AUG!$P$23:$R$38,3,FALSE),"")
AM45: =IFERROR(_xlfn.RANK.EQ(AP45, $AP$3:$AP$150)+ COUNTIFS($AP$3:AP45, AP45) - 1,"") | AN45: =P33 | AO45: DEBTS | AP45: =IFERROR(VLOOKUP(AN45,AUG!$P$23:$R$38,3,FALSE),"")
AM46: =IFERROR(_xlfn.RANK.EQ(AP46, $AP$3:$AP$150)+ COUNTIFS($AP$3:AP46, AP46) - 1,"") | AN46: =P34 | AO46: DEBTS | AP46: =IFERROR(VLOOKUP(AN46,AUG!$P$23:$R$38,3,FALSE),"")
AM47: =IFERROR(_xlfn.RANK.EQ(AP47, $AP$3:$AP$150)+ COUNTIFS($AP$3:AP47, AP47) - 1,"") | AN47: =P35 | AO47: DEBTS | AP47: =IFERROR(VLOOKUP(AN47,AUG!$P$23:$R$38,3,FALSE),"")
AM48: =IFERROR(_xlfn.RANK.EQ(AP48, $AP$3:$AP$150)+ COUNTIFS($AP$3:AP48, AP48) - 1,"") | AN48: =P36 | AO48: DEBTS | AP48: =IFERROR(VLOOKUP(AN48,AUG!$P$23:$R$38,3,FALSE),"")
AM49: =IFERROR(_xlfn.RANK.EQ(AP49, $AP$3:$AP$150)+ COUNTIFS($AP$3:AP49, AP49) - 1,"") | AN49: =P37 | AO49: SAVINGS | AP49: =IFERROR(VLOOKUP(AN49,AUG!$P$23:$R$38,3,FALSE),"")
AM50: =IFERROR(_xlfn.RANK.EQ(AP50, $AP$3:$AP$150)+ COUNTIFS($AP$3:AP50, AP50) - 1,"") | AN50: =U23 | AO50: SAVINGS | AP50: =IFERROR(VLOOKUP(AN50,AUG!$U$23:$W$38,3,FALSE),"")
AM51: =IFERROR(_xlfn.RANK.EQ(AP51, $AP$3:$AP$150)+ COUNTIFS($AP$3:AP51, AP51) - 1,"") | AN51: =U24 | AO51: SAVINGS | AP51: =IFERROR(VLOOKUP(AN51,AUG!$U$23:$W$38,3,FALSE),"")
AM52: =IFERROR(_xlfn.RANK.EQ(AP52, $AP$3:$AP$150)+ COUNTIFS($AP$3:AP52, AP52) - 1,"") | AN52: =U25 | AO52: SAVINGS | AP52: =IFERROR(VLOOKUP(AN52,AUG!$U$23:$W$38,3,FALSE),"")
AM53: =IFERROR(_xlfn.RANK.EQ(AP53, $AP$3:$AP$150)+ COUNTIFS($AP$3:AP53, AP53) - 1,"") | AN53: =U26 | AO53: SAVINGS | AP53: =IFERROR(VLOOKUP(AN53,AUG!$U$23:$W$38,3,FALSE),"")
AM54: =IFERROR(_xlfn.RANK.EQ(AP54, $AP$3:$AP$150)+ COUNTIFS($AP$3:AP54, AP54) - 1,"") | AN54: =U27 | AO54: SAVINGS | AP54: =IFERROR(VLOOKUP(AN54,AUG!$U$23:$W$38,3,FALSE),"")
AM55: =IFERROR(_xlfn.RANK.EQ(AP55, $AP$3:$AP$150)+ COUNTIFS($AP$3:AP55, AP55) - 1,"") | AN55: =U28 | AO55: SAVINGS | AP55: =IFERROR(VLOOKUP(AN55,AUG!$U$23:$W$38,3,FALSE),"")
AM56: =IFERROR(_xlfn.RANK.EQ(AP56, $AP$3:$AP$150)+ COUNTIFS($AP$3:AP56, AP56) - 1,"") | AN56: =U29 | AO56: SAVINGS | AP56: =IFERROR(VLOOKUP(AN56,AUG!$U$23:$W$38,3,FALSE),"")
AM57: =IFERROR(_xlfn.RANK.EQ(AP57, $AP$3:$AP$150)+ COUNTIFS($AP$3:AP57, AP57) - 1,"") | AN57: =U30 | AO57: SAVINGS | AP57: =IFERROR(VLOOKUP(AN57,AUG!$U$23:$W$38,3,FALSE),"")
AM58: =IFERROR(_xlfn.RANK.EQ(AP58, $AP$3:$AP$150)+ COUNTIFS($AP$3:AP58, AP58) - 1,"") | AN58: =U31 | AO58: SAVINGS | AP58: =IFERROR(VLOOKUP(AN58,AUG!$U$23:$W$38,3,FALSE),"")
AM59: =IFERROR(_xlfn.RANK.EQ(AP59, $AP$3:$AP$150)+ COUNTIFS($AP$3:AP59, AP59) - 1,"") | AN59: =U32 | AO59: SAVINGS | AP59: =IFERROR(VLOOKUP(AN59,AUG!$U$23:$W$38,3,FALSE),"")
AM60: =IFERROR(_xlfn.RANK.EQ(AP60, $AP$3:$AP$150)+ COUNTIFS($AP$3:AP60, AP60) - 1,"") | AN60: =U33 | AO60: SAVINGS | AP60: =IFERROR(VLOOKUP(AN60,AUG!$U$23:$W$38,3,FALSE),"")
AM61: =IFERROR(_xlfn.RANK.EQ(AP61, $AP$3:$AP$150)+ COUNTIFS($AP$3:AP61, AP61) - 1,"") | AN61: =U34 | AO61: SAVINGS | AP61: =IFERROR(VLOOKUP(AN61,AUG!$U$23:$W$38,3,FALSE),"")
... AM65: =IFERROR(_xlfn.RANK.EQ(AP65, $AP$3:$AP$150)+ COUNTIFS($AP$3:AP65, AP65) - 1,"") | AN65: =U38 | AO65: SAVINGS | AP65: =IFERROR(VLOOKUP(AN65,AUG!$U$23:$W$38,3,FALSE),"")

Sheet SEPT
B2: SEPTEMBER | F2: INCOME | J2: BILLS | N2: EXPENSES | R2: DEBT | V2: SAVINGS | AM2: Ranking | AN2: ITEM | AO2: CATEGORY | AP2: TOTAL SPENT
AM3: =IFERROR(_xlfn.RANK.EQ(AP3, $AP$3:$AP$150)+ COUNTIFS($AP$3:AP3, AP3) - 1,"") | AN3: =F23 | AO3: BILLS | AP3: =IFERROR(VLOOKUP(AN3,SEPT!$F$23:$H$38,3,FALSE),"")
F4: =SUM(SEPT!$D$23:$D$38) -> 0 | J4: =SUM(SEPT!$H$23:$H$38) -> 0 | N4: =SUM(SEPT!$M$23:$M$38) -> 0 | R4: =SUM(SEPT!$R$23:$R$38) -> 0 | V4: =SUM(SEPT!$W$23:$W$38) -> 0 | AM4: =IFERROR(_xlfn.RANK.EQ(AP4, $AP$3:$AP$150)+ COUNTIFS($AP$3:AP4, AP4) - 1,"") | AN4: =F24 | AO4: BILLS | AP4: =IFERROR(VLOOKUP(AN4,SEPT!$F$23:$H$38,3,FALSE),"")
B5: SUMMARY | AM5: =IFERROR(_xlfn.RANK.EQ(AP5, $AP$3:$AP$150)+ COUNTIFS($AP$3:AP5, AP5) - 1,"") | AN5: =F25 | AO5: BILLS | AP5: =IFERROR(VLOOKUP(AN5,SEPT!$F$23:$H$38,3,FALSE),"")
AM6: =IFERROR(_xlfn.RANK.EQ(AP6, $AP$3:$AP$150)+ COUNTIFS($AP$3:AP6, AP6) - 1,"") | AN6: =F26 | AO6: BILLS | AP6: =IFERROR(VLOOKUP(AN6,SEPT!$F$23:$H$38,3,FALSE),"")
B7: INCOME OVERVIEW | V7: RANK | W7: ITEM | X7: AMOUNT | AM7: =IFERROR(_xlfn.RANK.EQ(AP7, $AP$3:$AP$150)+ COUNTIFS($AP$3:AP7, AP7) - 1,"") | AN7: =F27 | AO7: BILLS | AP7: =IFERROR(VLOOKUP(AN7,SEPT!$F$23:$H$38,3,FALSE),"")
V8: 1 | W8: =IFERROR(VLOOKUP(V8,$AM$3:$AP$65,2,FALSE),"") | X8: =IFERROR(VLOOKUP(V8,$AM$3:$AP$65,4,FALSE),"") | AM8: =IFERROR(_xlfn.RANK.EQ(AP8, $AP$3:$AP$150)+ COUNTIFS($AP$3:AP8, AP8) - 1,"") | AN8: =F28 | AO8: BILLS | AP8: =IFERROR(VLOOKUP(AN8,SEPT!$F$23:$H$38,3,FALSE),"")
V9: 2 | W9: =IFERROR(VLOOKUP(V9,$AM$3:$AP$65,2,FALSE),"") | X9: =IFERROR(VLOOKUP(V9,$AM$3:$AP$65,4,FALSE),"") | AM9: =IFERROR(_xlfn.RANK.EQ(AP9, $AP$3:$AP$150)+ COUNTIFS($AP$3:AP9, AP9) - 1,"") | AN9: =F29 | AO9: BILLS | AP9: =IFERROR(VLOOKUP(AN9,SEPT!$F$23:$H$38,3,FALSE),"")
C10: Planned | D10: Actual | V10: 3 | W10: =IFERROR(VLOOKUP(V10,$AM$3:$AP$65,2,FALSE),"") | X10: =IFERROR(VLOOKUP(V10,$AM$3:$AP$65,4,FALSE),"") | AM10: =IFERROR(_xlfn.RANK.EQ(AP10, $AP$3:$AP$150)+ COUNTIFS($AP$3:AP10, AP10) - 1,"") | AN10: =F30 | AO10: BILLS | AP10: =IFERROR(VLOOKUP(AN10,SEPT!$F$23:$H$38,3,FALSE),"")
B11: INCOME | C11: =SUM(SEPT!$C$23:$C$38) -> 0 | D11: =SUM(SEPT!$D$23:$D$38) -> 0 | V11: 4 | W11: =IFERROR(VLOOKUP(V11,$AM$3:$AP$65,2,FALSE),"") | X11: =IFERROR(VLOOKUP(V11,$AM$3:$AP$65,4,FALSE),"") | AM11: =IFERROR(_xlfn.RANK.EQ(AP11, $AP$3:$AP$150)+ COUNTIFS($AP$3:AP11, AP11) - 1,"") | AN11: =F31 | AO11: BILLS | AP11: =IFERROR(VLOOKUP(AN11,SEPT!$F$23:$H$38,3,FALSE),"")
B12: BILLS | C12: =SUM(SEPT!$G$23:$G$38) -> 0 | D12: =SUM(SEPT!$H$23:$H$38) -> 0 | V12: 5 | W12: =IFERROR(VLOOKUP(V12,$AM$3:$AP$65,2,FALSE),"") | X12: =IFERROR(VLOOKUP(V12,$AM$3:$AP$65,4,FALSE),"") | AM12: =IFERROR(_xlfn.RANK.EQ(AP12, $AP$3:$AP$150)+ COUNTIFS($AP$3:AP12, AP12) - 1,"") | AN12: =F32 | AO12: BILLS | AP12: =IFERROR(VLOOKUP(AN12,SEPT!$F$23:$H$38,3,FALSE),"")
B13: EXPENSES | C13: =SUM(SEPT!$L$23:$L$38) -> 0 | D13: =SUM(SEPT!$M$23:$M$38) -> 0 | V13: 6 | W13: =IFERROR(VLOOKUP(V13,$AM$3:$AP$65,2,FALSE),"") | X13: =IFERROR(VLOOKUP(V13,$AM$3:$AP$65,4,FALSE),"") | AM13: =IFERROR(_xlfn.RANK.EQ(AP13, $AP$3:$AP$150)+ COUNTIFS($AP$3:AP13, AP13) - 1,"") | AN13: =F33 | AO13: BILLS | AP13: =IFERROR(VLOOKUP(AN13,SEPT!$F$23:$H$38,3,FALSE),"")
B14: DEBT | C14: =SUM(SEPT!$Q$23:$Q$38) -> 0 | D14: =SUM(SEPT!$R$23:$R$38) -> 0 | V14: 7 | W14: =IFERROR(VLOOKUP(V14,$AM$3:$AP$65,2,FALSE),"") | X14: =IFERROR(VLOOKUP(V14,$AM$3:$AP$65,4,FALSE),"") | AM14: =IFERROR(_xlfn.RANK.EQ(AP14, $AP$3:$AP$150)+ COUNTIFS($AP$3:AP14, AP14) - 1,"") | AN14: =F34 | AO14: BILLS | AP14: =IFERROR(VLOOKUP(AN14,SEPT!$F$23:$H$38,3,FALSE),"")
B15: SAVINGS | C15: =SUM(SEPT!$V$23:$V$38) -> 0 | D15: =SUM(SEPT!$W$23:$W$38) -> 0 | V15: 8 | W15: =IFERROR(VLOOKUP(V15,$AM$3:$AP$65,2,FALSE),"") | X15: =IFERROR(VLOOKUP(V15,$AM$3:$AP$65,4,FALSE),"") | AM15: =IFERROR(_xlfn.RANK.EQ(AP15, $AP$3:$AP$150)+ COUNTIFS($AP$3:AP15, AP15) - 1,"") | AN15: =F35 | AO15: BILLS | AP15: =IFERROR(VLOOKUP(AN15,SEPT!$F$23:$H$38,3,FALSE),"")
B16: BALANCE | C16: =(C11-SUM(C12:C15)) -> 0 | D16: =(D11-SUM(D12:D15)) -> 0 | V16: 9 | W16: =IFERROR(VLOOKUP(V16,$AM$3:$AP$65,2,FALSE),"") | X16: =IFERROR(VLOOKUP(V16,$AM$3:$AP$65,4,FALSE),"") | AM16: =IFERROR(_xlfn.RANK.EQ(AP16, $AP$3:$AP$150)+ COUNTIFS($AP$3:AP16, AP16) - 1,"") | AN16: =F36 | AO16: BILLS | AP16: =IFERROR(VLOOKUP(AN16,SEPT!$F$23:$H$38,3,FALSE),"")
V17: 10 | W17: =IFERROR(VLOOKUP(V17,$AM$3:$AP$65,2,FALSE),"") | X17: =IFERROR(VLOOKUP(V17,$AM$3:$AP$65,4,FALSE),"") | AM17: =IFERROR(_xlfn.RANK.EQ(AP17, $AP$3:$AP$150)+ COUNTIFS($AP$3:AP17, AP17) - 1,"") | AN17: =F37 | AO17: BILLS | AP17: =IFERROR(VLOOKUP(AN17,SEPT!$F$23:$H$38,3,FALSE),"")
V18: 11 | W18: =IFERROR(VLOOKUP(V18,$AM$3:$AP$65,2,FALSE),"") | X18: =IFERROR(VLOOKUP(V18,$AM$3:$AP$65,4,FALSE),"") | AM18: =IFERROR(_xlfn.RANK.EQ(AP18, $AP$3:$AP$150)+ COUNTIFS($AP$3:AP18, AP18) - 1,"") | AN18: =F38 | AO18: BILLS | AP18: =IFERROR(VLOOKUP(AN18,SEPT!$F$23:$H$38,3,FALSE),"")
AM19: =IFERROR(_xlfn.RANK.EQ(AP19, $AP$3:$AP$150)+ COUNTIFS($AP$3:AP19, AP19) - 1,"") | AN19: =K23 | AO19: EXPENSES | AP19: =IFERROR(VLOOKUP(AN19,SEPT!$K$23:$M$38,3,FALSE),"")
B20: INCOME | F20: BILLS | K20: EXPENSES | P20: DEBT | U20: SAVINGS | AM20: =IFERROR(_xlfn.RANK.EQ(AP20, $AP$3:$AP$150)+ COUNTIFS($AP$3:AP20, AP20) - 1,"") | AN20: =K24 | AO20: EXPENSES | AP20: =IFERROR(VLOOKUP(AN20,SEPT!$K$23:$M$38,3,FALSE),"")
AM21: =IFERROR(_xlfn.RANK.EQ(AP21, $AP$3:$AP$150)+ COUNTIFS($AP$3:AP21, AP21) - 1,"") | AN21: =K25 | AO21: EXPENSES | AP21: =IFERROR(VLOOKUP(AN21,SEPT!$K$23:$M$38,3,FALSE),"")
B22: Details | C22: Planned | D22: Actual | F22: Details | G22: Planned | H22: Actual | I22: Variance | K22: Details | L22: Planned | M22: Actual | N22: Variance | P22: Details | Q22: Planned | R22: Actual | S22: Variance | U22: Details | V22: Planned | W22: Actual | X22: Variance | AM22: =IFERROR(_xlfn.RANK.EQ(AP22, $AP$3:$AP$150)+ COUNTIFS($AP$3:AP22, AP22) - 1,"") | AN22: =K26 | AO22: EXPENSES | AP22: =IFERROR(VLOOKUP(AN22,SEPT!$K$23:$M$38,3,FALSE),"")
I23: =SEPT!$G23-SEPT!$H23 -> 0 | N23: =SEPT!$L23-SEPT!$M23 -> 0 | S23: =SEPT!$Q23-SEPT!$R23 -> 0 | X23: =SEPT!$V23-SEPT!$W23 -> 0 | AM23: =IFERROR(_xlfn.RANK.EQ(AP23, $AP$3:$AP$150)+ COUNTIFS($AP$3:AP23, AP23) - 1,"") | AN23: =K27 | AO23: EXPENSES | AP23: =IFERROR(VLOOKUP(AN23,SEPT!$K$23:$M$38,3,FALSE),"")
I24: =SEPT!$G24-SEPT!$H24 -> 0 | N24: =SEPT!$L24-SEPT!$M24 -> 0 | S24: =SEPT!$Q24-SEPT!$R24 -> 0 | X24: =SEPT!$V24-SEPT!$W24 -> 0 | AM24: =IFERROR(_xlfn.RANK.EQ(AP24, $AP$3:$AP$150)+ COUNTIFS($AP$3:AP24, AP24) - 1,"") | AN24: =K28 | AO24: EXPENSES | AP24: =IFERROR(VLOOKUP(AN24,SEPT!$K$23:$M$38,3,FALSE),"")
I25: =SEPT!$G25-SEPT!$H25 -> 0 | N25: =SEPT!$L25-SEPT!$M25 -> 0 | S25: =SEPT!$Q25-SEPT!$R25 -> 0 | X25: =SEPT!$V25-SEPT!$W25 -> 0 | AM25: =IFERROR(_xlfn.RANK.EQ(AP25, $AP$3:$AP$150)+ COUNTIFS($AP$3:AP25, AP25) - 1,"") | AN25: =K29 | AO25: EXPENSES | AP25: =IFERROR(VLOOKUP(AN25,SEPT!$K$23:$M$38,3,FALSE),"")
I26: =SEPT!$G26-SEPT!$H26 -> 0 | N26: =SEPT!$L26-SEPT!$M26 -> 0 | S26: =SEPT!$Q26-SEPT!$R26 -> 0 | X26: =SEPT!$V26-SEPT!$W26 -> 0 | AM26: =IFERROR(_xlfn.RANK.EQ(AP26, $AP$3:$AP$150)+ COUNTIFS($AP$3:AP26, AP26) - 1,"") | AN26: =K30 | AO26: EXPENSES | AP26: =IFERROR(VLOOKUP(AN26,SEPT!$K$23:$M$38,3,FALSE),"")
I27: =SEPT!$G27-SEPT!$H27 -> 0 | N27: =SEPT!$L27-SEPT!$M27 -> 0 | S27: =SEPT!$Q27-SEPT!$R27 -> 0 | X27: =SEPT!$V27-SEPT!$W27 -> 0 | AM27: =IFERROR(_xlfn.RANK.EQ(AP27, $AP$3:$AP$150)+ COUNTIFS($AP$3:AP27, AP27) - 1,"") | AN27: =K31 | AO27: EXPENSES | AP27: =IFERROR(VLOOKUP(AN27,SEPT!$K$23:$M$38,3,FALSE),"")
I28: =SEPT!$G28-SEPT!$H28 -> 0 | N28: =SEPT!$L28-SEPT!$M28 -> 0 | S28: =SEPT!$Q28-SEPT!$R28 -> 0 | X28: =SEPT!$V28-SEPT!$W28 -> 0 | AM28: =IFERROR(_xlfn.RANK.EQ(AP28, $AP$3:$AP$150)+ COUNTIFS($AP$3:AP28, AP28) - 1,"") | AN28: =K32 | AO28: EXPENSES | AP28: =IFERROR(VLOOKUP(AN28,SEPT!$K$23:$M$38,3,FALSE),"")
I29: =SEPT!$G29-SEPT!$H29 -> 0 | N29: =SEPT!$L29-SEPT!$M29 -> 0 | S29: =SEPT!$Q29-SEPT!$R29 -> 0 | X29: =SEPT!$V29-SEPT!$W29 -> 0 | AM29: =IFERROR(_xlfn.RANK.EQ(AP29, $AP$3:$AP$150)+ COUNTIFS($AP$3:AP29, AP29) - 1,"") | AN29: =K33 | AO29: EXPENSES | AP29: =IFERROR(VLOOKUP(AN29,SEPT!$K$23:$M$38,3,FALSE),"")
I30: =SEPT!$G30-SEPT!$H30 -> 0 | N30: =SEPT!$L30-SEPT!$M30 -> 0 | S30: =SEPT!$Q30-SEPT!$R30 -> 0 | X30: =SEPT!$V30-SEPT!$W30 -> 0 | AM30: =IFERROR(_xlfn.RANK.EQ(AP30, $AP$3:$AP$150)+ COUNTIFS($AP$3:AP30, AP30) - 1,"") | AN30: =K34 | AO30: EXPENSES | AP30: =IFERROR(VLOOKUP(AN30,SEPT!$K$23:$M$38,3,FALSE),"")
I31: =SEPT!$G31-SEPT!$H31 -> 0 | N31: =SEPT!$L31-SEPT!$M31 -> 0 | S31: =SEPT!$Q31-SEPT!$R31 -> 0 | X31: =SEPT!$V31-SEPT!$W31 -> 0 | AM31: =IFERROR(_xlfn.RANK.EQ(AP31, $AP$3:$AP$150)+ COUNTIFS($AP$3:AP31, AP31) - 1,"") | AN31: =K35 | AO31: EXPENSES | AP31: =IFERROR(VLOOKUP(AN31,SEPT!$K$23:$M$38,3,FALSE),"")
I32: =SEPT!$G32-SEPT!$H32 -> 0 | N32: =SEPT!$L32-SEPT!$M32 -> 0 | S32: =SEPT!$Q32-SEPT!$R32 -> 0 | X32: =SEPT!$V32-SEPT!$W32 -> 0 | AM32: =IFERROR(_xlfn.RANK.EQ(AP32, $AP$3:$AP$150)+ COUNTIFS($AP$3:AP32, AP32) - 1,"") | AN32: =K36 | AO32: EXPENSES | AP32: =IFERROR(VLOOKUP(AN32,SEPT!$K$23:$M$38,3,FALSE),"")
I33: =SEPT!$G33-SEPT!$H33 -> 0 | N33: =SEPT!$L33-SEPT!$M33 -> 0 | S33: =SEPT!$Q33-SEPT!$R33 -> 0 | X33: =SEPT!$V33-SEPT!$W33 -> 0 | AM33: =IFERROR(_xlfn.RANK.EQ(AP33, $AP$3:$AP$150)+ COUNTIFS($AP$3:AP33, AP33) - 1,"") | AN33: =K37 | AO33: EXPENSES | AP33: =IFERROR(VLOOKUP(AN33,SEPT!$K$23:$M$38,3,FALSE),"")
I34: =SEPT!$G34-SEPT!$H34 -> 0 | N34: =SEPT!$L34-SEPT!$M34 -> 0 | S34: =SEPT!$Q34-SEPT!$R34 -> 0 | X34: =SEPT!$V34-SEPT!$W34 -> 0 | AM34: =IFERROR(_xlfn.RANK.EQ(AP34, $AP$3:$AP$150)+ COUNTIFS($AP$3:AP34, AP34) - 1,"") | AN34: =K38 | AO34: DEBTS | AP34: =IFERROR(VLOOKUP(AN34,SEPT!$K$23:$M$38,3,FALSE),"")
I35: =SEPT!$G35-SEPT!$H35 -> 0 | N35: =SEPT!$L35-SEPT!$M35 -> 0 | S35: =SEPT!$Q35-SEPT!$R35 -> 0 | X35: =SEPT!$V35-SEPT!$W35 -> 0 | AM35: =IFERROR(_xlfn.RANK.EQ(AP35, $AP$3:$AP$150)+ COUNTIFS($AP$3:AP35, AP35) - 1,"") | AN35: =P23 | AO35: DEBTS | AP35: =IFERROR(VLOOKUP(AN35,SEPT!$P$23:$R$38,3,FALSE),"")
I36: =SEPT!$G36-SEPT!$H36 -> 0 | N36: =SEPT!$L36-SEPT!$M36 -> 0 | S36: =SEPT!$Q36-SEPT!$R36 -> 0 | X36: =SEPT!$V36-SEPT!$W36 -> 0 | AM36: =IFERROR(_xlfn.RANK.EQ(AP36, $AP$3:$AP$150)+ COUNTIFS($AP$3:AP36, AP36) - 1,"") | AN36: =P24 | AO36: DEBTS | AP36: =IFERROR(VLOOKUP(AN36,SEPT!$P$23:$R$38,3,FALSE),"")
I37: =SEPT!$G37-SEPT!$H37 -> 0 | N37: =SEPT!$L37-SEPT!$M37 -> 0 | S37: =SEPT!$Q37-SEPT!$R37 -> 0 | X37: =SEPT!$V37-SEPT!$W37 -> 0 | AM37: =IFERROR(_xlfn.RANK.EQ(AP37, $AP$3:$AP$150)+ COUNTIFS($AP$3:AP37, AP37) - 1,"") | AN37: =P25 | AO37: DEBTS | AP37: =IFERROR(VLOOKUP(AN37,SEPT!$P$23:$R$38,3,FALSE),"")
I38: =SEPT!$G38-SEPT!$H38 -> 0 | N38: =SEPT!$L38-SEPT!$M38 -> 0 | S38: =SEPT!$Q38-SEPT!$R38 -> 0 | X38: =SEPT!$V38-SEPT!$W38 -> 0 | AM38: =IFERROR(_xlfn.RANK.EQ(AP38, $AP$3:$AP$150)+ COUNTIFS($AP$3:AP38, AP38) - 1,"") | AN38: =P26 | AO38: DEBTS | AP38: =IFERROR(VLOOKUP(AN38,SEPT!$P$23:$R$38,3,FALSE),"")
AM39: =IFERROR(_xlfn.RANK.EQ(AP39, $AP$3:$AP$150)+ COUNTIFS($AP$3:AP39, AP39) - 1,"") | AN39: =P27 | AO39: DEBTS | AP39: =IFERROR(VLOOKUP(AN39,SEPT!$P$23:$R$38,3,FALSE),"")
AM40: =IFERROR(_xlfn.RANK.EQ(AP40, $AP$3:$AP$150)+ COUNTIFS($AP$3:AP40, AP40) - 1,"") | AN40: =P28 | AO40: DEBTS | AP40: =IFERROR(VLOOKUP(AN40,SEPT!$P$23:$R$38,3,FALSE),"")
AM41: =IFERROR(_xlfn.RANK.EQ(AP41, $AP$3:$AP$150)+ COUNTIFS($AP$3:AP41, AP41) - 1,"") | AN41: =P29 | AO41: DEBTS | AP41: =IFERROR(VLOOKUP(AN41,SEPT!$P$23:$R$38,3,FALSE),"")
AM42: =IFERROR(_xlfn.RANK.EQ(AP42, $AP$3:$AP$150)+ COUNTIFS($AP$3:AP42, AP42) - 1,"") | AN42: =P30 | AO42: DEBTS | AP42: =IFERROR(VLOOKUP(AN42,SEPT!$P$23:$R$38,3,FALSE),"")
AM43: =IFERROR(_xlfn.RANK.EQ(AP43, $AP$3:$AP$150)+ COUNTIFS($AP$3:AP43, AP43) - 1,"") | AN43: =P31 | AO43: DEBTS | AP43: =IFERROR(VLOOKUP(AN43,SEPT!$P$23:$R$38,3,FALSE),"")
AM44: =IFERROR(_xlfn.RANK.EQ(AP44, $AP$3:$AP$150)+ COUNTIFS($AP$3:AP44, AP44) - 1,"") | AN44: =P32 | AO44: DEBTS | AP44: =IFERROR(VLOOKUP(AN44,SEPT!$P$23:$R$38,3,FALSE),"")
AM45: =IFERROR(_xlfn.RANK.EQ(AP45, $AP$3:$AP$150)+ COUNTIFS($AP$3:AP45, AP45) - 1,"") | AN45: =P33 | AO45: DEBTS | AP45: =IFERROR(VLOOKUP(AN45,SEPT!$P$23:$R$38,3,FALSE),"")
AM46: =IFERROR(_xlfn.RANK.EQ(AP46, $AP$3:$AP$150)+ COUNTIFS($AP$3:AP46, AP46) - 1,"") | AN46: =P34 | AO46: DEBTS | AP46: =IFERROR(VLOOKUP(AN46,SEPT!$P$23:$R$38,3,FALSE),"")
AM47: =IFERROR(_xlfn.RANK.EQ(AP47, $AP$3:$AP$150)+ COUNTIFS($AP$3:AP47, AP47) - 1,"") | AN47: =P35 | AO47: DEBTS | AP47: =IFERROR(VLOOKUP(AN47,SEPT!$P$23:$R$38,3,FALSE),"")
AM48: =IFERROR(_xlfn.RANK.EQ(AP48, $AP$3:$AP$150)+ COUNTIFS($AP$3:AP48, AP48) - 1,"") | AN48: =P36 | AO48: DEBTS | AP48: =IFERROR(VLOOKUP(AN48,SEPT!$P$23:$R$38,3,FALSE),"")
AM49: =IFERROR(_xlfn.RANK.EQ(AP49, $AP$3:$AP$150)+ COUNTIFS($AP$3:AP49, AP49) - 1,"") | AN49: =P37 | AO49: SAVINGS | AP49: =IFERROR(VLOOKUP(AN49,SEPT!$P$23:$R$38,3,FALSE),"")
AM50: =IFERROR(_xlfn.RANK.EQ(AP50, $AP$3:$AP$150)+ COUNTIFS($AP$3:AP50, AP50) - 1,"") | AN50: =U23 | AO50: SAVINGS | AP50: =IFERROR(VLOOKUP(AN50,SEPT!$U$23:$W$38,3,FALSE),"")
AM51: =IFERROR(_xlfn.RANK.EQ(AP51, $AP$3:$AP$150)+ COUNTIFS($AP$3:AP51, AP51) - 1,"") | AN51: =U24 | AO51: SAVINGS | AP51: =IFERROR(VLOOKUP(AN51,SEPT!$U$23:$W$38,3,FALSE),"")
AM52: =IFERROR(_xlfn.RANK.EQ(AP52, $AP$3:$AP$150)+ COUNTIFS($AP$3:AP52, AP52) - 1,"") | AN52: =U25 | AO52: SAVINGS | AP52: =IFERROR(VLOOKUP(AN52,SEPT!$U$23:$W$38,3,FALSE),"")
AM53: =IFERROR(_xlfn.RANK.EQ(AP53, $AP$3:$AP$150)+ COUNTIFS($AP$3:AP53, AP53) - 1,"") | AN53: =U26 | AO53: SAVINGS | AP53: =IFERROR(VLOOKUP(AN53,SEPT!$U$23:$W$38,3,FALSE),"")
AM54: =IFERROR(_xlfn.RANK.EQ(AP54, $AP$3:$AP$150)+ COUNTIFS($AP$3:AP54, AP54) - 1,"") | AN54: =U27 | AO54: SAVINGS | AP54: =IFERROR(VLOOKUP(AN54,SEPT!$U$23:$W$38,3,FALSE),"")
AM55: =IFERROR(_xlfn.RANK.EQ(AP55, $AP$3:$AP$150)+ COUNTIFS($AP$3:AP55, AP55) - 1,"") | AN55: =U28 | AO55: SAVINGS | AP55: =IFERROR(VLOOKUP(AN55,SEPT!$U$23:$W$38,3,FALSE),"")
AM56: =IFERROR(_xlfn.RANK.EQ(AP56, $AP$3:$AP$150)+ COUNTIFS($AP$3:AP56, AP56) - 1,"") | AN56: =U29 | AO56: SAVINGS | AP56: =IFERROR(VLOOKUP(AN56,SEPT!$U$23:$W$38,3,FALSE),"")
AM57: =IFERROR(_xlfn.RANK.EQ(AP57, $AP$3:$AP$150)+ COUNTIFS($AP$3:AP57, AP57) - 1,"") | AN57: =U30 | AO57: SAVINGS | AP57: =IFERROR(VLOOKUP(AN57,SEPT!$U$23:$W$38,3,FALSE),"")
AM58: =IFERROR(_xlfn.RANK.EQ(AP58, $AP$3:$AP$150)+ COUNTIFS($AP$3:AP58, AP58) - 1,"") | AN58: =U31 | AO58: SAVINGS | AP58: =IFERROR(VLOOKUP(AN58,SEPT!$U$23:$W$38,3,FALSE),"")
AM59: =IFERROR(_xlfn.RANK.EQ(AP59, $AP$3:$AP$150)+ COUNTIFS($AP$3:AP59, AP59) - 1,"") | AN59: =U32 | AO59: SAVINGS | AP59: =IFERROR(VLOOKUP(AN59,SEPT!$U$23:$W$38,3,FALSE),"")
AM60: =IFERROR(_xlfn.RANK.EQ(AP60, $AP$3:$AP$150)+ COUNTIFS($AP$3:AP60, AP60) - 1,"") | AN60: =U33 | AO60: SAVINGS | AP60: =IFERROR(VLOOKUP(AN60,SEPT!$U$23:$W$38,3,FALSE),"")
AM61: =IFERROR(_xlfn.RANK.EQ(AP61, $AP$3:$AP$150)+ COUNTIFS($AP$3:AP61, AP61) - 1,"") | AN61: =U34 | AO61: SAVINGS | AP61: =IFERROR(VLOOKUP(AN61,SEPT!$U$23:$W$38,3,FALSE),"")
... AM65: =IFERROR(_xlfn.RANK.EQ(AP65, $AP$3:$AP$150)+ COUNTIFS($AP$3:AP65, AP65) - 1,"") | AN65: =U38 | AO65: SAVINGS | AP65: =IFERROR(VLOOKUP(AN65,SEPT!$U$23:$W$38,3,FALSE),"")

Sheet OCT
B2: OCTOBER | F2: INCOME | J2: BILLS | N2: EXPENSES | R2: DEBT | V2: SAVINGS | AM2: Ranking | AN2: ITEM | AO2: CATEGORY | AP2: TOTAL SPENT
AM3: =IFERROR(_xlfn.RANK.EQ(AP3, $AP$3:$AP$150)+ COUNTIFS($AP$3:AP3, AP3) - 1,"") | AN3: =F23 | AO3: BILLS | AP3: =IFERROR(VLOOKUP(AN3,OCT!$F$23:$H$38,3,FALSE),"")
F4: =SUM(OCT!$D$23:$D$38) -> 0 | J4: =SUM(OCT!$H$23:$H$38) -> 0 | N4: =SUM(OCT!$M$23:$M$38) -> 0 | R4: =SUM(OCT!$R$23:$R$38) -> 0 | V4: =SUM(OCT!$W$23:$W$38) -> 0 | AM4: =IFERROR(_xlfn.RANK.EQ(AP4, $AP$3:$AP$150)+ COUNTIFS($AP$3:AP4, AP4) - 1,"") | AN4: =F24 | AO4: BILLS | AP4: =IFERROR(VLOOKUP(AN4,OCT!$F$23:$H$38,3,FALSE),"")
B5: SUMMARY | AM5: =IFERROR(_xlfn.RANK.EQ(AP5, $AP$3:$AP$150)+ COUNTIFS($AP$3:AP5, AP5) - 1,"") | AN5: =F25 | AO5: BILLS | AP5: =IFERROR(VLOOKUP(AN5,OCT!$F$23:$H$38,3,FALSE),"")
AM6: =IFERROR(_xlfn.RANK.EQ(AP6, $AP$3:$AP$150)+ COUNTIFS($AP$3:AP6, AP6) - 1,"") | AN6: =F26 | AO6: BILLS | AP6: =IFERROR(VLOOKUP(AN6,OCT!$F$23:$H$38,3,FALSE),"")
B7: INCOME OVERVIEW | V7: RANK | W7: ITEM | X7: AMOUNT | AM7: =IFERROR(_xlfn.RANK.EQ(AP7, $AP$3:$AP$150)+ COUNTIFS($AP$3:AP7, AP7) - 1,"") | AN7: =F27 | AO7: BILLS | AP7: =IFERROR(VLOOKUP(AN7,OCT!$F$23:$H$38,3,FALSE),"")
V8: 1 | W8: =IFERROR(VLOOKUP(V8,$AM$3:$AP$65,2,FALSE),"") | X8: =IFERROR(VLOOKUP(V8,$AM$3:$AP$65,4,FALSE),"") | AM8: =IFERROR(_xlfn.RANK.EQ(AP8, $AP$3:$AP$150)+ COUNTIFS($AP$3:AP8, AP8) - 1,"") | AN8: =F28 | AO8: BILLS | AP8: =IFERROR(VLOOKUP(AN8,OCT!$F$23:$H$38,3,FALSE),"")
V9: 2 | W9: =IFERROR(VLOOKUP(V9,$AM$3:$AP$65,2,FALSE),"") | X9: =IFERROR(VLOOKUP(V9,$AM$3:$AP$65,4,FALSE),"") | AM9: =IFERROR(_xlfn.RANK.EQ(AP9, $AP$3:$AP$150)+ COUNTIFS($AP$3:AP9, AP9) - 1,"") | AN9: =F29 | AO9: BILLS | AP9: =IFERROR(VLOOKUP(AN9,OCT!$F$23:$H$38,3,FALSE),"")
C10: Planned | D10: Actual | V10: 3 | W10: =IFERROR(VLOOKUP(V10,$AM$3:$AP$65,2,FALSE),"") | X10: =IFERROR(VLOOKUP(V10,$AM$3:$AP$65,4,FALSE),"") | AM10: =IFERROR(_xlfn.RANK.EQ(AP10, $AP$3:$AP$150)+ COUNTIFS($AP$3:AP10, AP10) - 1,"") | AN10: =F30 | AO10: BILLS | AP10: =IFERROR(VLOOKUP(AN10,OCT!$F$23:$H$38,3,FALSE),"")
B11: INCOME | C11: =SUM(OCT!$C$23:$C$38) -> 0 | D11: =SUM(OCT!$D$23:$D$38) -> 0 | V11: 4 | W11: =IFERROR(VLOOKUP(V11,$AM$3:$AP$65,2,FALSE),"") | X11: =IFERROR(VLOOKUP(V11,$AM$3:$AP$65,4,FALSE),"") | AM11: =IFERROR(_xlfn.RANK.EQ(AP11, $AP$3:$AP$150)+ COUNTIFS($AP$3:AP11, AP11) - 1,"") | AN11: =F31 | AO11: BILLS | AP11: =IFERROR(VLOOKUP(AN11,OCT!$F$23:$H$38,3,FALSE),"")
B12: BILLS | C12: =SUM(OCT!$G$23:$G$38) -> 0 | D12: =SUM(OCT!$H$23:$H$38) -> 0 | V12: 5 | W12: =IFERROR(VLOOKUP(V12,$AM$3:$AP$65,2,FALSE),"") | X12: =IFERROR(VLOOKUP(V12,$AM$3:$AP$65,4,FALSE),"") | AM12: =IFERROR(_xlfn.RANK.EQ(AP12, $AP$3:$AP$150)+ COUNTIFS($AP$3:AP12, AP12) - 1,"") | AN12: =F32 | AO12: BILLS | AP12: =IFERROR(VLOOKUP(AN12,OCT!$F$23:$H$38,3,FALSE),"")
B13: EXPENSES | C13: =SUM(OCT!$L$23:$L$38) -> 0 | D13: =SUM(OCT!$M$23:$M$38) -> 0 | V13: 6 | W13: =IFERROR(VLOOKUP(V13,$AM$3:$AP$65,2,FALSE),"") | X13: =IFERROR(VLOOKUP(V13,$AM$3:$AP$65,4,FALSE),"") | AM13: =IFERROR(_xlfn.RANK.EQ(AP13, $AP$3:$AP$150)+ COUNTIFS($AP$3:AP13, AP13) - 1,"") | AN13: =F33 | AO13: BILLS | AP13: =IFERROR(VLOOKUP(AN13,OCT!$F$23:$H$38,3,FALSE),"")
B14: DEBT | C14: =SUM(OCT!$Q$23:$Q$38) -> 0 | D14: =SUM(OCT!$R$23:$R$38) -> 0 | V14: 7 | W14: =IFERROR(VLOOKUP(V14,$AM$3:$AP$65,2,FALSE),"") | X14: =IFERROR(VLOOKUP(V14,$AM$3:$AP$65,4,FALSE),"") | AM14: =IFERROR(_xlfn.RANK.EQ(AP14, $AP$3:$AP$150)+ COUNTIFS($AP$3:AP14, AP14) - 1,"") | AN14: =F34 | AO14: BILLS | AP14: =IFERROR(VLOOKUP(AN14,OCT!$F$23:$H$38,3,FALSE),"")
B15: SAVINGS | C15: =SUM(OCT!$V$23:$V$38) -> 0 | D15: =SUM(OCT!$W$23:$W$38) -> 0 | V15: 8 | W15: =IFERROR(VLOOKUP(V15,$AM$3:$AP$65,2,FALSE),"") | X15: =IFERROR(VLOOKUP(V15,$AM$3:$AP$65,4,FALSE),"") | AM15: =IFERROR(_xlfn.RANK.EQ(AP15, $AP$3:$AP$150)+ COUNTIFS($AP$3:AP15, AP15) - 1,"") | AN15: =F35 | AO15: BILLS | AP15: =IFERROR(VLOOKUP(AN15,OCT!$F$23:$H$38,3,FALSE),"")
B16: BALANCE | C16: =(C11-SUM(C12:C15)) -> 0 | D16: =(D11-SUM(D12:D15)) -> 0 | V16: 9 | W16: =IFERROR(VLOOKUP(V16,$AM$3:$AP$65,2,FALSE),"") | X16: =IFERROR(VLOOKUP(V16,$AM$3:$AP$65,4,FALSE),"") | AM16: =IFERROR(_xlfn.RANK.EQ(AP16, $AP$3:$AP$150)+ COUNTIFS($AP$3:AP16, AP16) - 1,"") | AN16: =F36 | AO16: BILLS | AP16: =IFERROR(VLOOKUP(AN16,OCT!$F$23:$H$38,3,FALSE),"")
V17: 10 | W17: =IFERROR(VLOOKUP(V17,$AM$3:$AP$65,2,FALSE),"") | X17: =IFERROR(VLOOKUP(V17,$AM$3:$AP$65,4,FALSE),"") | AM17: =IFERROR(_xlfn.RANK.EQ(AP17, $AP$3:$AP$150)+ COUNTIFS($AP$3:AP17, AP17) - 1,"") | AN17: =F37 | AO17: BILLS | AP17: =IFERROR(VLOOKUP(AN17,OCT!$F$23:$H$38,3,FALSE),"")
V18: 11 | W18: =IFERROR(VLOOKUP(V18,$AM$3:$AP$65,2,FALSE),"") | X18: =IFERROR(VLOOKUP(V18,$AM$3:$AP$65,4,FALSE),"") | AM18: =IFERROR(_xlfn.RANK.EQ(AP18, $AP$3:$AP$150)+ COUNTIFS($AP$3:AP18, AP18) - 1,"") | AN18: =F38 | AO18: BILLS | AP18: =IFERROR(VLOOKUP(AN18,OCT!$F$23:$H$38,3,FALSE),"")
AM19: =IFERROR(_xlfn.RANK.EQ(AP19, $AP$3:$AP$150)+ COUNTIFS($AP$3:AP19, AP19) - 1,"") | AN19: =K23 | AO19: EXPENSES | AP19: =IFERROR(VLOOKUP(AN19,OCT!$K$23:$M$38,3,FALSE),"")
B20: INCOME | F20: BILLS | K20: EXPENSES | P20: DEBT | U20: SAVINGS | AM20: =IFERROR(_xlfn.RANK.EQ(AP20, $AP$3:$AP$150)+ COUNTIFS($AP$3:AP20, AP20) - 1,"") | AN20: =K24 | AO20: EXPENSES | AP20: =IFERROR(VLOOKUP(AN20,OCT!$K$23:$M$38,3,FALSE),"")
AM21: =IFERROR(_xlfn.RANK.EQ(AP21, $AP$3:$AP$150)+ COUNTIFS($AP$3:AP21, AP21) - 1,"") | AN21: =K25 | AO21: EXPENSES | AP21: =IFERROR(VLOOKUP(AN21,OCT!$K$23:$M$38,3,FALSE),"")
B22: Details | C22: Planned | D22: Actual | F22: Details | G22: Planned | H22: Actual | I22: Variance | K22: Details | L22: Planned | M22: Actual | N22: Variance | P22: Details | Q22: Planned | R22: Actual | S22: Variance | U22: Details | V22: Planned | W22: Actual | X22: Variance | AM22: =IFERROR(_xlfn.RANK.EQ(AP22, $AP$3:$AP$150)+ COUNTIFS($AP$3:AP22, AP22) - 1,"") | AN22: =K26 | AO22: EXPENSES | AP22: =IFERROR(VLOOKUP(AN22,OCT!$K$23:$M$38,3,FALSE),"")
I23: =OCT!$G23-OCT!$H23 -> 0 | N23: =OCT!$L23-OCT!$M23 -> 0 | S23: =OCT!$Q23-OCT!$R23 -> 0 | X23: =OCT!$V23-OCT!$W23 -> 0 | AM23: =IFERROR(_xlfn.RANK.EQ(AP23, $AP$3:$AP$150)+ COUNTIFS($AP$3:AP23, AP23) - 1,"") | AN23: =K27 | AO23: EXPENSES | AP23: =IFERROR(VLOOKUP(AN23,OCT!$K$23:$M$38,3,FALSE),"")
I24: =OCT!$G24-OCT!$H24 -> 0 | N24: =OCT!$L24-OCT!$M24 -> 0 | S24: =OCT!$Q24-OCT!$R24 -> 0 | X24: =OCT!$V24-OCT!$W24 -> 0 | AM24: =IFERROR(_xlfn.RANK.EQ(AP24, $AP$3:$AP$150)+ COUNTIFS($AP$3:AP24, AP24) - 1,"") | AN24: =K28 | AO24: EXPENSES | AP24: =IFERROR(VLOOKUP(AN24,OCT!$K$23:$M$38,3,FALSE),"")
I25: =OCT!$G25-OCT!$H25 -> 0 | N25: =OCT!$L25-OCT!$M25 -> 0 | S25: =OCT!$Q25-OCT!$R25 -> 0 | X25: =OCT!$V25-OCT!$W25 -> 0 | AM25: =IFERROR(_xlfn.RANK.EQ(AP25, $AP$3:$AP$150)+ COUNTIFS($AP$3:AP25, AP25) - 1,"") | AN25: =K29 | AO25: EXPENSES | AP25: =IFERROR(VLOOKUP(AN25,OCT!$K$23:$M$38,3,FALSE),"")
I26: =OCT!$G26-OCT!$H26 -> 0 | N26: =OCT!$L26-OCT!$M26 -> 0 | S26: =OCT!$Q26-OCT!$R26 -> 0 | X26: =OCT!$V26-OCT!$W26 -> 0 | AM26: =IFERROR(_xlfn.RANK.EQ(AP26, $AP$3:$AP$150)+ COUNTIFS($AP$3:AP26, AP26) - 1,"") | AN26: =K30 | AO26: EXPENSES | AP26: =IFERROR(VLOOKUP(AN26,OCT!$K$23:$M$38,3,FALSE),"")
I27: =OCT!$G27-OCT!$H27 -> 0 | N27: =OCT!$L27-OCT!$M27 -> 0 | S27: =OCT!$Q27-OCT!$R27 -> 0 | X27: =OCT!$V27-OCT!$W27 -> 0 | AM27: =IFERROR(_xlfn.RANK.EQ(AP27, $AP$3:$AP$150)+ COUNTIFS($AP$3:AP27, AP27) - 1,"") | AN27: =K31 | AO27: EXPENSES | AP27: =IFERROR(VLOOKUP(AN27,OCT!$K$23:$M$38,3,FALSE),"")
I28: =OCT!$G28-OCT!$H28 -> 0 | N28: =OCT!$L28-OCT!$M28 -> 0 | S28: =OCT!$Q28-OCT!$R28 -> 0 | X28: =OCT!$V28-OCT!$W28 -> 0 | AM28: =IFERROR(_xlfn.RANK.EQ(AP28, $AP$3:$AP$150)+ COUNTIFS($AP$3:AP28, AP28) - 1,"") | AN28: =K32 | AO28: EXPENSES | AP28: =IFERROR(VLOOKUP(AN28,OCT!$K$23:$M$38,3,FALSE),"")
I29: =OCT!$G29-OCT!$H29 -> 0 | N29: =OCT!$L29-OCT!$M29 -> 0 | S29: =OCT!$Q29-OCT!$R29 -> 0 | X29: =OCT!$V29-OCT!$W29 -> 0 | AM29: =IFERROR(_xlfn.RANK.EQ(AP29, $AP$3:$AP$150)+ COUNTIFS($AP$3:AP29, AP29) - 1,"") | AN29: =K33 | AO29: EXPENSES | AP29: =IFERROR(VLOOKUP(AN29,OCT!$K$23:$M$38,3,FALSE),"")
I30: =OCT!$G30-OCT!$H30 -> 0 | N30: =OCT!$L30-OCT!$M30 -> 0 | S30: =OCT!$Q30-OCT!$R30 -> 0 | X30: =OCT!$V30-OCT!$W30 -> 0 | AM30: =IFERROR(_xlfn.RANK.EQ(AP30, $AP$3:$AP$150)+ COUNTIFS($AP$3:AP30, AP30) - 1,"") | AN30: =K34 | AO30: EXPENSES | AP30: =IFERROR(VLOOKUP(AN30,OCT!$K$23:$M$38,3,FALSE),"")
I31: =OCT!$G31-OCT!$H31 -> 0 | N31: =OCT!$L31-OCT!$M31 -> 0 | S31: =OCT!$Q31-OCT!$R31 -> 0 | X31: =OCT!$V31-OCT!$W31 -> 0 | AM31: =IFERROR(_xlfn.RANK.EQ(AP31, $AP$3:$AP$150)+ COUNTIFS($AP$3:AP31, AP31) - 1,"") | AN31: =K35 | AO31: EXPENSES | AP31: =IFERROR(VLOOKUP(AN31,OCT!$K$23:$M$38,3,FALSE),"")
I32: =OCT!$G32-OCT!$H32 -> 0 | N32: =OCT!$L32-OCT!$M32 -> 0 | S32: =OCT!$Q32-OCT!$R32 -> 0 | X32: =OCT!$V32-OCT!$W32 -> 0 | AM32: =IFERROR(_xlfn.RANK.EQ(AP32, $AP$3:$AP$150)+ COUNTIFS($AP$3:AP32, AP32) - 1,"") | AN32: =K36 | AO32: EXPENSES | AP32: =IFERROR(VLOOKUP(AN32,OCT!$K$23:$M$38,3,FALSE),"")
I33: =OCT!$G33-OCT!$H33 -> 0 | N33: =OCT!$L33-OCT!$M33 -> 0 | S33: =OCT!$Q33-OCT!$R33 -> 0 | X33: =OCT!$V33-OCT!$W33 -> 0 | AM33: =IFERROR(_xlfn.RANK.EQ(AP33, $AP$3:$AP$150)+ COUNTIFS($AP$3:AP33, AP33) - 1,"") | AN33: =K37 | AO33: EXPENSES | AP33: =IFERROR(VLOOKUP(AN33,OCT!$K$23:$M$38,3,FALSE),"")
I34: =OCT!$G34-OCT!$H34 -> 0 | N34: =OCT!$L34-OCT!$M34 -> 0 | S34: =OCT!$Q34-OCT!$R34 -> 0 | X34: =OCT!$V34-OCT!$W34 -> 0 | AM34: =IFERROR(_xlfn.RANK.EQ(AP34, $AP$3:$AP$150)+ COUNTIFS($AP$3:AP34, AP34) - 1,"") | AN34: =K38 | AO34: DEBTS | AP34: =IFERROR(VLOOKUP(AN34,OCT!$K$23:$M$38,3,FALSE),"")
I35: =OCT!$G35-OCT!$H35 -> 0 | N35: =OCT!$L35-OCT!$M35 -> 0 | S35: =OCT!$Q35-OCT!$R35 -> 0 | X35: =OCT!$V35-OCT!$W35 -> 0 | AM35: =IFERROR(_xlfn.RANK.EQ(AP35, $AP$3:$AP$150)+ COUNTIFS($AP$3:AP35, AP35) - 1,"") | AN35: =P23 | AO35: DEBTS | AP35: =IFERROR(VLOOKUP(AN35,OCT!$P$23:$R$38,3,FALSE),"")
I36: =OCT!$G36-OCT!$H36 -> 0 | N36: =OCT!$L36-OCT!$M36 -> 0 | S36: =OCT!$Q36-OCT!$R36 -> 0 | X36: =OCT!$V36-OCT!$W36 -> 0 | AM36: =IFERROR(_xlfn.RANK.EQ(AP36, $AP$3:$AP$150)+ COUNTIFS($AP$3:AP36, AP36) - 1,"") | AN36: =P24 | AO36: DEBTS | AP36: =IFERROR(VLOOKUP(AN36,OCT!$P$23:$R$38,3,FALSE),"")
I37: =OCT!$G37-OCT!$H37 -> 0 | N37: =OCT!$L37-OCT!$M37 -> 0 | S37: =OCT!$Q37-OCT!$R37 -> 0 | X37: =OCT!$V37-OCT!$W37 -> 0 | AM37: =IFERROR(_xlfn.RANK.EQ(AP37, $AP$3:$AP$150)+ COUNTIFS($AP$3:AP37, AP37) - 1,"") | AN37: =P25 | AO37: DEBTS | AP37: =IFERROR(VLOOKUP(AN37,OCT!$P$23:$R$38,3,FALSE),"")
I38: =OCT!$G38-OCT!$H38 -> 0 | N38: =OCT!$L38-OCT!$M38 -> 0 | S38: =OCT!$Q38-OCT!$R38 -> 0 | X38: =OCT!$V38-OCT!$W38 -> 0 | AM38: =IFERROR(_xlfn.RANK.EQ(AP38, $AP$3:$AP$150)+ COUNTIFS($AP$3:AP38, AP38) - 1,"") | AN38: =P26 | AO38: DEBTS | AP38: =IFERROR(VLOOKUP(AN38,OCT!$P$23:$R$38,3,FALSE),"")
AM39: =IFERROR(_xlfn.RANK.EQ(AP39, $AP$3:$AP$150)+ COUNTIFS($AP$3:AP39, AP39) - 1,"") | AN39: =P27 | AO39: DEBTS | AP39: =IFERROR(VLOOKUP(AN39,OCT!$P$23:$R$38,3,FALSE),"")
AM40: =IFERROR(_xlfn.RANK.EQ(AP40, $AP$3:$AP$150)+ COUNTIFS($AP$3:AP40, AP40) - 1,"") | AN40: =P28 | AO40: DEBTS | AP40: =IFERROR(VLOOKUP(AN40,OCT!$P$23:$R$38,3,FALSE),"")
AM41: =IFERROR(_xlfn.RANK.EQ(AP41, $AP$3:$AP$150)+ COUNTIFS($AP$3:AP41, AP41) - 1,"") | AN41: =P29 | AO41: DEBTS | AP41: =IFERROR(VLOOKUP(AN41,OCT!$P$23:$R$38,3,FALSE),"")
AM42: =IFERROR(_xlfn.RANK.EQ(AP42, $AP$3:$AP$150)+ COUNTIFS($AP$3:AP42, AP42) - 1,"") | AN42: =P30 | AO42: DEBTS | AP42: =IFERROR(VLOOKUP(AN42,OCT!$P$23:$R$38,3,FALSE),"")
AM43: =IFERROR(_xlfn.RANK.EQ(AP43, $AP$3:$AP$150)+ COUNTIFS($AP$3:AP43, AP43) - 1,"") | AN43: =P31 | AO43: DEBTS | AP43: =IFERROR(VLOOKUP(AN43,OCT!$P$23:$R$38,3,FALSE),"")
AM44: =IFERROR(_xlfn.RANK.EQ(AP44, $AP$3:$AP$150)+ COUNTIFS($AP$3:AP44, AP44) - 1,"") | AN44: =P32 | AO44: DEBTS | AP44: =IFERROR(VLOOKUP(AN44,OCT!$P$23:$R$38,3,FALSE),"")
AM45: =IFERROR(_xlfn.RANK.EQ(AP45, $AP$3:$AP$150)+ COUNTIFS($AP$3:AP45, AP45) - 1,"") | AN45: =P33 | AO45: DEBTS | AP45: =IFERROR(VLOOKUP(AN45,OCT!$P$23:$R$38,3,FALSE),"")
AM46: =IFERROR(_xlfn.RANK.EQ(AP46, $AP$3:$AP$150)+ COUNTIFS($AP$3:AP46, AP46) - 1,"") | AN46: =P34 | AO46: DEBTS | AP46: =IFERROR(VLOOKUP(AN46,OCT!$P$23:$R$38,3,FALSE),"")
AM47: =IFERROR(_xlfn.RANK.EQ(AP47, $AP$3:$AP$150)+ COUNTIFS($AP$3:AP47, AP47) - 1,"") | AN47: =P35 | AO47: DEBTS | AP47: =IFERROR(VLOOKUP(AN47,OCT!$P$23:$R$38,3,FALSE),"")
AM48: =IFERROR(_xlfn.RANK.EQ(AP48, $AP$3:$AP$150)+ COUNTIFS($AP$3:AP48, AP48) - 1,"") | AN48: =P36 | AO48: DEBTS | AP48: =IFERROR(VLOOKUP(AN48,OCT!$P$23:$R$38,3,FALSE),"")
AM49: =IFERROR(_xlfn.RANK.EQ(AP49, $AP$3:$AP$150)+ COUNTIFS($AP$3:AP49, AP49) - 1,"") | AN49: =P37 | AO49: SAVINGS | AP49: =IFERROR(VLOOKUP(AN49,OCT!$P$23:$R$38,3,FALSE),"")
AM50: =IFERROR(_xlfn.RANK.EQ(AP50, $AP$3:$AP$150)+ COUNTIFS($AP$3:AP50, AP50) - 1,"") | AN50: =U23 | AO50: SAVINGS | AP50: =IFERROR(VLOOKUP(AN50,OCT!$U$23:$W$38,3,FALSE),"")
AM51: =IFERROR(_xlfn.RANK.EQ(AP51, $AP$3:$AP$150)+ COUNTIFS($AP$3:AP51, AP51) - 1,"") | AN51: =U24 | AO51: SAVINGS | AP51: =IFERROR(VLOOKUP(AN51,OCT!$U$23:$W$38,3,FALSE),"")
AM52: =IFERROR(_xlfn.RANK.EQ(AP52, $AP$3:$AP$150)+ COUNTIFS($AP$3:AP52, AP52) - 1,"") | AN52: =U25 | AO52: SAVINGS | AP52: =IFERROR(VLOOKUP(AN52,OCT!$U$23:$W$38,3,FALSE),"")
AM53: =IFERROR(_xlfn.RANK.EQ(AP53, $AP$3:$AP$150)+ COUNTIFS($AP$3:AP53, AP53) - 1,"") | AN53: =U26 | AO53: SAVINGS | AP53: =IFERROR(VLOOKUP(AN53,OCT!$U$23:$W$38,3,FALSE),"")
AM54: =IFERROR(_xlfn.RANK.EQ(AP54, $AP$3:$AP$150)+ COUNTIFS($AP$3:AP54, AP54) - 1,"") | AN54: =U27 | AO54: SAVINGS | AP54: =IFERROR(VLOOKUP(AN54,OCT!$U$23:$W$38,3,FALSE),"")
AM55: =IFERROR(_xlfn.RANK.EQ(AP55, $AP$3:$AP$150)+ COUNTIFS($AP$3:AP55, AP55) - 1,"") | AN55: =U28 | AO55: SAVINGS | AP55: =IFERROR(VLOOKUP(AN55,OCT!$U$23:$W$38,3,FALSE),"")
AM56: =IFERROR(_xlfn.RANK.EQ(AP56, $AP$3:$AP$150)+ COUNTIFS($AP$3:AP56, AP56) - 1,"") | AN56: =U29 | AO56: SAVINGS | AP56: =IFERROR(VLOOKUP(AN56,OCT!$U$23:$W$38,3,FALSE),"")
AM57: =IFERROR(_xlfn.RANK.EQ(AP57, $AP$3:$AP$150)+ COUNTIFS($AP$3:AP57, AP57) - 1,"") | AN57: =U30 | AO57: SAVINGS | AP57: =IFERROR(VLOOKUP(AN57,OCT!$U$23:$W$38,3,FALSE),"")
AM58: =IFERROR(_xlfn.RANK.EQ(AP58, $AP$3:$AP$150)+ COUNTIFS($AP$3:AP58, AP58) - 1,"") | AN58: =U31 | AO58: SAVINGS | AP58: =IFERROR(VLOOKUP(AN58,OCT!$U$23:$W$38,3,FALSE),"")
AM59: =IFERROR(_xlfn.RANK.EQ(AP59, $AP$3:$AP$150)+ COUNTIFS($AP$3:AP59, AP59) - 1,"") | AN59: =U32 | AO59: SAVINGS | AP59: =IFERROR(VLOOKUP(AN59,OCT!$U$23:$W$38,3,FALSE),"")
AM60: =IFERROR(_xlfn.RANK.EQ(AP60, $AP$3:$AP$150)+ COUNTIFS($AP$3:AP60, AP60) - 1,"") | AN60: =U33 | AO60: SAVINGS | AP60: =IFERROR(VLOOKUP(AN60,OCT!$U$23:$W$38,3,FALSE),"")
AM61: =IFERROR(_xlfn.RANK.EQ(AP61, $AP$3:$AP$150)+ COUNTIFS($AP$3:AP61, AP61) - 1,"") | AN61: =U34 | AO61: SAVINGS | AP61: =IFERROR(VLOOKUP(AN61,OCT!$U$23:$W$38,3,FALSE),"")
... AM65: =IFERROR(_xlfn.RANK.EQ(AP65, $AP$3:$AP$150)+ COUNTIFS($AP$3:AP65, AP65) - 1,"") | AN65: =U38 | AO65: SAVINGS | AP65: =IFERROR(VLOOKUP(AN65,OCT!$U$23:$W$38,3,FALSE),"")

Sheet NOV
B2: NOVEMBER | F2: INCOME | J2: BILLS | N2: EXPENSES | R2: DEBT | V2: SAVINGS | AM2: Ranking | AN2: ITEM | AO2: CATEGORY | AP2: TOTAL SPENT
AM3: =IFERROR(_xlfn.RANK.EQ(AP3, $AP$3:$AP$150)+ COUNTIFS($AP$3:AP3, AP3) - 1,"") | AN3: =F23 | AO3: BILLS | AP3: =IFERROR(VLOOKUP(AN3,NOV!$F$23:$H$38,3,FALSE),"")
F4: =SUM(NOV!$D$23:$D$38) -> 0 | J4: =SUM(NOV!$H$23:$H$38) -> 0 | N4: =SUM(NOV!$M$23:$M$38) -> 0 | R4: =SUM(NOV!$R$23:$R$38) -> 0 | V4: =SUM(NOV!$W$23:$W$38) -> 0 | AM4: =IFERROR(_xlfn.RANK.EQ(AP4, $AP$3:$AP$150)+ COUNTIFS($AP$3:AP4, AP4) - 1,"") | AN4: =F24 | AO4: BILLS | AP4: =IFERROR(VLOOKUP(AN4,NOV!$F$23:$H$38,3,FALSE),"")
B5: SUMMARY | AM5: =IFERROR(_xlfn.RANK.EQ(AP5, $AP$3:$AP$150)+ COUNTIFS($AP$3:AP5, AP5) - 1,"") | AN5: =F25 | AO5: BILLS | AP5: =IFERROR(VLOOKUP(AN5,NOV!$F$23:$H$38,3,FALSE),"")
AM6: =IFERROR(_xlfn.RANK.EQ(AP6, $AP$3:$AP$150)+ COUNTIFS($AP$3:AP6, AP6) - 1,"") | AN6: =F26 | AO6: BILLS | AP6: =IFERROR(VLOOKUP(AN6,NOV!$F$23:$H$38,3,FALSE),"")
B7: INCOME OVERVIEW | V7: RANK | W7: ITEM | X7: AMOUNT | AM7: =IFERROR(_xlfn.RANK.EQ(AP7, $AP$3:$AP$150)+ COUNTIFS($AP$3:AP7, AP7) - 1,"") | AN7: =F27 | AO7: BILLS | AP7: =IFERROR(VLOOKUP(AN7,NOV!$F$23:$H$38,3,FALSE),"")
V8: 1 | W8: =IFERROR(VLOOKUP(V8,$AM$3:$AP$65,2,FALSE),"") | X8: =IFERROR(VLOOKUP(V8,$AM$3:$AP$65,4,FALSE),"") | AM8: =IFERROR(_xlfn.RANK.EQ(AP8, $AP$3:$AP$150)+ COUNTIFS($AP$3:AP8, AP8) - 1,"") | AN8: =F28 | AO8: BILLS | AP8: =IFERROR(VLOOKUP(AN8,NOV!$F$23:$H$38,3,FALSE),"")
V9: 2 | W9: =IFERROR(VLOOKUP(V9,$AM$3:$AP$65,2,FALSE),"") | X9: =IFERROR(VLOOKUP(V9,$AM$3:$AP$65,4,FALSE),"") | AM9: =IFERROR(_xlfn.RANK.EQ(AP9, $AP$3:$AP$150)+ COUNTIFS($AP$3:AP9, AP9) - 1,"") | AN9: =F29 | AO9: BILLS | AP9: =IFERROR(VLOOKUP(AN9,NOV!$F$23:$H$38,3,FALSE),"")
C10: Planned | D10: Actual | V10: 3 | W10: =IFERROR(VLOOKUP(V10,$AM$3:$AP$65,2,FALSE),"") | X10: =IFERROR(VLOOKUP(V10,$AM$3:$AP$65,4,FALSE),"") | AM10: =IFERROR(_xlfn.RANK.EQ(AP10, $AP$3:$AP$150)+ COUNTIFS($AP$3:AP10, AP10) - 1,"") | AN10: =F30 | AO10: BILLS | AP10: =IFERROR(VLOOKUP(AN10,NOV!$F$23:$H$38,3,FALSE),"")
B11: INCOME | C11: =SUM(NOV!$C$23:$C$38) -> 0 | D11: =SUM(NOV!$D$23:$D$38) -> 0 | V11: 4 | W11: =IFERROR(VLOOKUP(V11,$AM$3:$AP$65,2,FALSE),"") | X11: =IFERROR(VLOOKUP(V11,$AM$3:$AP$65,4,FALSE),"") | AM11: =IFERROR(_xlfn.RANK.EQ(AP11, $AP$3:$AP$150)+ COUNTIFS($AP$3:AP11, AP11) - 1,"") | AN11: =F31 | AO11: BILLS | AP11: =IFERROR(VLOOKUP(AN11,NOV!$F$23:$H$38,3,FALSE),"")
B12: BILLS | C12: =SUM(NOV!$G$23:$G$38) -> 0 | D12: =SUM(NOV!$H$23:$H$38) -> 0 | V12: 5 | W12: =IFERROR(VLOOKUP(V12,$AM$3:$AP$65,2,FALSE),"") | X12: =IFERROR(VLOOKUP(V12,$AM$3:$AP$65,4,FALSE),"") | AM12: =IFERROR(_xlfn.RANK.EQ(AP12, $AP$3:$AP$150)+ COUNTIFS($AP$3:AP12, AP12) - 1,"") | AN12: =F32 | AO12: BILLS | AP12: =IFERROR(VLOOKUP(AN12,NOV!$F$23:$H$38,3,FALSE),"")
B13: EXPENSES | C13: =SUM(NOV!$L$23:$L$38) -> 0 | D13: =SUM(NOV!$M$23:$M$38) -> 0 | V13: 6 | W13: =IFERROR(VLOOKUP(V13,$AM$3:$AP$65,2,FALSE),"") | X13: =IFERROR(VLOOKUP(V13,$AM$3:$AP$65,4,FALSE),"") | AM13: =IFERROR(_xlfn.RANK.EQ(AP13, $AP$3:$AP$150)+ COUNTIFS($AP$3:AP13, AP13) - 1,"") | AN13: =F33 | AO13: BILLS | AP13: =IFERROR(VLOOKUP(AN13,NOV!$F$23:$H$38,3,FALSE),"")
B14: DEBT | C14: =SUM(NOV!$Q$23:$Q$38) -> 0 | D14: =SUM(NOV!$R$23:$R$38) -> 0 | V14: 7 | W14: =IFERROR(VLOOKUP(V14,$AM$3:$AP$65,2,FALSE),"") | X14: =IFERROR(VLOOKUP(V14,$AM$3:$AP$65,4,FALSE),"") | AM14: =IFERROR(_xlfn.RANK.EQ(AP14, $AP$3:$AP$150)+ COUNTIFS($AP$3:AP14, AP14) - 1,"") | AN14: =F34 | AO14: BILLS | AP14: =IFERROR(VLOOKUP(AN14,NOV!$F$23:$H$38,3,FALSE),"")
B15: SAVINGS | C15: =SUM(NOV!$V$23:$V$38) -> 0 | D15: =SUM(NOV!$W$23:$W$38) -> 0 | V15: 8 | W15: =IFERROR(VLOOKUP(V15,$AM$3:$AP$65,2,FALSE),"") | X15: =IFERROR(VLOOKUP(V15,$AM$3:$AP$65,4,FALSE),"") | AM15: =IFERROR(_xlfn.RANK.EQ(AP15, $AP$3:$AP$150)+ COUNTIFS($AP$3:AP15, AP15) - 1,"") | AN15: =F35 | AO15: BILLS | AP15: =IFERROR(VLOOKUP(AN15,NOV!$F$23:$H$38,3,FALSE),"")
B16: BALANCE | C16: =(C11-SUM(C12:C15)) -> 0 | D16: =(D11-SUM(D12:D15)) -> 0 | V16: 9 | W16: =IFERROR(VLOOKUP(V16,$AM$3:$AP$65,2,FALSE),"") | X16: =IFERROR(VLOOKUP(V16,$AM$3:$AP$65,4,FALSE),"") | AM16: =IFERROR(_xlfn.RANK.EQ(AP16, $AP$3:$AP$150)+ COUNTIFS($AP$3:AP16, AP16) - 1,"") | AN16: =F36 | AO16: BILLS | AP16: =IFERROR(VLOOKUP(AN16,NOV!$F$23:$H$38,3,FALSE),"")
V17: 10 | W17: =IFERROR(VLOOKUP(V17,$AM$3:$AP$65,2,FALSE),"") | X17: =IFERROR(VLOOKUP(V17,$AM$3:$AP$65,4,FALSE),"") | AM17: =IFERROR(_xlfn.RANK.EQ(AP17, $AP$3:$AP$150)+ COUNTIFS($AP$3:AP17, AP17) - 1,"") | AN17: =F37 | AO17: BILLS | AP17: =IFERROR(VLOOKUP(AN17,NOV!$F$23:$H$38,3,FALSE),"")
V18: 11 | W18: =IFERROR(VLOOKUP(V18,$AM$3:$AP$65,2,FALSE),"") | X18: =IFERROR(VLOOKUP(V18,$AM$3:$AP$65,4,FALSE),"") | AM18: =IFERROR(_xlfn.RANK.EQ(AP18, $AP$3:$AP$150)+ COUNTIFS($AP$3:AP18, AP18) - 1,"") | AN18: =F38 | AO18: BILLS | AP18: =IFERROR(VLOOKUP(AN18,NOV!$F$23:$H$38,3,FALSE),"")
AM19: =IFERROR(_xlfn.RANK.EQ(AP19, $AP$3:$AP$150)+ COUNTIFS($AP$3:AP19, AP19) - 1,"") | AN19: =K23 | AO19: EXPENSES | AP19: =IFERROR(VLOOKUP(AN19,NOV!$K$23:$M$38,3,FALSE),"")
B20: INCOME | F20: BILLS | K20: EXPENSES | P20: DEBT | U20: SAVINGS | AM20: =IFERROR(_xlfn.RANK.EQ(AP20, $AP$3:$AP$150)+ COUNTIFS($AP$3:AP20, AP20) - 1,"") | AN20: =K24 | AO20: EXPENSES | AP20: =IFERROR(VLOOKUP(AN20,NOV!$K$23:$M$38,3,FALSE),"")
AM21: =IFERROR(_xlfn.RANK.EQ(AP21, $AP$3:$AP$150)+ COUNTIFS($AP$3:AP21, AP21) - 1,"") | AN21: =K25 | AO21: EXPENSES | AP21: =IFERROR(VLOOKUP(AN21,NOV!$K$23:$M$38,3,FALSE),"")
B22: Details | C22: Planned | D22: Actual | F22: Details | G22: Planned | H22: Actual | I22: Variance | K22: Details | L22: Planned | M22: Actual | N22: Variance | P22: Details | Q22: Planned | R22: Actual | S22: Variance | U22: Details | V22: Planned | W22: Actual | X22: Variance | AM22: =IFERROR(_xlfn.RANK.EQ(AP22, $AP$3:$AP$150)+ COUNTIFS($AP$3:AP22, AP22) - 1,"") | AN22: =K26 | AO22: EXPENSES | AP22: =IFERROR(VLOOKUP(AN22,NOV!$K$23:$M$38,3,FALSE),"")
I23: =NOV!$G23-NOV!$H23 -> 0 | N23: =NOV!$L23-NOV!$M23 -> 0 | S23: =NOV!$Q23-NOV!$R23 -> 0 | X23: =NOV!$V23-NOV!$W23 -> 0 | AM23: =IFERROR(_xlfn.RANK.EQ(AP23, $AP$3:$AP$150)+ COUNTIFS($AP$3:AP23, AP23) - 1,"") | AN23: =K27 | AO23: EXPENSES | AP23: =IFERROR(VLOOKUP(AN23,NOV!$K$23:$M$38,3,FALSE),"")
I24: =NOV!$G24-NOV!$H24 -> 0 | N24: =NOV!$L24-NOV!$M24 -> 0 | S24: =NOV!$Q24-NOV!$R24 -> 0 | X24: =NOV!$V24-NOV!$W24 -> 0 | AM24: =IFERROR(_xlfn.RANK.EQ(AP24, $AP$3:$AP$150)+ COUNTIFS($AP$3:AP24, AP24) - 1,"") | AN24: =K28 | AO24: EXPENSES | AP24: =IFERROR(VLOOKUP(AN24,NOV!$K$23:$M$38,3,FALSE),"")
I25: =NOV!$G25-NOV!$H25 -> 0 | N25: =NOV!$L25-NOV!$M25 -> 0 | S25: =NOV!$Q25-NOV!$R25 -> 0 | X25: =NOV!$V25-NOV!$W25 -> 0 | AM25: =IFERROR(_xlfn.RANK.EQ(AP25, $AP$3:$AP$150)+ COUNTIFS($AP$3:AP25, AP25) - 1,"") | AN25: =K29 | AO25: EXPENSES | AP25: =IFERROR(VLOOKUP(AN25,NOV!$K$23:$M$38,3,FALSE),"")
I26: =NOV!$G26-NOV!$H26 -> 0 | N26: =NOV!$L26-NOV!$M26 -> 0 | S26: =NOV!$Q26-NOV!$R26 -> 0 | X26: =NOV!$V26-NOV!$W26 -> 0 | AM26: =IFERROR(_xlfn.RANK.EQ(AP26, $AP$3:$AP$150)+ COUNTIFS($AP$3:AP26, AP26) - 1,"") | AN26: =K30 | AO26: EXPENSES | AP26: =IFERROR(VLOOKUP(AN26,NOV!$K$23:$M$38,3,FALSE),"")
I27: =NOV!$G27-NOV!$H27 -> 0 | N27: =NOV!$L27-NOV!$M27 -> 0 | S27: =NOV!$Q27-NOV!$R27 -> 0 | X27: =NOV!$V27-NOV!$W27 -> 0 | AM27: =IFERROR(_xlfn.RANK.EQ(AP27, $AP$3:$AP$150)+ COUNTIFS($AP$3:AP27, AP27) - 1,"") | AN27: =K31 | AO27: EXPENSES | AP27: =IFERROR(VLOOKUP(AN27,NOV!$K$23:$M$38,3,FALSE),"")
I28: =NOV!$G28-NOV!$H28 -> 0 | N28: =NOV!$L28-NOV!$M28 -> 0 | S28: =NOV!$Q28-NOV!$R28 -> 0 | X28: =NOV!$V28-NOV!$W28 -> 0 | AM28: =IFERROR(_xlfn.RANK.EQ(AP28, $AP$3:$AP$150)+ COUNTIFS($AP$3:AP28, AP28) - 1,"") | AN28: =K32 | AO28: EXPENSES | AP28: =IFERROR(VLOOKUP(AN28,NOV!$K$23:$M$38,3,FALSE),"")
I29: =NOV!$G29-NOV!$H29 -> 0 | N29: =NOV!$L29-NOV!$M29 -> 0 | S29: =NOV!$Q29-NOV!$R29 -> 0 | X29: =NOV!$V29-NOV!$W29 -> 0 | AM29: =IFERROR(_xlfn.RANK.EQ(AP29, $AP$3:$AP$150)+ COUNTIFS($AP$3:AP29, AP29) - 1,"") | AN29: =K33 | AO29: EXPENSES | AP29: =IFERROR(VLOOKUP(AN29,NOV!$K$23:$M$38,3,FALSE),"")
I30: =NOV!$G30-NOV!$H30 -> 0 | N30: =NOV!$L30-NOV!$M30 -> 0 | S30: =NOV!$Q30-NOV!$R30 -> 0 | X30: =NOV!$V30-NOV!$W30 -> 0 | AM30: =IFERROR(_xlfn.RANK.EQ(AP30, $AP$3:$AP$150)+ COUNTIFS($AP$3:AP30, AP30) - 1,"") | AN30: =K34 | AO30: EXPENSES | AP30: =IFERROR(VLOOKUP(AN30,NOV!$K$23:$M$38,3,FALSE),"")
I31: =NOV!$G31-NOV!$H31 -> 0 | N31: =NOV!$L31-NOV!$M31 -> 0 | S31: =NOV!$Q31-NOV!$R31 -> 0 | X31: =NOV!$V31-NOV!$W31 -> 0 | AM31: =IFERROR(_xlfn.RANK.EQ(AP31, $AP$3:$AP$150)+ COUNTIFS($AP$3:AP31, AP31) - 1,"") | AN31: =K35 | AO31: EXPENSES | AP31: =IFERROR(VLOOKUP(AN31,NOV!$K$23:$M$38,3,FALSE),"")
I32: =NOV!$G32-NOV!$H32 -> 0 | N32: =NOV!$L32-NOV!$M32 -> 0 | S32: =NOV!$Q32-NOV!$R32 -> 0 | X32: =NOV!$V32-NOV!$W32 -> 0 | AM32: =IFERROR(_xlfn.RANK.EQ(AP32, $AP$3:$AP$150)+ COUNTIFS($AP$3:AP32, AP32) - 1,"") | AN32: =K36 | AO32: EXPENSES | AP32: =IFERROR(VLOOKUP(AN32,NOV!$K$23:$M$38,3,FALSE),"")
I33: =NOV!$G33-NOV!$H33 -> 0 | N33: =NOV!$L33-NOV!$M33 -> 0 | S33: =NOV!$Q33-NOV!$R33 -> 0 | X33: =NOV!$V33-NOV!$W33 -> 0 | AM33: =IFERROR(_xlfn.RANK.EQ(AP33, $AP$3:$AP$150)+ COUNTIFS($AP$3:AP33, AP33) - 1,"") | AN33: =K37 | AO33: EXPENSES | AP33: =IFERROR(VLOOKUP(AN33,NOV!$K$23:$M$38,3,FALSE),"")
I34: =NOV!$G34-NOV!$H34 -> 0 | N34: =NOV!$L34-NOV!$M34 -> 0 | S34: =NOV!$Q34-NOV!$R34 -> 0 | X34: =NOV!$V34-NOV!$W34 -> 0 | AM34: =IFERROR(_xlfn.RANK.EQ(AP34, $AP$3:$AP$150)+ COUNTIFS($AP$3:AP34, AP34) - 1,"") | AN34: =K38 | AO34: DEBTS | AP34: =IFERROR(VLOOKUP(AN34,NOV!$K$23:$M$38,3,FALSE),"")
I35: =NOV!$G35-NOV!$H35 -> 0 | N35: =NOV!$L35-NOV!$M35 -> 0 | S35: =NOV!$Q35-NOV!$R35 -> 0 | X35: =NOV!$V35-NOV!$W35 -> 0 | AM35: =IFERROR(_xlfn.RANK.EQ(AP35, $AP$3:$AP$150)+ COUNTIFS($AP$3:AP35, AP35) - 1,"") | AN35: =P23 | AO35: DEBTS | AP35: =IFERROR(VLOOKUP(AN35,NOV!$P$23:$R$38,3,FALSE),"")
I36: =NOV!$G36-NOV!$H36 -> 0 | N36: =NOV!$L36-NOV!$M36 -> 0 | S36: =NOV!$Q36-NOV!$R36 -> 0 | X36: =NOV!$V36-NOV!$W36 -> 0 | AM36: =IFERROR(_xlfn.RANK.EQ(AP36, $AP$3:$AP$150)+ COUNTIFS($AP$3:AP36, AP36) - 1,"") | AN36: =P24 | AO36: DEBTS | AP36: =IFERROR(VLOOKUP(AN36,NOV!$P$23:$R$38,3,FALSE),"")
I37: =NOV!$G37-NOV!$H37 -> 0 | N37: =NOV!$L37-NOV!$M37 -> 0 | S37: =NOV!$Q37-NOV!$R37 -> 0 | X37: =NOV!$V37-NOV!$W37 -> 0 | AM37: =IFERROR(_xlfn.RANK.EQ(AP37, $AP$3:$AP$150)+ COUNTIFS($AP$3:AP37, AP37) - 1,"") | AN37: =P25 | AO37: DEBTS | AP37: =IFERROR(VLOOKUP(AN37,NOV!$P$23:$R$38,3,FALSE),"")
I38: =NOV!$G38-NOV!$H38 -> 0 | N38: =NOV!$L38-NOV!$M38 -> 0 | S38: =NOV!$Q38-NOV!$R38 -> 0 | X38: =NOV!$V38-NOV!$W38 -> 0 | AM38: =IFERROR(_xlfn.RANK.EQ(AP38, $AP$3:$AP$150)+ COUNTIFS($AP$3:AP38, AP38) - 1,"") | AN38: =P26 | AO38: DEBTS | AP38: =IFERROR(VLOOKUP(AN38,NOV!$P$23:$R$38,3,FALSE),"")
AM39: =IFERROR(_xlfn.RANK.EQ(AP39, $AP$3:$AP$150)+ COUNTIFS($AP$3:AP39, AP39) - 1,"") | AN39: =P27 | AO39: DEBTS | AP39: =IFERROR(VLOOKUP(AN39,NOV!$P$23:$R$38,3,FALSE),"")
AM40: =IFERROR(_xlfn.RANK.EQ(AP40, $AP$3:$AP$150)+ COUNTIFS($AP$3:AP40, AP40) - 1,"") | AN40: =P28 | AO40: DEBTS | AP40: =IFERROR(VLOOKUP(AN40,NOV!$P$23:$R$38,3,FALSE),"")
AM41: =IFERROR(_xlfn.RANK.EQ(AP41, $AP$3:$AP$150)+ COUNTIFS($AP$3:AP41, AP41) - 1,"") | AN41: =P29 | AO41: DEBTS | AP41: =IFERROR(VLOOKUP(AN41,NOV!$P$23:$R$38,3,FALSE),"")
AM42: =IFERROR(_xlfn.RANK.EQ(AP42, $AP$3:$AP$150)+ COUNTIFS($AP$3:AP42, AP42) - 1,"") | AN42: =P30 | AO42: DEBTS | AP42: =IFERROR(VLOOKUP(AN42,NOV!$P$23:$R$38,3,FALSE),"")
AM43: =IFERROR(_xlfn.RANK.EQ(AP43, $AP$3:$AP$150)+ COUNTIFS($AP$3:AP43, AP43) - 1,"") | AN43: =P31 | AO43: DEBTS | AP43: =IFERROR(VLOOKUP(AN43,NOV!$P$23:$R$38,3,FALSE),"")
AM44: =IFERROR(_xlfn.RANK.EQ(AP44, $AP$3:$AP$150)+ COUNTIFS($AP$3:AP44, AP44) - 1,"") | AN44: =P32 | AO44: DEBTS | AP44: =IFERROR(VLOOKUP(AN44,NOV!$P$23:$R$38,3,FALSE),"")
AM45: =IFERROR(_xlfn.RANK.EQ(AP45, $AP$3:$AP$150)+ COUNTIFS($AP$3:AP45, AP45) - 1,"") | AN45: =P33 | AO45: DEBTS | AP45: =IFERROR(VLOOKUP(AN45,NOV!$P$23:$R$38,3,FALSE),"")
AM46: =IFERROR(_xlfn.RANK.EQ(AP46, $AP$3:$AP$150)+ COUNTIFS($AP$3:AP46, AP46) - 1,"") | AN46: =P34 | AO46: DEBTS | AP46: =IFERROR(VLOOKUP(AN46,NOV!$P$23:$R$38,3,FALSE),"")
AM47: =IFERROR(_xlfn.RANK.EQ(AP47, $AP$3:$AP$150)+ COUNTIFS($AP$3:AP47, AP47) - 1,"") | AN47: =P35 | AO47: DEBTS | AP47: =IFERROR(VLOOKUP(AN47,NOV!$P$23:$R$38,3,FALSE),"")
AM48: =IFERROR(_xlfn.RANK.EQ(AP48, $AP$3:$AP$150)+ COUNTIFS($AP$3:AP48, AP48) - 1,"") | AN48: =P36 | AO48: DEBTS | AP48: =IFERROR(VLOOKUP(AN48,NOV!$P$23:$R$38,3,FALSE),"")
AM49: =IFERROR(_xlfn.RANK.EQ(AP49, $AP$3:$AP$150)+ COUNTIFS($AP$3:AP49, AP49) - 1,"") | AN49: =P37 | AO49: SAVINGS | AP49: =IFERROR(VLOOKUP(AN49,NOV!$P$23:$R$38,3,FALSE),"")
AM50: =IFERROR(_xlfn.RANK.EQ(AP50, $AP$3:$AP$150)+ COUNTIFS($AP$3:AP50, AP50) - 1,"") | AN50: =U23 | AO50: SAVINGS | AP50: =IFERROR(VLOOKUP(AN50,NOV!$U$23:$W$38,3,FALSE),"")
AM51: =IFERROR(_xlfn.RANK.EQ(AP51, $AP$3:$AP$150)+ COUNTIFS($AP$3:AP51, AP51) - 1,"") | AN51: =U24 | AO51: SAVINGS | AP51: =IFERROR(VLOOKUP(AN51,NOV!$U$23:$W$38,3,FALSE),"")
AM52: =IFERROR(_xlfn.RANK.EQ(AP52, $AP$3:$AP$150)+ COUNTIFS($AP$3:AP52, AP52) - 1,"") | AN52: =U25 | AO52: SAVINGS | AP52: =IFERROR(VLOOKUP(AN52,NOV!$U$23:$W$38,3,FALSE),"")
AM53: =IFERROR(_xlfn.RANK.EQ(AP53, $AP$3:$AP$150)+ COUNTIFS($AP$3:AP53, AP53) - 1,"") | AN53: =U26 | AO53: SAVINGS | AP53: =IFERROR(VLOOKUP(AN53,NOV!$U$23:$W$38,3,FALSE),"")
AM54: =IFERROR(_xlfn.RANK.EQ(AP54, $AP$3:$AP$150)+ COUNTIFS($AP$3:AP54, AP54) - 1,"") | AN54: =U27 | AO54: SAVINGS | AP54: =IFERROR(VLOOKUP(AN54,NOV!$U$23:$W$38,3,FALSE),"")
AM55: =IFERROR(_xlfn.RANK.EQ(AP55, $AP$3:$AP$150)+ COUNTIFS($AP$3:AP55, AP55) - 1,"") | AN55: =U28 | AO55: SAVINGS | AP55: =IFERROR(VLOOKUP(AN55,NOV!$U$23:$W$38,3,FALSE),"")
AM56: =IFERROR(_xlfn.RANK.EQ(AP56, $AP$3:$AP$150)+ COUNTIFS($AP$3:AP56, AP56) - 1,"") | AN56: =U29 | AO56: SAVINGS | AP56: =IFERROR(VLOOKUP(AN56,NOV!$U$23:$W$38,3,FALSE),"")
AM57: =IFERROR(_xlfn.RANK.EQ(AP57, $AP$3:$AP$150)+ COUNTIFS($AP$3:AP57, AP57) - 1,"") | AN57: =U30 | AO57: SAVINGS | AP57: =IFERROR(VLOOKUP(AN57,NOV!$U$23:$W$38,3,FALSE),"")
AM58: =IFERROR(_xlfn.RANK.EQ(AP58, $AP$3:$AP$150)+ COUNTIFS($AP$3:AP58, AP58) - 1,"") | AN58: =U31 | AO58: SAVINGS | AP58: =IFERROR(VLOOKUP(AN58,NOV!$U$23:$W$38,3,FALSE),"")
AM59: =IFERROR(_xlfn.RANK.EQ(AP59, $AP$3:$AP$150)+ COUNTIFS($AP$3:AP59, AP59) - 1,"") | AN59: =U32 | AO59: SAVINGS | AP59: =IFERROR(VLOOKUP(AN59,NOV!$U$23:$W$38,3,FALSE),"")
AM60: =IFERROR(_xlfn.RANK.EQ(AP60, $AP$3:$AP$150)+ COUNTIFS($AP$3:AP60, AP60) - 1,"") | AN60: =U33 | AO60: SAVINGS | AP60: =IFERROR(VLOOKUP(AN60,NOV!$U$23:$W$38,3,FALSE),"")
AM61: =IFERROR(_xlfn.RANK.EQ(AP61, $AP$3:$AP$150)+ COUNTIFS($AP$3:AP61, AP61) - 1,"") | AN61: =U34 | AO61: SAVINGS | AP61: =IFERROR(VLOOKUP(AN61,NOV!$U$23:$W$38,3,FALSE),"")
... AM65: =IFERROR(_xlfn.RANK.EQ(AP65, $AP$3:$AP$150)+ COUNTIFS($AP$3:AP65, AP65) - 1,"") | AN65: =U38 | AO65: SAVINGS | AP65: =IFERROR(VLOOKUP(AN65,NOV!$U$23:$W$38,3,FALSE),"")

Sheet DEC
B2: DECEMBER | F2: INCOME | J2: BILLS | N2: EXPENSES | R2: DEBT | V2: SAVINGS | AM2: Ranking | AN2: ITEM | AO2: CATEGORY | AP2: TOTAL SPENT
AM3: =IFERROR(_xlfn.RANK.EQ(AP3, $AP$3:$AP$150)+ COUNTIFS($AP$3:AP3, AP3) - 1,"") | AN3: =F23 | AO3: BILLS | AP3: =IFERROR(VLOOKUP(AN3,DEC!$F$23:$H$38,3,FALSE),"")
F4: =SUM(DEC!$D$23:$D$38) -> 0 | J4: =SUM(DEC!$H$23:$H$38) -> 0 | N4: =SUM(DEC!$M$23:$M$38) -> 0 | R4: =SUM(DEC!$R$23:$R$38) -> 0 | V4: =SUM(DEC!$W$23:$W$38) -> 0 | AM4: =IFERROR(_xlfn.RANK.EQ(AP4, $AP$3:$AP$150)+ COUNTIFS($AP$3:AP4, AP4) - 1,"") | AN4: =F24 | AO4: BILLS | AP4: =IFERROR(VLOOKUP(AN4,DEC!$F$23:$H$38,3,FALSE),"")
B5: SUMMARY | AM5: =IFERROR(_xlfn.RANK.EQ(AP5, $AP$3:$AP$150)+ COUNTIFS($AP$3:AP5, AP5) - 1,"") | AN5: =F25 | AO5: BILLS | AP5: =IFERROR(VLOOKUP(AN5,DEC!$F$23:$H$38,3,FALSE),"")
AM6: =IFERROR(_xlfn.RANK.EQ(AP6, $AP$3:$AP$150)+ COUNTIFS($AP$3:AP6, AP6) - 1,"") | AN6: =F26 | AO6: BILLS | AP6: =IFERROR(VLOOKUP(AN6,DEC!$F$23:$H$38,3,FALSE),"")
B7: INCOME OVERVIEW | V7: RANK | W7: ITEM | X7: AMOUNT | AM7: =IFERROR(_xlfn.RANK.EQ(AP7, $AP$3:$AP$150)+ COUNTIFS($AP$3:AP7, AP7) - 1,"") | AN7: =F27 | AO7: BILLS | AP7: =IFERROR(VLOOKUP(AN7,DEC!$F$23:$H$38,3,FALSE),"")
V8: 1 | W8: =IFERROR(VLOOKUP(V8,$AM$3:$AP$65,2,FALSE),"") | X8: =IFERROR(VLOOKUP(V8,$AM$3:$AP$65,4,FALSE),"") | AM8: =IFERROR(_xlfn.RANK.EQ(AP8, $AP$3:$AP$150)+ COUNTIFS($AP$3:AP8, AP8) - 1,"") | AN8: =F28 | AO8: BILLS | AP8: =IFERROR(VLOOKUP(AN8,DEC!$F$23:$H$38,3,FALSE),"")
V9: 2 | W9: =IFERROR(VLOOKUP(V9,$AM$3:$AP$65,2,FALSE),"") | X9: =IFERROR(VLOOKUP(V9,$AM$3:$AP$65,4,FALSE),"") | AM9: =IFERROR(_xlfn.RANK.EQ(AP9, $AP$3:$AP$150)+ COUNTIFS($AP$3:AP9, AP9) - 1,"") | AN9: =F29 | AO9: BILLS | AP9: =IFERROR(VLOOKUP(AN9,DEC!$F$23:$H$38,3,FALSE),"")
C10: Planned | D10: Actual | V10: 3 | W10: =IFERROR(VLOOKUP(V10,$AM$3:$AP$65,2,FALSE),"") | X10: =IFERROR(VLOOKUP(V10,$AM$3:$AP$65,4,FALSE),"") | AM10: =IFERROR(_xlfn.RANK.EQ(AP10, $AP$3:$AP$150)+ COUNTIFS($AP$3:AP10, AP10) - 1,"") | AN10: =F30 | AO10: BILLS | AP10: =IFERROR(VLOOKUP(AN10,DEC!$F$23:$H$38,3,FALSE),"")
B11: INCOME | C11: =SUM(DEC!$C$23:$C$38) -> 0 | D11: =SUM(DEC!$D$23:$D$38) -> 0 | V11: 4 | W11: =IFERROR(VLOOKUP(V11,$AM$3:$AP$65,2,FALSE),"") | X11: =IFERROR(VLOOKUP(V11,$AM$3:$AP$65,4,FALSE),"") | AM11: =IFERROR(_xlfn.RANK.EQ(AP11, $AP$3:$AP$150)+ COUNTIFS($AP$3:AP11, AP11) - 1,"") | AN11: =F31 | AO11: BILLS | AP11: =IFERROR(VLOOKUP(AN11,DEC!$F$23:$H$38,3,FALSE),"")
B12: BILLS | C12: =SUM(DEC!$G$23:$G$38) -> 0 | D12: =SUM(DEC!$H$23:$H$38) -> 0 | V12: 5 | W12: =IFERROR(VLOOKUP(V12,$AM$3:$AP$65,2,FALSE),"") | X12: =IFERROR(VLOOKUP(V12,$AM$3:$AP$65,4,FALSE),"") | AM12: =IFERROR(_xlfn.RANK.EQ(AP12, $AP$3:$AP$150)+ COUNTIFS($AP$3:AP12, AP12) - 1,"") | AN12: =F32 | AO12: BILLS | AP12: =IFERROR(VLOOKUP(AN12,DEC!$F$23:$H$38,3,FALSE),"")
B13: EXPENSES | C13: =SUM(DEC!$L$23:$L$38) -> 0 | D13: =SUM(DEC!$M$23:$M$38) -> 0 | V13: 6 | W13: =IFERROR(VLOOKUP(V13,$AM$3:$AP$65,2,FALSE),"") | X13: =IFERROR(VLOOKUP(V13,$AM$3:$AP$65,4,FALSE),"") | AM13: =IFERROR(_xlfn.RANK.EQ(AP13, $AP$3:$AP$150)+ COUNTIFS($AP$3:AP13, AP13) - 1,"") | AN13: =F33 | AO13: BILLS | AP13: =IFERROR(VLOOKUP(AN13,DEC!$F$23:$H$38,3,FALSE),"")
B14: DEBT | C14: =SUM(DEC!$Q$23:$Q$38) -> 0 | D14: =SUM(DEC!$R$23:$R$38) -> 0 | V14: 7 | W14: =IFERROR(VLOOKUP(V14,$AM$3:$AP$65,2,FALSE),"") | X14: =IFERROR(VLOOKUP(V14,$AM$3:$AP$65,4,FALSE),"") | AM14: =IFERROR(_xlfn.RANK.EQ(AP14, $AP$3:$AP$150)+ COUNTIFS($AP$3:AP14, AP14) - 1,"") | AN14: =F34 | AO14: BILLS | AP14: =IFERROR(VLOOKUP(AN14,DEC!$F$23:$H$38,3,FALSE),"")
B15: SAVINGS | C15: =SUM(DEC!$V$23:$V$38) -> 0 | D15: =SUM(DEC!$W$23:$W$38) -> 0 | V15: 8 | W15: =IFERROR(VLOOKUP(V15,$AM$3:$AP$65,2,FALSE),"") | X15: =IFERROR(VLOOKUP(V15,$AM$3:$AP$65,4,FALSE),"") | AM15: =IFERROR(_xlfn.RANK.EQ(AP15, $AP$3:$AP$150)+ COUNTIFS($AP$3:AP15, AP15) - 1,"") | AN15: =F35 | AO15: BILLS | AP15: =IFERROR(VLOOKUP(AN15,DEC!$F$23:$H$38,3,FALSE),"")
B16: BALANCE | C16: =(C11-SUM(C12:C15)) -> 0 | D16: =(D11-SUM(D12:D15)) -> 0 | V16: 9 | W16: =IFERROR(VLOOKUP(V16,$AM$3:$AP$65,2,FALSE),"") | X16: =IFERROR(VLOOKUP(V16,$AM$3:$AP$65,4,FALSE),"") | AM16: =IFERROR(_xlfn.RANK.EQ(AP16, $AP$3:$AP$150)+ COUNTIFS($AP$3:AP16, AP16) - 1,"") | AN16: =F36 | AO16: BILLS | AP16: =IFERROR(VLOOKUP(AN16,DEC!$F$23:$H$38,3,FALSE),"")
V17: 10 | W17: =IFERROR(VLOOKUP(V17,$AM$3:$AP$65,2,FALSE),"") | X17: =IFERROR(VLOOKUP(V17,$AM$3:$AP$65,4,FALSE),"") | AM17: =IFERROR(_xlfn.RANK.EQ(AP17, $AP$3:$AP$150)+ COUNTIFS($AP$3:AP17, AP17) - 1,"") | AN17: =F37 | AO17: BILLS | AP17: =IFERROR(VLOOKUP(AN17,DEC!$F$23:$H$38,3,FALSE),"")
V18: 11 | W18: =IFERROR(VLOOKUP(V18,$AM$3:$AP$65,2,FALSE),"") | X18: =IFERROR(VLOOKUP(V18,$AM$3:$AP$65,4,FALSE),"") | AM18: =IFERROR(_xlfn.RANK.EQ(AP18, $AP$3:$AP$150)+ COUNTIFS($AP$3:AP18, AP18) - 1,"") | AN18: =F38 | AO18: BILLS | AP18: =IFERROR(VLOOKUP(AN18,DEC!$F$23:$H$38,3,FALSE),"")
AM19: =IFERROR(_xlfn.RANK.EQ(AP19, $AP$3:$AP$150)+ COUNTIFS($AP$3:AP19, AP19) - 1,"") | AN19: =K23 | AO19: EXPENSES | AP19: =IFERROR(VLOOKUP(AN19,DEC!$K$23:$M$38,3,FALSE),"")
B20: INCOME | F20: BILLS | K20: EXPENSES | P20: DEBT | U20: SAVINGS | AM20: =IFERROR(_xlfn.RANK.EQ(AP20, $AP$3:$AP$150)+ COUNTIFS($AP$3:AP20, AP20) - 1,"") | AN20: =K24 | AO20: EXPENSES | AP20: =IFERROR(VLOOKUP(AN20,DEC!$K$23:$M$38,3,FALSE),"")
AM21: =IFERROR(_xlfn.RANK.EQ(AP21, $AP$3:$AP$150)+ COUNTIFS($AP$3:AP21, AP21) - 1,"") | AN21: =K25 | AO21: EXPENSES | AP21: =IFERROR(VLOOKUP(AN21,DEC!$K$23:$M$38,3,FALSE),"")
B22: Details | C22: Planned | D22: Actual | F22: Details | G22: Planned | H22: Actual | I22: Variance | K22: Details | L22: Planned | M22: Actual | N22: Variance | P22: Details | Q22: Planned | R22: Actual | S22: Variance | U22: Details | V22: Planned | W22: Actual | X22: Variance | AM22: =IFERROR(_xlfn.RANK.EQ(AP22, $AP$3:$AP$150)+ COUNTIFS($AP$3:AP22, AP22) - 1,"") | AN22: =K26 | AO22: EXPENSES | AP22: =IFERROR(VLOOKUP(AN22,DEC!$K$23:$M$38,3,FALSE),"")
I23: =DEC!$G23-DEC!$H23 -> 0 | N23: =DEC!$L23-DEC!$M23 -> 0 | S23: =DEC!$Q23-DEC!$R23 -> 0 | X23: =DEC!$V23-DEC!$W23 -> 0 | AM23: =IFERROR(_xlfn.RANK.EQ(AP23, $AP$3:$AP$150)+ COUNTIFS($AP$3:AP23, AP23) - 1,"") | AN23: =K27 | AO23: EXPENSES | AP23: =IFERROR(VLOOKUP(AN23,DEC!$K$23:$M$38,3,FALSE),"")
I24: =DEC!$G24-DEC!$H24 -> 0 | N24: =DEC!$L24-DEC!$M24 -> 0 | S24: =DEC!$Q24-DEC!$R24 -> 0 | X24: =DEC!$V24-DEC!$W24 -> 0 | AM24: =IFERROR(_xlfn.RANK.EQ(AP24, $AP$3:$AP$150)+ COUNTIFS($AP$3:AP24, AP24) - 1,"") | AN24: =K28 | AO24: EXPENSES | AP24: =IFERROR(VLOOKUP(AN24,DEC!$K$23:$M$38,3,FALSE),"")
I25: =DEC!$G25-DEC!$H25 -> 0 | N25: =DEC!$L25-DEC!$M25 -> 0 | S25: =DEC!$Q25-DEC!$R25 -> 0 | X25: =DEC!$V25-DEC!$W25 -> 0 | AM25: =IFERROR(_xlfn.RANK.EQ(AP25, $AP$3:$AP$150)+ COUNTIFS($AP$3:AP25, AP25) - 1,"") | AN25: =K29 | AO25: EXPENSES | AP25: =IFERROR(VLOOKUP(AN25,DEC!$K$23:$M$38,3,FALSE),"")
I26: =DEC!$G26-DEC!$H26 -> 0 | N26: =DEC!$L26-DEC!$M26 -> 0 | S26: =DEC!$Q26-DEC!$R26 -> 0 | X26: =DEC!$V26-DEC!$W26 -> 0 | AM26: =IFERROR(_xlfn.RANK.EQ(AP26, $AP$3:$AP$150)+ COUNTIFS($AP$3:AP26, AP26) - 1,"") | AN26: =K30 | AO26: EXPENSES | AP26: =IFERROR(VLOOKUP(AN26,DEC!$K$23:$M$38,3,FALSE),"")
I27: =DEC!$G27-DEC!$H27 -> 0 | N27: =DEC!$L27-DEC!$M27 -> 0 | S27: =DEC!$Q27-DEC!$R27 -> 0 | X27: =DEC!$V27-DEC!$W27 -> 0 | AM27: =IFERROR(_xlfn.RANK.EQ(AP27, $AP$3:$AP$150)+ COUNTIFS($AP$3:AP27, AP27) - 1,"") | AN27: =K31 | AO27: EXPENSES | AP27: =IFERROR(VLOOKUP(AN27,DEC!$K$23:$M$38,3,FALSE),"")
I28: =DEC!$G28-DEC!$H28 -> 0 | N28: =DEC!$L28-DEC!$M28 -> 0 | S28: =DEC!$Q28-DEC!$R28 -> 0 | X28: =DEC!$V28-DEC!$W28 -> 0 | AM28: =IFERROR(_xlfn.RANK.EQ(AP28, $AP$3:$AP$150)+ COUNTIFS($AP$3:AP28, AP28) - 1,"") | AN28: =K32 | AO28: EXPENSES | AP28: =IFERROR(VLOOKUP(AN28,DEC!$K$23:$M$38,3,FALSE),"")
I29: =DEC!$G29-DEC!$H29 -> 0 | N29: =DEC!$L29-DEC!$M29 -> 0 | S29: =DEC!$Q29-DEC!$R29 -> 0 | X29: =DEC!$V29-DEC!$W29 -> 0 | AM29: =IFERROR(_xlfn.RANK.EQ(AP29, $AP$3:$AP$150)+ COUNTIFS($AP$3:AP29, AP29) - 1,"") | AN29: =K33 | AO29: EXPENSES | AP29: =IFERROR(VLOOKUP(AN29,DEC!$K$23:$M$38,3,FALSE),"")
I30: =DEC!$G30-DEC!$H30 -> 0 | N30: =DEC!$L30-DEC!$M30 -> 0 | S30: =DEC!$Q30-DEC!$R30 -> 0 | X30: =DEC!$V30-DEC!$W30 -> 0 | AM30: =IFERROR(_xlfn.RANK.EQ(AP30, $AP$3:$AP$150)+ COUNTIFS($AP$3:AP30, AP30) - 1,"") | AN30: =K34 | AO30: EXPENSES | AP30: =IFERROR(VLOOKUP(AN30,DEC!$K$23:$M$38,3,FALSE),"")
I31: =DEC!$G31-DEC!$H31 -> 0 | N31: =DEC!$L31-DEC!$M31 -> 0 | S31: =DEC!$Q31-DEC!$R31 -> 0 | X31: =DEC!$V31-DEC!$W31 -> 0 | AM31: =IFERROR(_xlfn.RANK.EQ(AP31, $AP$3:$AP$150)+ COUNTIFS($AP$3:AP31, AP31) - 1,"") | AN31: =K35 | AO31: EXPENSES | AP31: =IFERROR(VLOOKUP(AN31,DEC!$K$23:$M$38,3,FALSE),"")
I32: =DEC!$G32-DEC!$H32 -> 0 | N32: =DEC!$L32-DEC!$M32 -> 0 | S32: =DEC!$Q32-DEC!$R32 -> 0 | X32: =DEC!$V32-DEC!$W32 -> 0 | AM32: =IFERROR(_xlfn.RANK.EQ(AP32, $AP$3:$AP$150)+ COUNTIFS($AP$3:AP32, AP32) - 1,"") | AN32: =K36 | AO32: EXPENSES | AP32: =IFERROR(VLOOKUP(AN32,DEC!$K$23:$M$38,3,FALSE),"")
I33: =DEC!$G33-DEC!$H33 -> 0 | N33: =DEC!$L33-DEC!$M33 -> 0 | S33: =DEC!$Q33-DEC!$R33 -> 0 | X33: =DEC!$V33-DEC!$W33 -> 0 | AM33: =IFERROR(_xlfn.RANK.EQ(AP33, $AP$3:$AP$150)+ COUNTIFS($AP$3:AP33, AP33) - 1,"") | AN33: =K37 | AO33: EXPENSES | AP33: =IFERROR(VLOOKUP(AN33,DEC!$K$23:$M$38,3,FALSE),"")
I34: =DEC!$G34-DEC!$H34 -> 0 | N34: =DEC!$L34-DEC!$M34 -> 0 | S34: =DEC!$Q34-DEC!$R34 -> 0 | X34: =DEC!$V34-DEC!$W34 -> 0 | AM34: =IFERROR(_xlfn.RANK.EQ(AP34, $AP$3:$AP$150)+ COUNTIFS($AP$3:AP34, AP34) - 1,"") | AN34: =K38 | AO34: DEBTS | AP34: =IFERROR(VLOOKUP(AN34,DEC!$K$23:$M$38,3,FALSE),"")
I35: =DEC!$G35-DEC!$H35 -> 0 | N35: =DEC!$L35-DEC!$M35 -> 0 | S35: =DEC!$Q35-DEC!$R35 -> 0 | X35: =DEC!$V35-DEC!$W35 -> 0 | AM35: =IFERROR(_xlfn.RANK.EQ(AP35, $AP$3:$AP$150)+ COUNTIFS($AP$3:AP35, AP35) - 1,"") | AN35: =P23 | AO35: DEBTS | AP35: =IFERROR(VLOOKUP(AN35,DEC!$P$23:$R$38,3,FALSE),"")
I36: =DEC!$G36-DEC!$H36 -> 0 | N36: =DEC!$L36-DEC!$M36 -> 0 | S36: =DEC!$Q36-DEC!$R36 -> 0 | X36: =DEC!$V36-DEC!$W36 -> 0 | AM36: =IFERROR(_xlfn.RANK.EQ(AP36, $AP$3:$AP$150)+ COUNTIFS($AP$3:AP36, AP36) - 1,"") | AN36: =P24 | AO36: DEBTS | AP36: =IFERROR(VLOOKUP(AN36,DEC!$P$23:$R$38,3,FALSE),"")
I37: =DEC!$G37-DEC!$H37 -> 0 | N37: =DEC!$L37-DEC!$M37 -> 0 | S37: =DEC!$Q37-DEC!$R37 -> 0 | X37: =DEC!$V37-DEC!$W37 -> 0 | AM37: =IFERROR(_xlfn.RANK.EQ(AP37, $AP$3:$AP$150)+ COUNTIFS($AP$3:AP37, AP37) - 1,"") | AN37: =P25 | AO37: DEBTS | AP37: =IFERROR(VLOOKUP(AN37,DEC!$P$23:$R$38,3,FALSE),"")
I38: =DEC!$G38-DEC!$H38 -> 0 | N38: =DEC!$L38-DEC!$M38 -> 0 | S38: =DEC!$Q38-DEC!$R38 -> 0 | X38: =DEC!$V38-DEC!$W38 -> 0 | AM38: =IFERROR(_xlfn.RANK.EQ(AP38, $AP$3:$AP$150)+ COUNTIFS($AP$3:AP38, AP38) - 1,"") | AN38: =P26 | AO38: DEBTS | AP38: =IFERROR(VLOOKUP(AN38,DEC!$P$23:$R$38,3,FALSE),"")
AM39: =IFERROR(_xlfn.RANK.EQ(AP39, $AP$3:$AP$150)+ COUNTIFS($AP$3:AP39, AP39) - 1,"") | AN39: =P27 | AO39: DEBTS | AP39: =IFERROR(VLOOKUP(AN39,DEC!$P$23:$R$38,3,FALSE),"")
AM40: =IFERROR(_xlfn.RANK.EQ(AP40, $AP$3:$AP$150)+ COUNTIFS($AP$3:AP40, AP40) - 1,"") | AN40: =P28 | AO40: DEBTS | AP40: =IFERROR(VLOOKUP(AN40,DEC!$P$23:$R$38,3,FALSE),"")
AM41: =IFERROR(_xlfn.RANK.EQ(AP41, $AP$3:$AP$150)+ COUNTIFS($AP$3:AP41, AP41) - 1,"") | AN41: =P29 | AO41: DEBTS | AP41: =IFERROR(VLOOKUP(AN41,DEC!$P$23:$R$38,3,FALSE),"")
AM42: =IFERROR(_xlfn.RANK.EQ(AP42, $AP$3:$AP$150)+ COUNTIFS($AP$3:AP42, AP42) - 1,"") | AN42: =P30 | AO42: DEBTS | AP42: =IFERROR(VLOOKUP(AN42,DEC!$P$23:$R$38,3,FALSE),"")
AM43: =IFERROR(_xlfn.RANK.EQ(AP43, $AP$3:$AP$150)+ COUNTIFS($AP$3:AP43, AP43) - 1,"") | AN43: =P31 | AO43: DEBTS | AP43: =IFERROR(VLOOKUP(AN43,DEC!$P$23:$R$38,3,FALSE),"")
AM44: =IFERROR(_xlfn.RANK.EQ(AP44, $AP$3:$AP$150)+ COUNTIFS($AP$3:AP44, AP44) - 1,"") | AN44: =P32 | AO44: DEBTS | AP44: =IFERROR(VLOOKUP(AN44,DEC!$P$23:$R$38,3,FALSE),"")
AM45: =IFERROR(_xlfn.RANK.EQ(AP45, $AP$3:$AP$150)+ COUNTIFS($AP$3:AP45, AP45) - 1,"") | AN45: =P33 | AO45: DEBTS | AP45: =IFERROR(VLOOKUP(AN45,DEC!$P$23:$R$38,3,FALSE),"")
AM46: =IFERROR(_xlfn.RANK.EQ(AP46, $AP$3:$AP$150)+ COUNTIFS($AP$3:AP46, AP46) - 1,"") | AN46: =P34 | AO46: DEBTS | AP46: =IFERROR(VLOOKUP(AN46,DEC!$P$23:$R$38,3,FALSE),"")
AM47: =IFERROR(_xlfn.RANK.EQ(AP47, $AP$3:$AP$150)+ COUNTIFS($AP$3:AP47, AP47) - 1,"") | AN47: =P35 | AO47: DEBTS | AP47: =IFERROR(VLOOKUP(AN47,DEC!$P$23:$R$38,3,FALSE),"")
AM48: =IFERROR(_xlfn.RANK.EQ(AP48, $AP$3:$AP$150)+ COUNTIFS($AP$3:AP48, AP48) - 1,"") | AN48: =P36 | AO48: DEBTS | AP48: =IFERROR(VLOOKUP(AN48,DEC!$P$23:$R$38,3,FALSE),"")
AM49: =IFERROR(_xlfn.RANK.EQ(AP49, $AP$3:$AP$150)+ COUNTIFS($AP$3:AP49, AP49) - 1,"") | AN49: =P37 | AO49: SAVINGS | AP49: =IFERROR(VLOOKUP(AN49,DEC!$P$23:$R$38,3,FALSE),"")
AM50: =IFERROR(_xlfn.RANK.EQ(AP50, $AP$3:$AP$150)+ COUNTIFS($AP$3:AP50, AP50) - 1,"") | AN50: =U23 | AO50: SAVINGS | AP50: =IFERROR(VLOOKUP(AN50,DEC!$U$23:$W$38,3,FALSE),"")
AM51: =IFERROR(_xlfn.RANK.EQ(AP51, $AP$3:$AP$150)+ COUNTIFS($AP$3:AP51, AP51) - 1,"") | AN51: =U24 | AO51: SAVINGS | AP51: =IFERROR(VLOOKUP(AN51,DEC!$U$23:$W$38,3,FALSE),"")
AM52: =IFERROR(_xlfn.RANK.EQ(AP52, $AP$3:$AP$150)+ COUNTIFS($AP$3:AP52, AP52) - 1,"") | AN52: =U25 | AO52: SAVINGS | AP52: =IFERROR(VLOOKUP(AN52,DEC!$U$23:$W$38,3,FALSE),"")
AM53: =IFERROR(_xlfn.RANK.EQ(AP53, $AP$3:$AP$150)+ COUNTIFS($AP$3:AP53, AP53) - 1,"") | AN53: =U26 | AO53: SAVINGS | AP53: =IFERROR(VLOOKUP(AN53,DEC!$U$23:$W$38,3,FALSE),"")
AM54: =IFERROR(_xlfn.RANK.EQ(AP54, $AP$3:$AP$150)+ COUNTIFS($AP$3:AP54, AP54) - 1,"") | AN54: =U27 | AO54: SAVINGS | AP54: =IFERROR(VLOOKUP(AN54,DEC!$U$23:$W$38,3,FALSE),"")
AM55: =IFERROR(_xlfn.RANK.EQ(AP55, $AP$3:$AP$150)+ COUNTIFS($AP$3:AP55, AP55) - 1,"") | AN55: =U28 | AO55: SAVINGS | AP55: =IFERROR(VLOOKUP(AN55,DEC!$U$23:$W$38,3,FALSE),"")
AM56: =IFERROR(_xlfn.RANK.EQ(AP56, $AP$3:$AP$150)+ COUNTIFS($AP$3:AP56, AP56) - 1,"") | AN56: =U29 | AO56: SAVINGS | AP56: =IFERROR(VLOOKUP(AN56,DEC!$U$23:$W$38,3,FALSE),"")
AM57: =IFERROR(_xlfn.RANK.EQ(AP57, $AP$3:$AP$150)+ COUNTIFS($AP$3:AP57, AP57) - 1,"") | AN57: =U30 | AO57: SAVINGS | AP57: =IFERROR(VLOOKUP(AN57,DEC!$U$23:$W$38,3,FALSE),"")
AM58: =IFERROR(_xlfn.RANK.EQ(AP58, $AP$3:$AP$150)+ COUNTIFS($AP$3:AP58, AP58) - 1,"") | AN58: =U31 | AO58: SAVINGS | AP58: =IFERROR(VLOOKUP(AN58,DEC!$U$23:$W$38,3,FALSE),"")
AM59: =IFERROR(_xlfn.RANK.EQ(AP59, $AP$3:$AP$150)+ COUNTIFS($AP$3:AP59, AP59) - 1,"") | AN59: =U32 | AO59: SAVINGS | AP59: =IFERROR(VLOOKUP(AN59,DEC!$U$23:$W$38,3,FALSE),"")
AM60: =IFERROR(_xlfn.RANK.EQ(AP60, $AP$3:$AP$150)+ COUNTIFS($AP$3:AP60, AP60) - 1,"") | AN60: =U33 | AO60: SAVINGS | AP60: =IFERROR(VLOOKUP(AN60,DEC!$U$23:$W$38,3,FALSE),"")
AM61: =IFERROR(_xlfn.RANK.EQ(AP61, $AP$3:$AP$150)+ COUNTIFS($AP$3:AP61, AP61) - 1,"") | AN61: =U34 | AO61: SAVINGS | AP61: =IFERROR(VLOOKUP(AN61,DEC!$U$23:$W$38,3,FALSE),"")
... AM65: =IFERROR(_xlfn.RANK.EQ(AP65, $AP$3:$AP$150)+ COUNTIFS($AP$3:AP65, AP65) - 1,"") | AN65: =U38 | AO65: SAVINGS | AP65: =IFERROR(VLOOKUP(AN65,DEC!$U$23:$W$38,3,FALSE),"")
